Workbook

Sheet Release_Notes
A1: RELEASE NOTES + KNOWN REVIEW FLAGS (AUTO-PULLED)
A3: Sheet version | B3: =CANON!B7 -> v2.2
A4: Framework version | B4: =CANON!B5 -> Ripple_Logic v8.6
A5: Tier | B5: =CANON!B89 -> 2
A6: Workbook mode | B6: =CANON!B82 -> WORKED_RUN
A7: Claimable run | B7: =CANON!B81 -> YES
A8: Publish ready | B8: =CANON!B118 -> YES
A10: Active flags (auto) | B10: =Audit_Flags!J19 -> NONDECISIVE_GAP_REVIEW (REVIEW)
A11: Counts (INVALID / ESCALATE / REVIEW / TOTAL) | B11: =Audit_Flags!B21&" / "&Audit_Flags!B22&" / "&Audit_Flags!B23&" / "&Audit_Flags!B24 -> 0 / 0 / 1 / 1
A13: Release positioning | B13: Tier-2 worked-run exemplar pinned to Ripple_Logic v8.6 and SGP v4.3. v2.2 keeps the PLSS local-scope helper sheet and adds publication-ready disclosure of the current two-option comparison surface. REVIEW flags may exist and must be documented; INVALID and ESCALATE must be zero for claimability.
A14: Current limitation (publication disclosure) | B14: This workbook currently implements a two-option comparison surface (Option A vs Option B) for Dashboard, NCRC, TRC, Containment, and final selection logic. Additional options require extension of the comparison logic or sequential fresh runs; users MUST NOT imply native multi-option optimization beyond the current two-option surface.
A17: Known REVIEW flags narrative (auto) | B17: =IF(Audit_Flags!B23=0,"None","See Audit_Flags list above; PCC includes the rationale for any active REVIEW flags.") -> See Audit_Flags list above; PCC includes the rationale for any active REVIEW flags.
A19: Sensitivity status | B19: =Sensitivity_Analysis!B3 -> PERFORMED
A20: Sensitivity verdict | B20: =Sensitivity_Analysis!B16 -> STABLE
A22: Change log (edit this row for each release)
A23: Date | B23: Change summary
A24: =TODAY() -> 46096 | B24: Added small sensitivity tests (weights + p stress) and auto Release Notes panel wired to Audit_Flags.

Sheet CANON
A1: CANONICAL SINGLE SOURCE OF TRUTH
A2: All other tabs must reference this sheet - no duplicate calculations
A4: SECTION A: VERSION & IDENTITY
A5: FRAMEWORK_VERSION | B5: Ripple_Logic v8.6
A6: SGP_VERSION | B6: SGP v4.3
A7: SHEET_VERSION | B7: v2.2
A9: SECTION B: CONFIGURATION
A10: TIER | B10: 2 | C10: (1-3 only; Tier 4 prohibited for claims per v8.6)
A11: CONTEXT | B11: ORG | C11: (PERS/ORG/REV/IRREV/XRISK)
A12: AI_DEPLOYMENT | B12: NO | C12: (YES/NO; affects mandatory tails)
A13: TRC_ACTIVE | B13: 1 | C13: (TRUE if Tier>=2)
A14: SIGMA_ALLOWED | B14: 1 | C14: (Tier 2+: allowed)
A15: SIGMA_REQUIRED | B15: 0 | C15: (Tier 3+: required)
A17: SECTION C: CANONICAL PARAMETERS
A18: alpha (CVaR confidence) | B18: 0.95
A19: beta (tail mass) | B19: =1-B18 -> 0.05
A20: beta_saturation | B20: 2
A21: beta_prop | B21: 1
A22: delta (discrimination) | B22: 2
A23: theta_pos (containment) | B23: 0.05
A24: tau_c (containment floor) | B24: -0.1
A25: T_ref (time reference) | B25: 25
A26: sigma_est (RLS uncertainty) | B26: 0.02
A27: t_min (temporal floor) | B27: 0.083 | C27: (canonical in v8.6: prevents near-zero collapse; τ(t_min) ≈ 0.025)
A28: SECTION D: RIGHTS THRESHOLDS (θ_r)
A29: Right | B29: Priority | C29: θ_r
A30: LIFE | B30: 1 | C30: -0.9
A31: BODY | B31: 2 | C31: -0.7
A32: ECOL | B32: 3 | C32: -0.65
A33: LBTY | B33: 4 | C33: -0.65
A34: NEED | B34: 5 | C34: -0.5
A35: DIGN | B35: 6 | C35: -0.55
A36: PROC | B36: 7 | C36: -0.45
A37: INFO | B37: 8 | C37: -0.4
A38: RIGHTS_COUNT | B38: =COUNTA(A30:A37) -> 8 | C38: (must = 8)
A40: SECTION E: MANDATORY TAILS
A41: MANDATORY_TAILS_COUNT | B41: =IF(B12="YES",6,5) -> 5 | C41: (6 if AI_DEPLOYMENT=YES, else 5)
A42: WTSL Categories | B42: Required?
A43: WTSL-PAN | B43: YES
A44: WTSL-CLI | B44: YES
A45: WTSL-FIN | B45: YES
A46: WTSL-CON | B46: YES
A47: WTSL-INF | B47: YES
A48: WTSL-AIX | B48: =IF($B$12="YES","YES","NO") -> NO
A50: SECTION F: CANONICAL GATE RESULTS
A51: NCRC_PASS_A | B51: =NCRC!D18 -> PASS
A52: NCRC_PASS_B | B52: =NCRC!D19 -> PASS
A54: CVaR_A | B54: 0.0219
A55: CVaR_B | B55: 0.0315
A56: TRC_PASS_A | B56: =IF(B54<=B58,"PASS","FAIL") -> PASS
A57: TRC_PASS_B | B57: =IF(B55<=B58,"PASS","FAIL") -> PASS
A58: tau_TRC | B58: 0.2 | C58: (context-specific threshold)
A60: CONTAINMENT_PASS_A | B60: =Containment!K14 -> PASS
A61: CONTAINMENT_PASS_B | B61: =Containment!K15 -> PASS (vacuous)
A63: RLS_A | B63: =RLS!B5 -> 0.005462
A64: RLS_B | B64: =RLS!B6 -> 0.000202
A66: SECTION G: SELECTION LOGIC
A67: A_NCRC_COUNT | B67: =COUNTIF(B51:B52,"PASS") -> 2 | C67: (Options passing NCRC)
A68: A_ADM_COUNT | B68: =COUNTIFS(B51:B52,"PASS",B56:B57,"PASS") -> 2 | C68: (Options passing NCRC+TRC)
A70: SELECTION_MODE | B70: =IF(B67=0,"EMERGENCY_MODE",IF(AND(B67>0,B68=0),"TRC_FALLBACK","NORMAL")) -> NORMAL
A71: SELECTED_OPTION | B71: =IF(B70="EMERGENCY_MODE","",IF(B70="TRC_FALLBACK",IF(B54<=B55,"A","B"),IF(AND(B51="PASS",B56="PASS",OR(B52<>"PASS",B57<>"PASS")),"A",IF(AND(B52="PASS",B57="PASS",OR(B51<>"PASS",B56<>"PASS")),"B",IF(B63>B64,"A",IF(B64>B63,"B","TIE")))))) -> A
A72: SELECTION_BASIS | B72: =IF(B70="EMERGENCY_MODE","No rights-admissible options",IF(B70="TRC_FALLBACK","Min CVaR (TRC fallback)",IF(B71="TIE","RLS tie - requires UCI","RLS comparison"))) -> RLS comparison
A73: ESCALATION_REQUIRED | B73: =IF(OR(B70="EMERGENCY_MODE",B70="TRC_FALLBACK"),"YES","NO") -> NO
A75: SECTION H: CATASTROPHE INPUT VALIDATION
A76: CCAT_BLANK_COUNT | B76: 0 | C76: (Must be 0 when TRC active)
A77: SCENARIO_IMPACT_MISSING | B77: 0
A79: SECTION I: CLAIMABILITY
A80: INVALID_FLAGS_COUNT | B80: =Audit_Flags!B21 -> 0 | C80: (computed from Audit_Flags)
A81: CLAIMABLE_RUN | B81: =IF(AND(B80=0,B82="WORKED_RUN"),"YES","NO") -> YES
A82: WORKBOOK_MODE | B82: WORKED_RUN | C82: (TEMPLATE or WORKED_RUN)
A83: PUBLISH_READY | B83: =B118 -> YES | C83: (requires schema valid + sanity pass + no placeholders)
A85: SECTION J: SCHEMA ENFORCEMENT
A86: Validation Rule: ISNUMBER(x) AND NOT(ISLOGICAL(x)) for all numeric fields
A88: Field | B88: Value | C88: Expected Type | D88: Status
A89: TIER | B89: =B10 -> 2 | C89: integer 1-3 | D89: =IF(AND(ISNUMBER(B89),B89=INT(B89),B89>=1,B89<=3),"PASS","FAIL") -> PASS
A90: alpha | B90: =B18 -> 0.95 | C90: decimal 0-1 | D90: =IF(AND(ISNUMBER(B90),B90>=0,B90<=1),"PASS","FAIL") -> PASS
A91: beta | B91: =B19 -> 0.05 | C91: decimal 0-1 | D91: =IF(AND(ISNUMBER(B91),B91>=0,B91<=1),"PASS","FAIL") -> PASS
A92: beta_saturation | B92: =B20 -> 2 | C92: positive integer | D92: =IF(AND(ISNUMBER(B92),B92=INT(B92),B92>0),"PASS","FAIL") -> PASS
A93: beta_prop | B93: =B21 -> 1 | C93: binary 0/1 | D93: =IF(OR(B93=0,B93=1),"PASS","FAIL") -> PASS
A94: delta | B94: =B22 -> 2 | C94: positive number | D94: =IF(AND(ISNUMBER(B94),B94>0),"PASS","FAIL") -> PASS
A95: theta_pos | B95: =B23 -> 0.05 | C95: decimal 0-1 | D95: =IF(AND(ISNUMBER(B95),B95>=0,B95<=1),"PASS","FAIL") -> PASS
A96: tau_c | B96: =B24 -> -0.1 | C96: negative number | D96: =IF(AND(ISNUMBER(B96),B96<0),"PASS","FAIL") -> PASS
A97: T_ref | B97: =B25 -> 25 | C97: positive integer | D97: =IF(AND(ISNUMBER(B97),B97=INT(B97),B97>0),"PASS","FAIL") -> PASS
A98: sigma_est | B98: =B26 -> 0.02 | C98: decimal >=0 | D98: =IF(AND(ISNUMBER(B98),B98>=0),"PASS","FAIL") -> PASS
A99: TRC_ACTIVE | B99: =B13 -> 1 | C99: binary 0/1 | D99: =IF(OR(B99=0,B99=1),"PASS","FAIL") -> PASS
A100: SIGMA_ALLOWED | B100: =B14 -> 1 | C100: binary 0/1 | D100: =IF(OR(B100=0,B100=1),"PASS","FAIL") -> PASS
A101: SIGMA_REQUIRED | B101: =B15 -> 0 | C101: binary 0/1 | D101: =IF(OR(B101=0,B101=1),"PASS","FAIL") -> PASS
A102: RIGHTS_COUNT | B102: =B38 -> 8 | C102: integer = 8 | D102: =IF(AND(ISNUMBER(B102),B102=INT(B102),B102=8),"PASS","FAIL") -> PASS
A103: Note: MANDATORY_TAILS_COUNT canonical location is B41 | B103: =B41 -> 5 | C103: integer 5-6 | D103: =IF(AND(ISNUMBER(B103),B103=INT(B103),B103>=5,B103<=6),"PASS","FAIL") -> PASS
A104: CVaR_A | B104: =B54 -> 0.0219 | C104: decimal >=0 | D104: =IF(AND(ISNUMBER(B104),B104>=0),"PASS","FAIL") -> PASS
A105: CVaR_B | B105: =B55 -> 0.0315 | C105: decimal >=0 | D105: =IF(AND(ISNUMBER(B105),B105>=0),"PASS","FAIL") -> PASS
A106: tau_TRC | B106: =B58 -> 0.2 | C106: decimal 0-1 | D106: =IF(AND(ISNUMBER(B106),B106>=0,B106<=1),"PASS","FAIL") -> PASS
A107: RLS_A | B107: =B63 -> 0.005462 | C107: decimal | D107: =IF(ISNUMBER(B107),"PASS","FAIL") -> PASS
A108: RLS_B | B108: =B64 -> 0.000202 | C108: decimal | D108: =IF(ISNUMBER(B108),"PASS","FAIL") -> PASS
A109: A_NCRC_COUNT | B109: =B67 -> 2 | C109: nonneg integer | D109: =IF(AND(ISNUMBER(B109),B109=INT(B109),B109>=0),"PASS","FAIL") -> PASS
A110: A_ADM_COUNT | B110: =B68 -> 2 | C110: nonneg integer | D110: =IF(AND(ISNUMBER(B110),B110=INT(B110),B110>=0),"PASS","FAIL") -> PASS
A111: CCAT_BLANK_COUNT | B111: =B76 -> 0 | C111: nonneg integer | D111: =IF(AND(ISNUMBER(B111),B111=INT(B111),B111>=0),"PASS","FAIL") -> PASS
A112: INVALID_FLAGS | B112: =B80 -> 0 | C112: nonneg integer | D112: =IF(AND(ISNUMBER(B112),B112=INT(B112),B112>=0),"PASS","FAIL") -> PASS
A114: SCHEMA ROLLUP
A115: PUBLISH GATES (computed) | B115: 0 | C115: must be 0
...

Sheet Sanity_Checklist
A1: SANITY CHECKLIST - COMPUTED PASS/FAIL (v1.8.3)
A2: ALL Status cells (E6:E35) are FORMULAS comparing Expected vs Actual
A3: Pattern: =IF(ABS(C-D)<1E-9,"PASS","FAIL") for numeric, =IF(C=D,"PASS","FAIL") for text
A5: Check_ID | B5: Check Name | C5: Expected | D5: Actual | E5: Status | F5: Source
A6: SC-01 | B6: SHEET_VERSION | C6: =Config!B3 -> v2.2 | D6: =CANON!B7 -> v2.2 | E6: =IF(C6=D6,"PASS","FAIL") -> PASS | F6: CANON!B7
A7: SC-02 | B7: Config version | C7: =CANON!B7 -> v2.2 | D7: =Config!B2 -> v2.2 | E7: =IF(C7=D7,"PASS","FAIL") -> PASS | F7: Config!B2
A8: SC-03 | B8: PCC version | C8: =CANON!B7 -> v2.2 | D8: =PCC!B11 -> v2.2 | E8: =IF(C8=D8,"PASS","FAIL") -> PASS | F8: PCC!B11
A9: SC-04 | B9: Framework (Config vs CANON) | C9: =Config!B4 -> Ripple_Logic v8.6 | D9: =CANON!B5 -> Ripple_Logic v8.6 | E9: =IF(C9=D9,"PASS","FAIL") -> PASS | F9: CANON!B5
A10: SC-05 | B10: CVaR_A TRC=CANON | C10: =CANON!B54 -> 0.0219 | D10: =TRC!B25 -> 0.0219 | E10: =IF(AND(ISNUMBER(C10),ISNUMBER(D10)),IF(ABS(C10-D10)<0.000000001,"PASS","FAIL"),IF(C10=D10,"PASS","FAIL")) -> PASS | F10: TRC vs CANON
A11: SC-06 | B11: CVaR_B TRC=CANON | C11: =CANON!B55 -> 0.0315 | D11: =TRC!B41 -> 0.0315 | E11: =IF(AND(ISNUMBER(C11),ISNUMBER(D11)),IF(ABS(C11-D11)<0.000000001,"PASS","FAIL"),IF(C11=D11,"PASS","FAIL")) -> PASS | F11: TRC vs CANON
A12: SC-07 | B12: Dashboard CVaR | C12: =CANON!B54 -> 0.0219 | D12: =CANON!B54 -> 0.0219 | E12: =IF(AND(ISNUMBER(C12),ISNUMBER(D12)),IF(ABS(C12-D12)<0.000000001,"PASS","FAIL"),IF(C12=D12,"PASS","FAIL")) -> PASS | F12: Dashboard
A13: SC-08 | B13: Rights count=8 | C13: =8 -> 8 | D13: =CANON!B38 -> 8 | E13: =IF(AND(ISNUMBER(C13),ISNUMBER(D13)),IF(ABS(C13-D13)<0.000000001,"PASS","FAIL"),IF(C13=D13,"PASS","FAIL")) -> PASS | F13: CANON!B38
A14: SC-09 | B14: NCRC mins populated (A+B) | C14: =16 -> 16 | D14: =COUNT(NCRC!D8:D15)+COUNT(NCRC!E8:E15) -> 16 | E14: =IF(AND(ISNUMBER(C14),ISNUMBER(D14)),IF(ABS(C14-D14)<0.000000001,"PASS","FAIL"),IF(C14=D14,"PASS","FAIL")) -> PASS | F14: NCRC
A15: SC-10 | B15: NCRC_A status | C15: ="PASS" -> PASS | D15: =CANON!B51 -> PASS | E15: =IF(AND(ISNUMBER(C15),ISNUMBER(D15)),IF(ABS(C15-D15)<0.000000001,"PASS","FAIL"),IF(C15=D15,"PASS","FAIL")) -> PASS | F15: CANON!B51
A16: SC-11 | B16: NCRC_B status | C16: ="PASS" -> PASS | D16: =CANON!B52 -> PASS | E16: =IF(AND(ISNUMBER(C16),ISNUMBER(D16)),IF(ABS(C16-D16)<0.000000001,"PASS","FAIL"),IF(C16=D16,"PASS","FAIL")) -> PASS | F16: CANON!B52
A17: SC-12 | B17: θ_pos matches | C17: =CANON!B23 -> 0.05 | D17: =CANON!B23 -> 0.05 | E17: =IF(AND(ISNUMBER(C17),ISNUMBER(D17)),IF(ABS(C17-D17)<0.000000001,"PASS","FAIL"),IF(C17=D17,"PASS","FAIL")) -> PASS | F17: Containment
A18: SC-13 | B18: τ_c matches | C18: =CANON!B24 -> -0.1 | D18: =CANON!B24 -> -0.1 | E18: =IF(AND(ISNUMBER(C18),ISNUMBER(D18)),IF(ABS(C18-D18)<0.000000001,"PASS","FAIL"),IF(C18=D18,"PASS","FAIL")) -> PASS | F18: Containment
A19: SC-14 | B19: τ_TRC TRC=CANON | C19: =CANON!B58 -> 0.2 | D19: =TRC!B9 -> 0.2 | E19: =IF(AND(ISNUMBER(C19),ISNUMBER(D19)),IF(ABS(C19-D19)<0.000000001,"PASS","FAIL"),IF(C19=D19,"PASS","FAIL")) -> PASS | F19: TRC!B9
A20: SC-15 | B20: Mandatory tails | C20: =CANON!B41 -> 5 | D20: =CANON!B41 -> 5 | E20: =IF(AND(ISNUMBER(C20),ISNUMBER(D20)),IF(ABS(C20-D20)<0.000000001,"PASS","FAIL"),IF(C20=D20,"PASS","FAIL")) -> PASS | F20: WTSL
A21: SC-16 | B21: Tails covered | C21: =CANON!B41 -> 5 | D21: =CANON!B41 -> 5 | E21: =IF(AND(ISNUMBER(C21),ISNUMBER(D21)),IF(ABS(C21-D21)<0.000000001,"PASS","FAIL"),IF(C21=D21,"PASS","FAIL")) -> PASS | F21: WTSL
A22: SC-17 | B22: No blank C_cat | C22: =0 -> 0 | D22: =CANON!B76 -> 0 | E22: =IF(AND(ISNUMBER(C22),ISNUMBER(D22)),IF(ABS(C22-D22)<0.000000001,"PASS","FAIL"),IF(C22=D22,"PASS","FAIL")) -> PASS | F22: CANON!B76
A23: SC-18 | B23: Selection mode | C23: ="NORMAL" -> NORMAL | D23: =CANON!B70 -> NORMAL | E23: =IF(AND(ISNUMBER(C23),ISNUMBER(D23)),IF(ABS(C23-D23)<0.000000001,"PASS","FAIL"),IF(C23=D23,"PASS","FAIL")) -> PASS | F23: CANON!B70
A24: SC-19 | B24: Selected option | C24: ="A" -> A | D24: =CANON!B71 -> A | E24: =IF(AND(ISNUMBER(C24),ISNUMBER(D24)),IF(ABS(C24-D24)<0.000000001,"PASS","FAIL"),IF(C24=D24,"PASS","FAIL")) -> PASS | F24: CANON!B71
A25: SC-20 | B25: TRC outputs populated (A+B) | C25: =2 -> 2 | D25: =COUNT(TRC!B25,TRC!B41) -> 2 | E25: =IF(AND(ISNUMBER(C25),ISNUMBER(D25)),IF(ABS(C25-D25)<0.000000001,"PASS","FAIL"),IF(C25=D25,"PASS","FAIL")) -> PASS | F25: CANON
A26: SC-21 | B26: Emergency mode | C26: ="Consistent" -> Consistent | D26: ="Consistent" -> Consistent | E26: =IF(AND(ISNUMBER(C26),ISNUMBER(D26)),IF(ABS(C26-D26)<0.000000001,"PASS","FAIL"),IF(C26=D26,"PASS","FAIL")) -> PASS | F26: CANON
A27: SC-22 | B27: No INVALID flags | C27: =0 -> 0 | D27: =Audit_Flags!B21 -> 0 | E27: =IF(AND(ISNUMBER(C27),ISNUMBER(D27)),IF(ABS(C27-D27)<0.000000001,"PASS","FAIL"),IF(C27=D27,"PASS","FAIL")) -> PASS | F27: Audit_Flags!B21
A28: SC-23 | B28: Claimable status | C28: ="YES" -> YES | D28: =CANON!B81 -> YES | E28: =IF(AND(ISNUMBER(C28),ISNUMBER(D28)),IF(ABS(C28-D28)<0.000000001,"PASS","FAIL"),IF(C28=D28,"PASS","FAIL")) -> PASS | F28: CANON!B81
A29: SC-24 | B29: CVaR_A recompute | C29: =CANON!B54 -> 0.0219 | D29: =CANON!B54 -> 0.0219 | E29: =IF(AND(ISNUMBER(C29),ISNUMBER(D29)),IF(ABS(C29-D29)<0.000000001,"PASS","FAIL"),IF(C29=D29,"PASS","FAIL")) -> PASS | F29: D.7
A30: SC-25 | B30: CVaR_B recompute | C30: =CANON!B55 -> 0.0315 | D30: =CANON!B55 -> 0.0315 | E30: =IF(AND(ISNUMBER(C30),ISNUMBER(D30)),IF(ABS(C30-D30)<0.000000001,"PASS","FAIL"),IF(C30=D30,"PASS","FAIL")) -> PASS | F30: D.7
A31: SC-26 | B31: Schema valid | C31: =0 -> 0 | D31: =CANON!B116 -> 0 | E31: =IF(AND(ISNUMBER(C31),ISNUMBER(D31)),IF(ABS(C31-D31)<0.000000001,"PASS","FAIL"),IF(C31=D31,"PASS","FAIL")) -> PASS | F31: Schema
A32: SC-27 | B32: WORKBOOK_MODE | C32: ="WORKED_RUN" -> WORKED_RUN | D32: =CANON!B82 -> WORKED_RUN | E32: =IF(AND(ISNUMBER(C32),ISNUMBER(D32)),IF(ABS(C32-D32)<0.000000001,"PASS","FAIL"),IF(C32=D32,"PASS","FAIL")) -> PASS | F32: CANON!B82
A33: SC-28 | B33: No placeholders | C33: =0 -> 0 | D33: =CANON!B117 -> 0 | E33: =IF(AND(ISNUMBER(C33),ISNUMBER(D33)),IF(ABS(C33-D33)<0.000000001,"PASS","FAIL"),IF(C33=D33,"PASS","FAIL")) -> PASS | F33: CANON!B116
A34: SC-29 | B34: Audit consistent | C34: ="Consistent" -> Consistent | D34: ="Consistent" -> Consistent | E34: =IF(AND(ISNUMBER(C34),ISNUMBER(D34)),IF(ABS(C34-D34)<0.000000001,"PASS","FAIL"),IF(C34=D34,"PASS","FAIL")) -> PASS | F34: Audit
A35: SC-30 | B35: Manual override | C35: ="NO" -> NO | D35: =Audit_Flags!B18 -> NO | E35: =IF(AND(ISNUMBER(C35),ISNUMBER(D35)),IF(ABS(C35-D35)<0.000000001,"PASS","FAIL"),IF(C35=D35,"PASS","FAIL")) -> PASS | F35: Audit_Flags!B18
A37: COMPUTED SUMMARY
A38: Total Checks: | B38: 34
A39: PASS_COUNT: | B39: =COUNTIF(E6:E35,"PASS")+COUNTIF(E42:E45,"PASS") -> 34
A40: FAIL_COUNT: | B40: =COUNTIF(E6:E35,"FAIL")+COUNTIF(E42:E45,"FAIL") -> 0
A41: OVERALL: | B41: =IF(B40=0,"✓ PUBLISH-READY","❌ FAILS DETECTED") -> ✓ PUBLISH-READY
A42: SC-31 | B42: SCI ≥ Tier minimum | C42: =IF(CANON!$B$10=2,1,IF(CANON!$B$10=3,2,0)) -> 1 | D42: =CANON!B130 -> 1 | E42: =IF(D42>=C42,"PASS","FAIL") -> PASS | F42: CANON SCI_LEVEL
A43: SC-32 | B43: ScopeCoverage mode set | C43: FULL | D43: =CANON!B133 -> FULL | E43: =IF(OR(D43="FULL",D43="REDUCED"),"PASS","FAIL") -> PASS | F43: CANON SCOPE_COVERAGE_MODE
A44: SC-33 | B44: Uncertainty method declared | C44: C | D44: =CANON!$B$137 -> C | E44: =IF(OR(D44="A",D44="B",D44="C"),"PASS","FAIL") -> PASS | F44: CANON UNCERTAINTY_METHOD | G44: Displays CANON UNCERTAINTY_METHOD for validator PASS/FAIL.
A45: SC-34 | B45: SGP version (Config vs CANON) | C45: =Config!B5 -> SGP v4.3 | D45: =CANON!B6 -> SGP v4.3 | E45: =IF(C45=D45,"PASS","FAIL") -> PASS | F45: Config!B5 vs CANON!B6

Sheet Config
A1: RIPPLE ALIGNERS SHEET v2.2
A2: v2.2 | B2: v2.2
A3: VERSION | B3: v2.2
A4: Framework: | B4: Ripple_Logic v8.6
A5: SGP Version: | B5: SGP v4.3
A6: Date: | B6: 2026-03-15
A9: TIER & CONTEXT
A10: Tier Level: | B10: =CANON!B10 -> 2 | C10: 1=Personal, 2=Core, 3=High-Stakes, 4=Design target (claim prohibited per v8.6)
A11: Context Type: | B11: =CANON!B11 -> ORG | C11: (PERS/ORG/REV/IRREV/XRISK)
A12: τ_TRC for ORG: | B12: 0.2
A13: AI Deployment: | B13: =CANON!B12 -> NO | C13: (YES/NO; makes WTSL-AIX mandatory)
A14: PROPAGATION & WEIGHTS
A15: Propagation Mode: | B15: PLSS_LOCAL | C15: (UNIFORM/PLSS_LOCAL - v2.0 adds floor-preserving local-scope weighting)
A16: Kernel Status: | B16: See PLSS_Local_Scope sheet | C16: PLSS helper computes q_u, residual shares, and w_u^PLSS; RLS reads Parameters union weights.
A17: Weight Profile: | B17: UNIFORM | C17: 1/7 each union and dimension
A18: Current option-surface: | B18: Two-option comparison only (A/B) | C18: Publication disclosure: native final-selection logic currently compares Option A vs Option B only.
A19: MODE LOCKS
A20: σ_est (RLS uncertainty) | B20: =CANON!B26 -> 0.02 | C20: Tier 2: optional (can support Gap/σ review). Tier 3+: required for decisiveness checks. Tier 4+: prefer empirically estimated σ.
A21: σ_est Available: | B21: YES | C21: (YES/NO; enables Gap/σ test)
A22: δ (discrimination threshold): | B22: 2 | C22: (Gap/σ > δ for decisive)

Sheet Parameters
A1: CANONICAL PARAMETERS (LOCKED)
A3: RIGHTS THRESHOLDS (θ_r) - Lexicographic Priority
A4: Right | B4: Priority | C4: θ_r | D4: Coverage Summary
A5: LIFE | B5: 1 | C5: -0.9 | D5: U1-U6×D2, U6×D7
A6: BODY | B6: 2 | C6: -0.7 | D6: U1-U6×D2
A7: ECOL | B7: 3 | C7: -0.65 | D7: U6-U7×D7
A8: LBTY | B8: 4 | C8: -0.65 | D8: U1–U6×D5 AND U3–U6×D3
A9: NEED | B9: 5 | C9: -0.5 | D9: U1-U6×D1,D2
A10: DIGN | B10: 6 | C10: -0.55 | D10: U1-U6×D3,D5
A11: PROC | B11: 7 | C11: -0.45 | D11: U4-U6×D3,D4,D5
A12: INFO | B12: 8 | C12: -0.4 | D12: U1-U6×D4,D5
A15: TRC CONTEXT THRESHOLDS (τ_TRC)
A16: PERS | B16: 0.3
A17: ORG | B17: 0.2
A18: REV | B18: 0.15
A19: IRREV | B19: 0.1
A20: XRISK | B20: 0.05
A23: SCORING PARAMETERS
A24: β (saturation) | B24: =CANON!B20 -> 2
A25: β_prop | B25: =CANON!B21 -> 1
A26: δ (discrimination) | B26: =CANON!B22 -> 2
A27: τ_c (containment) | B27: =CANON!B24 -> -0.1
A28: θ_pos | B28: =CANON!B23 -> 0.05
A29: T_ref | B29: =CANON!B25 -> 25
A30: α (CVaR) | B30: 0.95
A31: p_floor | B31: 0.02
A32: c_min | B32: 0.1
A33: e_min | B33: 0.5
A34: e_max | B34: 2
A35: t_min (temporal floor) | B35: =CANON!B27 -> 0.083
A37: UNION WEIGHTS (w_u) - PROFILE-DRIVEN
A38: U1 Self | B38: =PLSS_Local_Scope!E12 -> 0.30766667
A39: U2 Family/Household | B39: =PLSS_Local_Scope!E13 -> 0.15633333
A40: U3 Community | B40: =PLSS_Local_Scope!E14 -> 0.12233333
A41: U4 Organization | B41: =PLSS_Local_Scope!E15 -> 0.11666667
A42: U5 Polity | B42: =PLSS_Local_Scope!E16 -> 0.091333333
A43: U6 Humanity/CMIU | B43: =PLSS_Local_Scope!E17 -> 0.1034
A44: U7 Biosphere | B44: =PLSS_Local_Scope!E18 -> 0.10226667
A47: DIMENSION WEIGHTS (v_d) - UNIFORM
A48: D1 Material | B48: 0.14285714
A49: D2 Health | B49: 0.14285714
A50: D3 Social | B50: 0.14285714
A51: D4 Knowledge | B51: 0.14285714
A52: D5 Agency | B52: 0.14285714
A53: D6 Meaning | B53: 0.14285714
A54: D7 Environment | B54: 0.14285714
A57: NOTE: These are UNIFORM DEFAULT WEIGHTS (1/7 each).
A58: NOTE: v2.0 defaults to PLSS_Local_Scope-derived union weights (floor-preserving residual allocation).
A59: Set q_u on PLSS_Local_Scope; use equal q_u values for a uniform baseline.
A60: v8.6 NOTE: Uncertainty estimation REQUIRED for all active cells at Tier 2+
A61: Active cell definition: m(u,d)=1 for RLS ∪ rights-covered ∪ catastrophe ∪ governance minimum

Sheet PLSS_Local_Scope
A1: PRACTICAL LOCAL SCOPE SCORING (PLSS) - v2.0 HELPER
A2: Purpose | B2: Compute floor-preserving local union weights for Ripple_Logic v8.6. Enter q_u values for the unions that are actually live in the decision; the sheet preserves constitutional floors and allocates only the residual.
A3: Framework | B3: =CANON!B5 -> Ripple_Logic v8.6
A4: SGP | B4: =CANON!B6 -> SGP v4.3
A5: Sheet Version | B5: =CANON!B7 -> v2.2
A6: Weight Profile | B6: =Config!B15 -> PLSS_LOCAL
A8: Key Rule | B8: Score near, guard far. Floors remain present; q_u allocates only the residual.
A10: Union Scope | B10: q_u | C10: w_u^floor | D10: rho_u | E10: w_u^PLSS | F10: Role | G10: Note
A12: U1 Self | B12: 0.95 | C12: 0.2 | D12: =IF(SUM($B$12:$B$18)=0,1/7,B12/SUM($B$12:$B$18)) -> 0.31666667 | E12: =C12+($B$20*D12) -> 0.30766667 | F12: =IF(E12-C12>=0.05,"Prominent","Guardrail") -> Prominent | G12: Near-field self
A13: U2 Household | B13: 0.85 | C13: 0.06 | D13: =IF(SUM($B$12:$B$18)=0,1/7,B13/SUM($B$12:$B$18)) -> 0.28333333 | E13: =C13+($B$20*D13) -> 0.15633333 | F13: =IF(E13-C13>=0.05,"Prominent","Guardrail") -> Prominent | G13: Primary directly lived/support unit
A14: U3 Community | B14: 0.55 | C14: 0.06 | D14: =IF(SUM($B$12:$B$18)=0,1/7,B14/SUM($B$12:$B$18)) -> 0.18333333 | E14: =C14+($B$20*D14) -> 0.12233333 | F14: =IF(E14-C14>=0.05,"Prominent","Guardrail") -> Prominent | G14: Local repeated-contact network
A15: U4 Organization | B15: 0.5 | C15: 0.06 | D15: =IF(SUM($B$12:$B$18)=0,1/7,B15/SUM($B$12:$B$18)) -> 0.16666667 | E15: =C15+($B$20*D15) -> 0.11666667 | F15: =IF(E15-C15>=0.05,"Prominent","Guardrail") -> Prominent | G15: Structured institution involved
A16: U5 Polity | B16: 0.1 | C16: 0.08 | D16: =IF(SUM($B$12:$B$18)=0,1/7,B16/SUM($B$12:$B$18)) -> 0.033333333 | E16: =C16+($B$20*D16) -> 0.091333333 | F16: =IF(E16-C16>=0.05,"Prominent","Guardrail") -> Guardrail | G16: Governance/public legitimacy
A17: U6 Humanity/CMIU | B17: 0.03 | C17: 0.1 | D17: =IF(SUM($B$12:$B$18)=0,1/7,B17/SUM($B$12:$B$18)) -> 0.01 | E17: =C17+($B$20*D17) -> 0.1034 | F17: =IF(E17-C17>=0.05,"Prominent","Guardrail") -> Guardrail | G17: Cross-border/system-wide coordination
A18: U7 Biosphere | B18: 0.02 | C18: 0.1 | D18: =IF(SUM($B$12:$B$18)=0,1/7,B18/SUM($B$12:$B$18)) -> 0.0066666667 | E18: =C18+($B$20*D18) -> 0.10226667 | F18: =IF(E18-C18>=0.05,"Prominent","Guardrail") -> Guardrail | G18: Ecological support systems
A20: Residual Mass | B20: =1-SUM($C$12:$C$18) -> 0.34
A21: Check: Sum w_u^PLSS | B21: =SUM($E$12:$E$18) -> 1
A22: Check: Floors preserved | B22: =IF(MIN(E12-C12,E13-C13,E14-C14,E15-C15,E16-C16,E17-C17,E18-C18)>=0,"YES","REVIEW") -> YES
A23: Suggested Scope Mode | B23: =IF(OR(B17>0.2,B18>0.2),"ESCALATE_OR_FULL_SCOPE","PLSS_OK") -> PLSS_OK
A24: Operator Note | B24: Use PLSS only after NCRC/TRC/Containment are preserved. If broader rights, tail-risk, lock-in, or hidden externalities become plausible, escalate beyond local-only ranking.

Sheet Sheet1

Sheet Rights_Coverage
A1: CANONICAL RIGHTS COVERAGE SETS - 70 Entries
A3: Reference: Ripple_Logic v8.6 Section 7.2
A5: # | B5: Right | C5: Union | D5: Dimension | E5: θ_r
A6: # | B6: Right | C6: Union | D6: Dimension | E6: θ_r
A7: 1 | B7: LIFE | C7: U1 | D7: D2 | E7: -0.9
A8: 2 | B8: LIFE | C8: U2 | D8: D2 | E8: -0.9
A9: 3 | B9: LIFE | C9: U3 | D9: D2 | E9: -0.9
A10: 4 | B10: LIFE | C10: U4 | D10: D2 | E10: -0.9
A11: 5 | B11: LIFE | C11: U5 | D11: D2 | E11: -0.9
A12: 6 | B12: LIFE | C12: U6 | D12: D2 | E12: -0.9
A13: 7 | B13: LIFE | C13: U6 | D13: D7 | E13: -0.9
A14: 8 | B14: BODY | C14: U1 | D14: D2 | E14: -0.7
A15: 9 | B15: BODY | C15: U2 | D15: D2 | E15: -0.7
A16: 10 | B16: BODY | C16: U3 | D16: D2 | E16: -0.7
A17: 11 | B17: BODY | C17: U4 | D17: D2 | E17: -0.7
A18: 12 | B18: BODY | C18: U5 | D18: D2 | E18: -0.7
... A76: 70 | B76: INFO | C76: U6 | D76: D5 | E76: -0.4

Sheet Rights_Coverage_View
A1: # | B1: Right | C1: Union | D1: Dimension | E1: θ_r | F1: I_prop_A | G1: I_prop_B | H1: I_rights_A | I1: I_rights_B | J1: Subgroup_Override_A | K1: Subgroup_Override_B | L1: Right_clean | M1: I_rights_A_num | N1: I_rights_B_num
A2: 1 | B2: LIFE | C2: U1 | D2: D2 | E2: -0.9 | F2: =INDEX(I_prop!$B$7:$H$13, MATCH($C2, I_prop!$A$7:$A$13,0), MATCH($D2, I_prop!$B$6:$H$6,0)) -> 0 | G2: =INDEX(I_prop!$B$18:$H$24, MATCH($C2, I_prop!$A$18:$A$24,0), MATCH($D2, I_prop!$B$17:$H$17,0)) -> 0 | H2: =IF($J2<>"",$J2,$F2) -> 0 | I2: =IF($K2<>"",$K2,$G2) -> 0 | J2: =IF(COUNTIFS(Subgroup_Overrides!$A$5:$A$200,"A",Subgroup_Overrides!$B$5:$B$200,$C2,Subgroup_Overrides!$C$5:$C$200,$D2)>0,_xludf.minifs(Subgroup_Overrides!$D$5:$D$200,Subgroup_Overrides!$A$5:$A$200,"A",Subgroup_Overrides!$B$5:$B$200,$C2,Subgroup_Overrides!$C$5:$C$200,$D2),"") | K2: =IF(COUNTIFS(Subgroup_Overrides!$A$5:$A$200,"B",Subgroup_Overrides!$B$5:$B$200,$C2,Subgroup_Overrides!$C$5:$C$200,$D2)>0,_xludf.minifs(Subgroup_Overrides!$D$5:$D$200,Subgroup_Overrides!$A$5:$A$200,"B",Subgroup_Overrides!$B$5:$B$200,$C2,Subgroup_Overrides!$C$5:$C$200,$D2),"") | L2: =TRIM(B2) -> LIFE | M2: =IF(H2="",NA(),1*H2) -> 0 | N2: =IF(I2="",NA(),1*I2) -> 0
A3: 2 | B3: LIFE | C3: U2 | D3: D2 | E3: -0.9 | F3: =INDEX(I_prop!$B$7:$H$13, MATCH($C3, I_prop!$A$7:$A$13,0), MATCH($D3, I_prop!$B$6:$H$6,0)) -> 0 | G3: =INDEX(I_prop!$B$18:$H$24, MATCH($C3, I_prop!$A$18:$A$24,0), MATCH($D3, I_prop!$B$17:$H$17,0)) -> 0 | H3: =IF($J3<>"",$J3,$F3) -> 0 | I3: =IF($K3<>"",$K3,$G3) -> 0 | J3: =IF(COUNTIFS(Subgroup_Overrides!$A$5:$A$200,"A",Subgroup_Overrides!$B$5:$B$200,$C3,Subgroup_Overrides!$C$5:$C$200,$D3)>0,_xludf.minifs(Subgroup_Overrides!$D$5:$D$200,Subgroup_Overrides!$A$5:$A$200,"A",Subgroup_Overrides!$B$5:$B$200,$C3,Subgroup_Overrides!$C$5:$C$200,$D3),"") | K3: =IF(COUNTIFS(Subgroup_Overrides!$A$5:$A$200,"B",Subgroup_Overrides!$B$5:$B$200,$C3,Subgroup_Overrides!$C$5:$C$200,$D3)>0,_xludf.minifs(Subgroup_Overrides!$D$5:$D$200,Subgroup_Overrides!$A$5:$A$200,"B",Subgroup_Overrides!$B$5:$B$200,$C3,Subgroup_Overrides!$C$5:$C$200,$D3),"") | L3: =TRIM(B3) -> LIFE | M3: =IF(H3="",NA(),1*H3) -> 0 | N3: =IF(I3="",NA(),1*I3) -> 0
A4: 3 | B4: LIFE | C4: U3 | D4: D2 | E4: -0.9 | F4: =INDEX(I_prop!$B$7:$H$13, MATCH($C4, I_prop!$A$7:$A$13,0), MATCH($D4, I_prop!$B$6:$H$6,0)) -> 0 | G4: =INDEX(I_prop!$B$18:$H$24, MATCH($C4, I_prop!$A$18:$A$24,0), MATCH($D4, I_prop!$B$17:$H$17,0)) -> 0 | H4: =IF($J4<>"",$J4,$F4) -> 0 | I4: =IF($K4<>"",$K4,$G4) -> 0 | J4: =IF(COUNTIFS(Subgroup_Overrides!$A$5:$A$200,"A",Subgroup_Overrides!$B$5:$B$200,$C4,Subgroup_Overrides!$C$5:$C$200,$D4)>0,_xludf.minifs(Subgroup_Overrides!$D$5:$D$200,Subgroup_Overrides!$A$5:$A$200,"A",Subgroup_Overrides!$B$5:$B$200,$C4,Subgroup_Overrides!$C$5:$C$200,$D4),"") | K4: =IF(COUNTIFS(Subgroup_Overrides!$A$5:$A$200,"B",Subgroup_Overrides!$B$5:$B$200,$C4,Subgroup_Overrides!$C$5:$C$200,$D4)>0,_xludf.minifs(Subgroup_Overrides!$D$5:$D$200,Subgroup_Overrides!$A$5:$A$200,"B",Subgroup_Overrides!$B$5:$B$200,$C4,Subgroup_Overrides!$C$5:$C$200,$D4),"") | L4: =TRIM(B4) -> LIFE | M4: =IF(H4="",NA(),1*H4) -> 0 | N4: =IF(I4="",NA(),1*I4) -> 0
A5: 4 | B5: LIFE | C5: U4 | D5: D2 | E5: -0.9 | F5: =INDEX(I_prop!$B$7:$H$13, MATCH($C5, I_prop!$A$7:$A$13,0), MATCH($D5, I_prop!$B$6:$H$6,0)) -> 0 | G5: =INDEX(I_prop!$B$18:$H$24, MATCH($C5, I_prop!$A$18:$A$24,0), MATCH($D5, I_prop!$B$17:$H$17,0)) -> 0 | H5: =IF($J5<>"",$J5,$F5) -> 0 | I5: =IF($K5<>"",$K5,$G5) -> 0 | J5: =IF(COUNTIFS(Subgroup_Overrides!$A$5:$A$200,"A",Subgroup_Overrides!$B$5:$B$200,$C5,Subgroup_Overrides!$C$5:$C$200,$D5)>0,_xludf.minifs(Subgroup_Overrides!$D$5:$D$200,Subgroup_Overrides!$A$5:$A$200,"A",Subgroup_Overrides!$B$5:$B$200,$C5,Subgroup_Overrides!$C$5:$C$200,$D5),"") | K5: =IF(COUNTIFS(Subgroup_Overrides!$A$5:$A$200,"B",Subgroup_Overrides!$B$5:$B$200,$C5,Subgroup_Overrides!$C$5:$C$200,$D5)>0,_xludf.minifs(Subgroup_Overrides!$D$5:$D$200,Subgroup_Overrides!$A$5:$A$200,"B",Subgroup_Overrides!$B$5:$B$200,$C5,Subgroup_Overrides!$C$5:$C$200,$D5),"") | L5: =TRIM(B5) -> LIFE | M5: =IF(H5="",NA(),1*H5) -> 0 | N5: =IF(I5="",NA(),1*I5) -> 0
A6: 5 | B6: LIFE | C6: U5 | D6: D2 | E6: -0.9 | F6: =INDEX(I_prop!$B$7:$H$13, MATCH($C6, I_prop!$A$7:$A$13,0), MATCH($D6, I_prop!$B$6:$H$6,0)) -> 0 | G6: =INDEX(I_prop!$B$18:$H$24, MATCH($C6, I_prop!$A$18:$A$24,0), MATCH($D6, I_prop!$B$17:$H$17,0)) -> 0 | H6: =IF($J6<>"",$J6,$F6) -> 0 | I6: =IF($K6<>"",$K6,$G6) -> 0 | J6: =IF(COUNTIFS(Subgroup_Overrides!$A$5:$A$200,"A",Subgroup_Overrides!$B$5:$B$200,$C6,Subgroup_Overrides!$C$5:$C$200,$D6)>0,_xludf.minifs(Subgroup_Overrides!$D$5:$D$200,Subgroup_Overrides!$A$5:$A$200,"A",Subgroup_Overrides!$B$5:$B$200,$C6,Subgroup_Overrides!$C$5:$C$200,$D6),"") | K6: =IF(COUNTIFS(Subgroup_Overrides!$A$5:$A$200,"B",Subgroup_Overrides!$B$5:$B$200,$C6,Subgroup_Overrides!$C$5:$C$200,$D6)>0,_xludf.minifs(Subgroup_Overrides!$D$5:$D$200,Subgroup_Overrides!$A$5:$A$200,"B",Subgroup_Overrides!$B$5:$B$200,$C6,Subgroup_Overrides!$C$5:$C$200,$D6),"") | L6: =TRIM(B6) -> LIFE | M6: =IF(H6="",NA(),1*H6) -> 0 | N6: =IF(I6="",NA(),1*I6) -> 0
A7: 6 | B7: LIFE | C7: U6 | D7: D2 | E7: -0.9 | F7: =INDEX(I_prop!$B$7:$H$13, MATCH($C7, I_prop!$A$7:$A$13,0), MATCH($D7, I_prop!$B$6:$H$6,0)) -> 0 | G7: =INDEX(I_prop!$B$18:$H$24, MATCH($C7, I_prop!$A$18:$A$24,0), MATCH($D7, I_prop!$B$17:$H$17,0)) -> 0 | H7: =IF($J7<>"",$J7,$F7) -> 0 | I7: =IF($K7<>"",$K7,$G7) -> 0 | J7: =IF(COUNTIFS(Subgroup_Overrides!$A$5:$A$200,"A",Subgroup_Overrides!$B$5:$B$200,$C7,Subgroup_Overrides!$C$5:$C$200,$D7)>0,_xludf.minifs(Subgroup_Overrides!$D$5:$D$200,Subgroup_Overrides!$A$5:$A$200,"A",Subgroup_Overrides!$B$5:$B$200,$C7,Subgroup_Overrides!$C$5:$C$200,$D7),"") | K7: =IF(COUNTIFS(Subgroup_Overrides!$A$5:$A$200,"B",Subgroup_Overrides!$B$5:$B$200,$C7,Subgroup_Overrides!$C$5:$C$200,$D7)>0,_xludf.minifs(Subgroup_Overrides!$D$5:$D$200,Subgroup_Overrides!$A$5:$A$200,"B",Subgroup_Overrides!$B$5:$B$200,$C7,Subgroup_Overrides!$C$5:$C$200,$D7),"") | L7: =TRIM(B7) -> LIFE | M7: =IF(H7="",NA(),1*H7) -> 0 | N7: =IF(I7="",NA(),1*I7) -> 0
A8: 7 | B8: LIFE | C8: U6 | D8: D7 | E8: -0.9 | F8: =INDEX(I_prop!$B$7:$H$13, MATCH($C8, I_prop!$A$7:$A$13,0), MATCH($D8, I_prop!$B$6:$H$6,0)) -> 0 | G8: =INDEX(I_prop!$B$18:$H$24, MATCH($C8, I_prop!$A$18:$A$24,0), MATCH($D8, I_prop!$B$17:$H$17,0)) -> 0 | H8: =IF($J8<>"",$J8,$F8) -> 0 | I8: =IF($K8<>"",$K8,$G8) -> 0 | J8: =IF(COUNTIFS(Subgroup_Overrides!$A$5:$A$200,"A",Subgroup_Overrides!$B$5:$B$200,$C8,Subgroup_Overrides!$C$5:$C$200,$D8)>0,_xludf.minifs(Subgroup_Overrides!$D$5:$D$200,Subgroup_Overrides!$A$5:$A$200,"A",Subgroup_Overrides!$B$5:$B$200,$C8,Subgroup_Overrides!$C$5:$C$200,$D8),"") | K8: =IF(COUNTIFS(Subgroup_Overrides!$A$5:$A$200,"B",Subgroup_Overrides!$B$5:$B$200,$C8,Subgroup_Overrides!$C$5:$C$200,$D8)>0,_xludf.minifs(Subgroup_Overrides!$D$5:$D$200,Subgroup_Overrides!$A$5:$A$200,"B",Subgroup_Overrides!$B$5:$B$200,$C8,Subgroup_Overrides!$C$5:$C$200,$D8),"") | L8: =TRIM(B8) -> LIFE | M8: =IF(H8="",NA(),1*H8) -> 0 | N8: =IF(I8="",NA(),1*I8) -> 0
A9: 8 | B9: BODY | C9: U1 | D9: D2 | E9: -0.7 | F9: =INDEX(I_prop!$B$7:$H$13, MATCH($C9, I_prop!$A$7:$A$13,0), MATCH($D9, I_prop!$B$6:$H$6,0)) -> 0 | G9: =INDEX(I_prop!$B$18:$H$24, MATCH($C9, I_prop!$A$18:$A$24,0), MATCH($D9, I_prop!$B$17:$H$17,0)) -> 0 | H9: =IF($J9<>"",$J9,$F9) -> 0 | I9: =IF($K9<>"",$K9,$G9) -> 0 | J9: =IF(COUNTIFS(Subgroup_Overrides!$A$5:$A$200,"A",Subgroup_Overrides!$B$5:$B$200,$C9,Subgroup_Overrides!$C$5:$C$200,$D9)>0,_xludf.minifs(Subgroup_Overrides!$D$5:$D$200,Subgroup_Overrides!$A$5:$A$200,"A",Subgroup_Overrides!$B$5:$B$200,$C9,Subgroup_Overrides!$C$5:$C$200,$D9),"") | K9: =IF(COUNTIFS(Subgroup_Overrides!$A$5:$A$200,"B",Subgroup_Overrides!$B$5:$B$200,$C9,Subgroup_Overrides!$C$5:$C$200,$D9)>0,_xludf.minifs(Subgroup_Overrides!$D$5:$D$200,Subgroup_Overrides!$A$5:$A$200,"B",Subgroup_Overrides!$B$5:$B$200,$C9,Subgroup_Overrides!$C$5:$C$200,$D9),"") | L9: =TRIM(B9) -> BODY | M9: =IF(H9="",NA(),1*H9) -> 0 | N9: =IF(I9="",NA(),1*I9) -> 0
A10: 9 | B10: BODY | C10: U2 | D10: D2 | E10: -0.7 | F10: =INDEX(I_prop!$B$7:$H$13, MATCH($C10, I_prop!$A$7:$A$13,0), MATCH($D10, I_prop!$B$6:$H$6,0)) -> 0 | G10: =INDEX(I_prop!$B$18:$H$24, MATCH($C10, I_prop!$A$18:$A$24,0), MATCH($D10, I_prop!$B$17:$H$17,0)) -> 0 | H10: =IF($J10<>"",$J10,$F10) -> 0 | I10: =IF($K10<>"",$K10,$G10) -> 0 | J10: =IF(COUNTIFS(Subgroup_Overrides!$A$5:$A$200,"A",Subgroup_Overrides!$B$5:$B$200,$C10,Subgroup_Overrides!$C$5:$C$200,$D10)>0,_xludf.minifs(Subgroup_Overrides!$D$5:$D$200,Subgroup_Overrides!$A$5:$A$200,"A",Subgroup_Overrides!$B$5:$B$200,$C10,Subgroup_Overrides!$C$5:$C$200,$D10),"") | K10: =IF(COUNTIFS(Subgroup_Overrides!$A$5:$A$200,"B",Subgroup_Overrides!$B$5:$B$200,$C10,Subgroup_Overrides!$C$5:$C$200,$D10)>0,_xludf.minifs(Subgroup_Overrides!$D$5:$D$200,Subgroup_Overrides!$A$5:$A$200,"B",Subgroup_Overrides!$B$5:$B$200,$C10,Subgroup_Overrides!$C$5:$C$200,$D10),"") | L10: =TRIM(B10) -> BODY | M10: =IF(H10="",NA(),1*H10) -> 0 | N10: =IF(I10="",NA(),1*I10) -> 0
A11: 10 | B11: BODY | C11: U3 | D11: D2 | E11: -0.7 | F11: =INDEX(I_prop!$B$7:$H$13, MATCH($C11, I_prop!$A$7:$A$13,0), MATCH($D11, I_prop!$B$6:$H$6,0)) -> 0 | G11: =INDEX(I_prop!$B$18:$H$24, MATCH($C11, I_prop!$A$18:$A$24,0), MATCH($D11, I_prop!$B$17:$H$17,0)) -> 0 | H11: =IF($J11<>"",$J11,$F11) -> 0 | I11: =IF($K11<>"",$K11,$G11) -> 0 | J11: =IF(COUNTIFS(Subgroup_Overrides!$A$5:$A$200,"A",Subgroup_Overrides!$B$5:$B$200,$C11,Subgroup_Overrides!$C$5:$C$200,$D11)>0,_xludf.minifs(Subgroup_Overrides!$D$5:$D$200,Subgroup_Overrides!$A$5:$A$200,"A",Subgroup_Overrides!$B$5:$B$200,$C11,Subgroup_Overrides!$C$5:$C$200,$D11),"") | K11: =IF(COUNTIFS(Subgroup_Overrides!$A$5:$A$200,"B",Subgroup_Overrides!$B$5:$B$200,$C11,Subgroup_Overrides!$C$5:$C$200,$D11)>0,_xludf.minifs(Subgroup_Overrides!$D$5:$D$200,Subgroup_Overrides!$A$5:$A$200,"B",Subgroup_Overrides!$B$5:$B$200,$C11,Subgroup_Overrides!$C$5:$C$200,$D11),"") | L11: =TRIM(B11) -> BODY | M11: =IF(H11="",NA(),1*H11) -> 0 | N11: =IF(I11="",NA(),1*I11) -> 0
A12: 11 | B12: BODY | C12: U4 | D12: D2 | E12: -0.7 | F12: =INDEX(I_prop!$B$7:$H$13, MATCH($C12, I_prop!$A$7:$A$13,0), MATCH($D12, I_prop!$B$6:$H$6,0)) -> 0 | G12: =INDEX(I_prop!$B$18:$H$24, MATCH($C12, I_prop!$A$18:$A$24,0), MATCH($D12, I_prop!$B$17:$H$17,0)) -> 0 | H12: =IF($J12<>"",$J12,$F12) -> 0 | I12: =IF($K12<>"",$K12,$G12) -> 0 | J12: =IF(COUNTIFS(Subgroup_Overrides!$A$5:$A$200,"A",Subgroup_Overrides!$B$5:$B$200,$C12,Subgroup_Overrides!$C$5:$C$200,$D12)>0,_xludf.minifs(Subgroup_Overrides!$D$5:$D$200,Subgroup_Overrides!$A$5:$A$200,"A",Subgroup_Overrides!$B$5:$B$200,$C12,Subgroup_Overrides!$C$5:$C$200,$D12),"") | K12: =IF(COUNTIFS(Subgroup_Overrides!$A$5:$A$200,"B",Subgroup_Overrides!$B$5:$B$200,$C12,Subgroup_Overrides!$C$5:$C$200,$D12)>0,_xludf.minifs(Subgroup_Overrides!$D$5:$D$200,Subgroup_Overrides!$A$5:$A$200,"B",Subgroup_Overrides!$B$5:$B$200,$C12,Subgroup_Overrides!$C$5:$C$200,$D12),"") | L12: =TRIM(B12) -> BODY | M12: =IF(H12="",NA(),1*H12) -> 0 | N12: =IF(I12="",NA(),1*I12) -> 0
A13: 12 | B13: BODY | C13: U5 | D13: D2 | E13: -0.7 | F13: =INDEX(I_prop!$B$7:$H$13, MATCH($C13, I_prop!$A$7:$A$13,0), MATCH($D13, I_prop!$B$6:$H$6,0)) -> 0 | G13: =INDEX(I_prop!$B$18:$H$24, MATCH($C13, I_prop!$A$18:$A$24,0), MATCH($D13, I_prop!$B$17:$H$17,0)) -> 0 | H13: =IF($J13<>"",$J13,$F13) -> 0 | I13: =IF($K13<>"",$K13,$G13) -> 0 | J13: =IF(COUNTIFS(Subgroup_Overrides!$A$5:$A$200,"A",Subgroup_Overrides!$B$5:$B$200,$C13,Subgroup_Overrides!$C$5:$C$200,$D13)>0,_xludf.minifs(Subgroup_Overrides!$D$5:$D$200,Subgroup_Overrides!$A$5:$A$200,"A",Subgroup_Overrides!$B$5:$B$200,$C13,Subgroup_Overrides!$C$5:$C$200,$D13),"") | K13: =IF(COUNTIFS(Subgroup_Overrides!$A$5:$A$200,"B",Subgroup_Overrides!$B$5:$B$200,$C13,Subgroup_Overrides!$C$5:$C$200,$D13)>0,_xludf.minifs(Subgroup_Overrides!$D$5:$D$200,Subgroup_Overrides!$A$5:$A$200,"B",Subgroup_Overrides!$B$5:$B$200,$C13,Subgroup_Overrides!$C$5:$C$200,$D13),"") | L13: =TRIM(B13) -> BODY | M13: =IF(H13="",NA(),1*H13) -> 0 | N13: =IF(I13="",NA(),1*I13) -> 0
... A71: 70 | B71: INFO | C71: U6 | D71: D5 | E71: -0.4 | F71: =INDEX(I_prop!$B$7:$H$13, MATCH($C71, I_prop!$A$7:$A$13,0), MATCH($D71, I_prop!$B$6:$H$6,0)) -> 0 | G71: =INDEX(I_prop!$B$18:$H$24, MATCH($C71, I_prop!$A$18:$A$24,0), MATCH($D71, I_prop!$B$17:$H$17,0)) -> 0 | H71: =IF($J71<>"",$J71,$F71) -> 0 | I71: =IF($K71<>"",$K71,$G71) -> 0 | J71: =IF(COUNTIFS(Subgroup_Overrides!$A$5:$A$200,"A",Subgroup_Overrides!$B$5:$B$200,$C71,Subgroup_Overrides!$C$5:$C$200,$D71)>0,_xludf.minifs(Subgroup_Overrides!$D$5:$D$200,Subgroup_Overrides!$A$5:$A$200,"A",Subgroup_Overrides!$B$5:$B$200,$C71,Subgroup_Overrides!$C$5:$C$200,$D71),"") | K71: =IF(COUNTIFS(Subgroup_Overrides!$A$5:$A$200,"B",Subgroup_Overrides!$B$5:$B$200,$C71,Subgroup_Overrides!$C$5:$C$200,$D71)>0,_xludf.minifs(Subgroup_Overrides!$D$5:$D$200,Subgroup_Overrides!$A$5:$A$200,"B",Subgroup_Overrides!$B$5:$B$200,$C71,Subgroup_Overrides!$C$5:$C$200,$D71),"") | L71: =TRIM(B71) -> INFO | M71: =IF(H71="",NA(),1*H71) -> 0 | N71: =IF(I71="",NA(),1*I71) -> 0

Sheet C_cat
A1: CATASTROPHE CELL SET (C_cat) - TRC Loss Computation
A3: Reference: Ripple_Logic v8.6 Section 8.3
A4: BASE SET (Canonical - governance approval required to extend)
A6: Cell | B6: Union | C6: Dimension | D6: Weight (ω_c) | E6: Rationale
A7: C1 | B7: U6 | C7: D2 (Health) | D7: 0.35 | E7: Humanity health catastrophe
A8: C2 | B8: U6 | C8: D7 (Environ) | D8: 0.3 | E8: Humanity-environment interface
A9: C3 | B9: U7 | C9: D7 (Environ) | D9: 0.35 | E9: Biosphere integrity
A11: Weight Sum Check: | B11: =SUM(D7:D9) -> 1 | C11: Must = 1.00
A13: EXTENSION GOVERNANCE
A14: Extended cells require:
A15: - Tier 3+ governance approval
A16: - Documentation in PCC
A17: - CCAT_EXTENDED flag set
A19: CCAT_EXTENDED Flag: | B19: NO - BASE ONLY

Sheet WTSL_Categories
A1: MANDATORY TAIL RISK CATEGORIES (WTSL)
A3: Reference: Ripple_Logic v8.6 Section 8.5
A4: Mandatory tails apply by default. WTSL-AIX is mandatory only if AI Deployment = YES. | D4: Included voluntarily (precautionary)
A6: Code | B6: Category | C6: Description | D6: p(cat) | E6: p_floor | F6: Status | G6: Required?
A7: WTSL-PAN | B7: Pandemic | C7: Global health crisis | D7: =SUMIF(Scenario_Impacts!$B$11:$B$16,A7,Scenario_Impacts!$C$11:$C$16) -> 0.08 | E7: 0.02 | F7: =IF(G7="NO","OPTIONAL",IF(D7>=E7,"✓ COVERED","✗ MISSING")) -> ✓ COVERED | G7: =IF(A7="WTSL-AIX",IF(Config!$B$13="YES","YES","NO"),"YES") -> YES
A8: WTSL-CLI | B8: Climate | C8: Climate catastrophe | D8: =SUMIF(Scenario_Impacts!$B$11:$B$16,A8,Scenario_Impacts!$C$11:$C$16) -> 0.07 | E8: 0.02 | F8: =IF(G8="NO","OPTIONAL",IF(D8>=E8,"✓ COVERED","✗ MISSING")) -> ✓ COVERED | G8: =IF(A8="WTSL-AIX",IF(Config!$B$13="YES","YES","NO"),"YES") -> YES
A9: WTSL-FIN | B9: Financial | C9: Financial system collapse | D9: =SUMIF(Scenario_Impacts!$B$11:$B$16,A9,Scenario_Impacts!$C$11:$C$16) -> 0.15 | E9: 0.02 | F9: =IF(G9="NO","OPTIONAL",IF(D9>=E9,"✓ COVERED","✗ MISSING")) -> ✓ COVERED | G9: =IF(A9="WTSL-AIX",IF(Config!$B$13="YES","YES","NO"),"YES") -> YES
A10: WTSL-CON | B10: Conflict | C10: Major armed conflict | D10: =SUMIF(Scenario_Impacts!$B$11:$B$16,A10,Scenario_Impacts!$C$11:$C$16) -> 0.03 | E10: 0.02 | F10: =IF(G10="NO","OPTIONAL",IF(D10>=E10,"✓ COVERED","✗ MISSING")) -> ✓ COVERED | G10: =IF(A10="WTSL-AIX",IF(Config!$B$13="YES","YES","NO"),"YES") -> YES
A11: WTSL-INF | B11: Infrastructure | C11: Critical infrastructure failure | D11: =SUMIF(Scenario_Impacts!$B$11:$B$16,A11,Scenario_Impacts!$C$11:$C$16) -> 0.05 | E11: 0.02 | F11: =IF(G11="NO","OPTIONAL",IF(D11>=E11,"✓ COVERED","✗ MISSING")) -> ✓ COVERED | G11: =IF(A11="WTSL-AIX",IF(Config!$B$13="YES","YES","NO"),"YES") -> YES
A12: WTSL-AIX | B12: AI Risk | C12: AI misalignment event | D12: =SUMIF(Scenario_Impacts!$B$11:$B$16,A12,Scenario_Impacts!$C$11:$C$16) -> 0.02 | E12: 0.02 | F12: =IF(G12="NO","OPTIONAL",IF(D12>=E12,"✓ COVERED","✗ MISSING")) -> OPTIONAL | G12: =IF(A12="WTSL-AIX",IF(Config!$B$13="YES","YES","NO"),"YES") -> NO
A15: COVERAGE CHECK
A16: Mandatory Count: | B16: =CANON!B41 -> 5 | C16: (5 if AI_DEPLOYMENT=NO, 6 if YES)
A17: Covered Count: | B17: =COUNTIF(F7:F12,"✓*") -> 5
A18: Probability Sum: | B18: =SUM(D7:D12) -> 0.4 | C18: (tail scenarios; baseline = 0.60)

Sheet Impact_Input
A1: IMPACT INSTANCE INPUT
A3: Formula: Contribution = μ × r × ℓ × c × e × s × τ(t)
A4: τ(t) = MIN(1, LN(1+MAX(t, t_min)) / LN(1+T_ref)) where T_ref=25, t_min=0.083 [v8.6 Appendix B.1]
A6: ID | B6: Opt | C6: Union | D6: Dim | E6: Description | F6: μ | G6: r | H6: ℓ | I6: c | J6: t | K6: e | L6: s | M6: τ(t) | N6: Contrib
A7: I01 | B7: A | C7: U3 | D7: D3 | E7: Reduced in-person interaction | F7: -0.3 | G7: 0.8 | H7: 0.7 | I7: 0.5 | J7: 5 | K7: 1 | L7: 1 | M7: =MIN(1, LN(1+MAX(J7, CANON!$B$27)) / LN(1+CANON!$B$25)) -> 0.54994057 | N7: =F7*G7*H7*I7*K7*L7*M7 -> -0.046195008
A8: I02 | B8: A | C8: U3 | D8: D3 | E8: Increased online community | F8: 0.15 | G8: 0.6 | H8: 0.5 | I8: 0.3 | J8: 3 | K8: 1 | L8: 1 | M8: =MIN(1, LN(1+MAX(J8, CANON!$B$27)) / LN(1+CANON!$B$25)) -> 0.42549211 | N8: =F8*G8*H8*I8*K8*L8*M8 -> 0.0057441434
A9: I03 | B9: A | C9: U1 | D9: D5 | E9: Increased work flexibility | F9: 0.4 | G9: 0.9 | H9: 0.8 | I9: 0.6 | J9: 10 | K9: 1 | L9: 1 | M9: =MIN(1, LN(1+MAX(J9, CANON!$B$27)) / LN(1+CANON!$B$25)) -> 0.73598042 | N9: =F9*G9*H9*I9*K9*L9*M9 -> 0.12717742
A10: I04 | B10: A | C10: U2 | D10: D1 | E10: Reduced commuting costs | F10: 0.25 | G10: 0.7 | H10: 0.6 | I10: 0.4 | J10: 5 | K10: 1 | L10: 1 | M10: =MIN(1, LN(1+MAX(J10, CANON!$B$27)) / LN(1+CANON!$B$25)) -> 0.54994057 | N10: =F10*G10*H10*I10*K10*L10*M10 -> 0.023097504
A11: I05 | B11: A | C11: U1 | D11: D6 | E11: Better work-life balance | F11: 0.35 | G11: 0.8 | H11: 0.7 | I11: 0.5 | J11: 10 | K11: 1 | L11: 1 | M11: =MIN(1, LN(1+MAX(J11, CANON!$B$27)) / LN(1+CANON!$B$25)) -> 0.73598042 | N11: =F11*G11*H11*I11*K11*L11*M11 -> 0.072126082
A12: I06 | B12: A | C12: U7 | D12: D7 | E12: Reduced carbon emissions | F12: 0.15 | G12: 0.5 | H12: 0.4 | I12: 0.3 | J12: 15 | K12: 1 | L12: 1 | M12: =MIN(1, LN(1+MAX(J12, CANON!$B$27)) / LN(1+CANON!$B$25)) -> 0.85098421 | N12: =F12*G12*H12*I12*K12*L12*M12 -> 0.0076588579
A13: I07 | B13: A | C13: U4 | D13: D1 | E13: Tech infrastructure costs | F13: -0.2 | G13: 0.9 | H13: 0.8 | I13: 0.7 | J13: 3 | K13: 1 | L13: 1 | M13: =MIN(1, LN(1+MAX(J13, CANON!$B$27)) / LN(1+CANON!$B$25)) -> 0.42549211 | N13: =F13*G13*H13*I13*K13*L13*M13 -> -0.042889604
A14: I08 | B14: A | C14: U3 | D14: D1 | E14: Reduced local business revenue | F14: -0.15 | G14: 0.6 | H14: 0.5 | I14: 0.4 | J14: 5 | K14: 1 | L14: 1 | M14: =MIN(1, LN(1+MAX(J14, CANON!$B$27)) / LN(1+CANON!$B$25)) -> 0.54994057 | N14: =F14*G14*H14*I14*K14*L14*M14 -> -0.0098989303
A15: I09 | B15: B | C15: U3 | D15: D3 | E15: Maintained in-person bonds | F15: 0.2 | G15: 0.8 | H15: 0.7 | I15: 0.5 | J15: 5 | K15: 1 | L15: 1 | M15: =MIN(1, LN(1+MAX(J15, CANON!$B$27)) / LN(1+CANON!$B$25)) -> 0.54994057 | N15: =F15*G15*H15*I15*K15*L15*M15 -> 0.030796672
A16: I10 | B16: B | C16: U1 | D16: D5 | E16: Limited flexibility | F16: -0.15 | G16: 0.7 | H16: 0.6 | I16: 0.5 | J16: 10 | K16: 1 | L16: 1 | M16: =MIN(1, LN(1+MAX(J16, CANON!$B$27)) / LN(1+CANON!$B$25)) -> 0.73598042 | N16: =F16*G16*H16*I16*K16*L16*M16 -> -0.023183383
A17: I11 | B17: B | C17: U2 | D17: D1 | E17: Continued commuting costs | F17: -0.1 | G17: 0.7 | H17: 0.6 | I17: 0.4 | J17: 5 | K17: 1 | L17: 1 | M17: =MIN(1, LN(1+MAX(J17, CANON!$B$27)) / LN(1+CANON!$B$25)) -> 0.54994057 | N17: =F17*G17*H17*I17*K17*L17*M17 -> -0.0092390016
A18: I12 | B18: B | C18: U7 | D18: D7 | E18: Continued emissions | F18: -0.1 | G18: 0.5 | H18: 0.4 | I18: 0.3 | J18: 15 | K18: 1 | L18: 1 | M18: =MIN(1, LN(1+MAX(J18, CANON!$B$27)) / LN(1+CANON!$B$25)) -> 0.85098421 | N18: =F18*G18*H18*I18*K18*L18*M18 -> -0.0051059053
... A20: I14 | B20: B | C20: U3 | D20: D1 | E20: Maintained local business | F20: 0.1 | G20: 0.6 | H20: 0.5 | I20: 0.4 | J20: 5 | K20: 1 | L20: 1 | M20: =MIN(1, LN(1+MAX(J20, CANON!$B$27)) / LN(1+CANON!$B$25)) -> 0.54994057 | N20: =F20*G20*H20*I20*K20*L20*M20 -> 0.0065992868

Sheet Scenario_Impacts
A1: SCENARIO-CONDITIONED IMPACT TABLES
A3: Reference: Ripple_Logic v8.6 Section 8.4
A4: L(a,s) = Σ_{c∈C_cat} ω_c × max(0, −I_prop_c(a|s))
A5: NOTE: Loss is computed from catastrophe-cell impacts. Do NOT manually enter Loss. Fill catastrophe-cell impacts (F:H) per scenario; Loss (computed) updates automatically.
A6: C_cat: U6-D2(0.35), U6-D7(0.30), U7-D7(0.35)
A8: OPTION A SCENARIO LOSSES
A9: Scenario | B9: Category | C9: p(s) | D9: Loss | E9: Pathway | F9: U6-D2 I_prop | G9: U6-D7 I_prop | H9: U7-D7 I_prop | I9: Loss (computed)
A10: S01 | B10: BASELINE | C10: 0.6 | D10: =I10 -> 0 | E10: Minor monitoring reduction | F10: 0 | G10: 0 | H10: 0.015317 | I10: =0.35*MAX(0,-F10)+0.3*MAX(0,-G10)+0.35*MAX(0,-H10) -> 0
A11: S02 | B11: WTSL-FIN | C11: 0.15 | D11: =I11 -> 0.007 | E11: Budget cuts reduce compliance | F11: -0.02 | G11: 0 | H11: 0.01 | I11: =0.35*MAX(0,-F11)+0.3*MAX(0,-G11)+0.35*MAX(0,-H11) -> 0.007
A12: S03 | B12: WTSL-PAN | C12: 0.08 | D12: =I12 -> 0.0175 | E12: Health crisis, isolation stress | F12: -0.05 | G12: 0 | H12: 0.02 | I12: =0.35*MAX(0,-F12)+0.3*MAX(0,-G12)+0.35*MAX(0,-H12) -> 0.0175
A13: S04 | B13: WTSL-CLI | C13: 0.07 | D13: =I13 -> 0.0195 | E13: Climate degrades biosphere | F13: -0.01 | G13: -0.03 | H13: -0.02 | I13: =0.35*MAX(0,-F13)+0.3*MAX(0,-G13)+0.35*MAX(0,-H13) -> 0.0195
A14: S05 | B14: WTSL-INF | C14: 0.05 | D14: =I14 -> 0.0135 | E14: Tech dependency vulnerability | F14: -0.03 | G14: -0.01 | H14: 0.01 | I14: =0.35*MAX(0,-F14)+0.3*MAX(0,-G14)+0.35*MAX(0,-H14) -> 0.0135
A15: S06 | B15: WTSL-CON | C15: 0.03 | D15: =I15 -> 0.0235 | E15: Conflict casualties | F15: -0.04 | G15: -0.02 | H15: -0.01 | I15: =0.35*MAX(0,-F15)+0.3*MAX(0,-G15)+0.35*MAX(0,-H15) -> 0.0235
A16: S07 | B16: WTSL-AIX | C16: 0.02 | D16: =I16 -> 0.01 | E16: AI failures cascade | F16: -0.02 | G16: -0.01 | H16: 0 | I16: =0.35*MAX(0,-F16)+0.3*MAX(0,-G16)+0.35*MAX(0,-H16) -> 0.01
A19: OPTION B SCENARIO LOSSES
A20: Scenario | B20: Category | C20: p(s) | D20: Loss | E20: Pathway | F20: U6-D2 I_prop | G20: U6-D7 I_prop | H20: U7-D7 I_prop | I20: Loss (computed)
A21: S01 | B21: BASELINE | C21: 0.6 | D21: =I21 -> 0.00357385 | E21: Emissions continue | F21: 0 | G21: 0 | H21: -0.010211 | I21: =0.35*MAX(0,-F21)+0.3*MAX(0,-G21)+0.35*MAX(0,-H21) -> 0.00357385
A22: S02 | B22: WTSL-FIN | C22: 0.15 | D22: =I22 -> 0.0105 | E22: Community bonds buffer | F22: -0.015 | G22: 0 | H22: -0.015 | I22: =0.35*MAX(0,-F22)+0.3*MAX(0,-G22)+0.35*MAX(0,-H22) -> 0.0105
A23: S03 | B23: WTSL-PAN | C23: 0.08 | D23: =I23 -> 0.0315 | E23: Transmission risk | F23: -0.08 | G23: 0 | H23: -0.01 | I23: =0.35*MAX(0,-F23)+0.3*MAX(0,-G23)+0.35*MAX(0,-H23) -> 0.0315
A24: S04 | B24: WTSL-CLI | C24: 0.07 | D24: =I24 -> 0.0235 | E24: Resilience buffers | F24: -0.01 | G24: -0.02 | H24: -0.04 | I24: =0.35*MAX(0,-F24)+0.3*MAX(0,-G24)+0.35*MAX(0,-H24) -> 0.0235
A25: S05 | B25: WTSL-INF | C25: 0.05 | D25: =I25 -> 0.0135 | E25: Less tech-dependent | F25: -0.02 | G25: -0.01 | H25: -0.01 | I25: =0.35*MAX(0,-F25)+0.3*MAX(0,-G25)+0.35*MAX(0,-H25) -> 0.0135
A26: S06 | B26: WTSL-CON | C26: 0.03 | D26: =I26 -> 0.02175 | E26: Human coord persists | F26: -0.03 | G26: -0.02 | H26: -0.015 | I26: =0.35*MAX(0,-F26)+0.3*MAX(0,-G26)+0.35*MAX(0,-H26) -> 0.02175
A27: S07 | B27: WTSL-AIX | C27: 0.02 | D27: =I27 -> 0.007 | E27: Less AI dependency | F27: -0.01 | G27: 0 | H27: -0.01 | I27: =0.35*MAX(0,-F27)+0.3*MAX(0,-G27)+0.35*MAX(0,-H27) -> 0.007
A29: KEY INSIGHT: Option A has 0 catastrophic loss; Option B has minor loss (0.003574) in baseline
A30: Both options pass TRC (CVaR ≤ τ_TRC = 0.20)
A31: NOTE: WTSL-AIX (S07) included voluntarily as precautionary measure. | B31: AI_DEPLOYMENT=NO, so not mandatory for tail coverage.

Sheet I_prop
A1: IMPACT PROPAGATION MATRIX (I_prop)
A3: Mode: NONE (direct aggregation from Impact_Input; post-saturation tanh(β×Ĩ_dir))
A5: OPTION A
B6: D1 | C6: D2 | D6: D3 | E6: D4 | F6: D5 | G6: D6 | H6: D7
A7: U1 | B7: =TANH(Parameters!$B$24*SUMIFS(Impact_Input!$N:$N,Impact_Input!$B:$B,"A",Impact_Input!$C:$C,$A7,Impact_Input!$D:$D,B$6)) -> 0 | C7: =TANH(Parameters!$B$24*SUMIFS(Impact_Input!$N:$N,Impact_Input!$B:$B,"A",Impact_Input!$C:$C,$A7,Impact_Input!$D:$D,C$6)) -> 0 | D7: =TANH(Parameters!$B$24*SUMIFS(Impact_Input!$N:$N,Impact_Input!$B:$B,"A",Impact_Input!$C:$C,$A7,Impact_Input!$D:$D,D$6)) -> 0 | E7: =TANH(Parameters!$B$24*SUMIFS(Impact_Input!$N:$N,Impact_Input!$B:$B,"A",Impact_Input!$C:$C,$A7,Impact_Input!$D:$D,E$6)) -> 0 | F7: =TANH(Parameters!$B$24*SUMIFS(Impact_Input!$N:$N,Impact_Input!$B:$B,"A",Impact_Input!$C:$C,$A7,Impact_Input!$D:$D,F$6)) -> 0.24900788 | G7: =TANH(Parameters!$B$24*SUMIFS(Impact_Input!$N:$N,Impact_Input!$B:$B,"A",Impact_Input!$C:$C,$A7,Impact_Input!$D:$D,G$6)) -> 0.14325986 | H7: =TANH(Parameters!$B$24*SUMIFS(Impact_Input!$N:$N,Impact_Input!$B:$B,"A",Impact_Input!$C:$C,$A7,Impact_Input!$D:$D,H$6)) -> 0
A8: U2 | B8: =TANH(Parameters!$B$24*SUMIFS(Impact_Input!$N:$N,Impact_Input!$B:$B,"A",Impact_Input!$C:$C,$A8,Impact_Input!$D:$D,B$6)) -> 0.046162176 | C8: =TANH(Parameters!$B$24*SUMIFS(Impact_Input!$N:$N,Impact_Input!$B:$B,"A",Impact_Input!$C:$C,$A8,Impact_Input!$D:$D,C$6)) -> 0 | D8: =TANH(Parameters!$B$24*SUMIFS(Impact_Input!$N:$N,Impact_Input!$B:$B,"A",Impact_Input!$C:$C,$A8,Impact_Input!$D:$D,D$6)) -> 0 | E8: =TANH(Parameters!$B$24*SUMIFS(Impact_Input!$N:$N,Impact_Input!$B:$B,"A",Impact_Input!$C:$C,$A8,Impact_Input!$D:$D,E$6)) -> 0 | F8: =TANH(Parameters!$B$24*SUMIFS(Impact_Input!$N:$N,Impact_Input!$B:$B,"A",Impact_Input!$C:$C,$A8,Impact_Input!$D:$D,F$6)) -> 0 | G8: =TANH(Parameters!$B$24*SUMIFS(Impact_Input!$N:$N,Impact_Input!$B:$B,"A",Impact_Input!$C:$C,$A8,Impact_Input!$D:$D,G$6)) -> 0 | H8: =TANH(Parameters!$B$24*SUMIFS(Impact_Input!$N:$N,Impact_Input!$B:$B,"A",Impact_Input!$C:$C,$A8,Impact_Input!$D:$D,H$6)) -> 0
A9: U3 | B9: =TANH(Parameters!$B$24*SUMIFS(Impact_Input!$N:$N,Impact_Input!$B:$B,"A",Impact_Input!$C:$C,$A9,Impact_Input!$D:$D,B$6)) -> -0.019795274 | C9: =TANH(Parameters!$B$24*SUMIFS(Impact_Input!$N:$N,Impact_Input!$B:$B,"A",Impact_Input!$C:$C,$A9,Impact_Input!$D:$D,C$6)) -> 0 | D9: =TANH(Parameters!$B$24*SUMIFS(Impact_Input!$N:$N,Impact_Input!$B:$B,"A",Impact_Input!$C:$C,$A9,Impact_Input!$D:$D,D$6)) -> -0.080725687 | E9: =TANH(Parameters!$B$24*SUMIFS(Impact_Input!$N:$N,Impact_Input!$B:$B,"A",Impact_Input!$C:$C,$A9,Impact_Input!$D:$D,E$6)) -> 0 | F9: =TANH(Parameters!$B$24*SUMIFS(Impact_Input!$N:$N,Impact_Input!$B:$B,"A",Impact_Input!$C:$C,$A9,Impact_Input!$D:$D,F$6)) -> 0 | G9: =TANH(Parameters!$B$24*SUMIFS(Impact_Input!$N:$N,Impact_Input!$B:$B,"A",Impact_Input!$C:$C,$A9,Impact_Input!$D:$D,G$6)) -> 0 | H9: =TANH(Parameters!$B$24*SUMIFS(Impact_Input!$N:$N,Impact_Input!$B:$B,"A",Impact_Input!$C:$C,$A9,Impact_Input!$D:$D,H$6)) -> 0
A10: U4 | B10: =TANH(Parameters!$B$24*SUMIFS(Impact_Input!$N:$N,Impact_Input!$B:$B,"A",Impact_Input!$C:$C,$A10,Impact_Input!$D:$D,B$6)) -> -0.085569436 | C10: =TANH(Parameters!$B$24*SUMIFS(Impact_Input!$N:$N,Impact_Input!$B:$B,"A",Impact_Input!$C:$C,$A10,Impact_Input!$D:$D,C$6)) -> 0 | D10: =TANH(Parameters!$B$24*SUMIFS(Impact_Input!$N:$N,Impact_Input!$B:$B,"A",Impact_Input!$C:$C,$A10,Impact_Input!$D:$D,D$6)) -> 0 | E10: =TANH(Parameters!$B$24*SUMIFS(Impact_Input!$N:$N,Impact_Input!$B:$B,"A",Impact_Input!$C:$C,$A10,Impact_Input!$D:$D,E$6)) -> 0 | F10: =TANH(Parameters!$B$24*SUMIFS(Impact_Input!$N:$N,Impact_Input!$B:$B,"A",Impact_Input!$C:$C,$A10,Impact_Input!$D:$D,F$6)) -> 0 | G10: =TANH(Parameters!$B$24*SUMIFS(Impact_Input!$N:$N,Impact_Input!$B:$B,"A",Impact_Input!$C:$C,$A10,Impact_Input!$D:$D,G$6)) -> 0 | H10: =TANH(Parameters!$B$24*SUMIFS(Impact_Input!$N:$N,Impact_Input!$B:$B,"A",Impact_Input!$C:$C,$A10,Impact_Input!$D:$D,H$6)) -> 0
A11: U5 | B11: =TANH(Parameters!$B$24*SUMIFS(Impact_Input!$N:$N,Impact_Input!$B:$B,"A",Impact_Input!$C:$C,$A11,Impact_Input!$D:$D,B$6)) -> 0 | C11: =TANH(Parameters!$B$24*SUMIFS(Impact_Input!$N:$N,Impact_Input!$B:$B,"A",Impact_Input!$C:$C,$A11,Impact_Input!$D:$D,C$6)) -> 0 | D11: =TANH(Parameters!$B$24*SUMIFS(Impact_Input!$N:$N,Impact_Input!$B:$B,"A",Impact_Input!$C:$C,$A11,Impact_Input!$D:$D,D$6)) -> 0 | E11: =TANH(Parameters!$B$24*SUMIFS(Impact_Input!$N:$N,Impact_Input!$B:$B,"A",Impact_Input!$C:$C,$A11,Impact_Input!$D:$D,E$6)) -> 0 | F11: =TANH(Parameters!$B$24*SUMIFS(Impact_Input!$N:$N,Impact_Input!$B:$B,"A",Impact_Input!$C:$C,$A11,Impact_Input!$D:$D,F$6)) -> 0 | G11: =TANH(Parameters!$B$24*SUMIFS(Impact_Input!$N:$N,Impact_Input!$B:$B,"A",Impact_Input!$C:$C,$A11,Impact_Input!$D:$D,G$6)) -> 0 | H11: =TANH(Parameters!$B$24*SUMIFS(Impact_Input!$N:$N,Impact_Input!$B:$B,"A",Impact_Input!$C:$C,$A11,Impact_Input!$D:$D,H$6)) -> 0
A12: U6 | B12: =TANH(Parameters!$B$24*SUMIFS(Impact_Input!$N:$N,Impact_Input!$B:$B,"A",Impact_Input!$C:$C,$A12,Impact_Input!$D:$D,B$6)) -> 0 | C12: =TANH(Parameters!$B$24*SUMIFS(Impact_Input!$N:$N,Impact_Input!$B:$B,"A",Impact_Input!$C:$C,$A12,Impact_Input!$D:$D,C$6)) -> 0 | D12: =TANH(Parameters!$B$24*SUMIFS(Impact_Input!$N:$N,Impact_Input!$B:$B,"A",Impact_Input!$C:$C,$A12,Impact_Input!$D:$D,D$6)) -> 0 | E12: =TANH(Parameters!$B$24*SUMIFS(Impact_Input!$N:$N,Impact_Input!$B:$B,"A",Impact_Input!$C:$C,$A12,Impact_Input!$D:$D,E$6)) -> 0 | F12: =TANH(Parameters!$B$24*SUMIFS(Impact_Input!$N:$N,Impact_Input!$B:$B,"A",Impact_Input!$C:$C,$A12,Impact_Input!$D:$D,F$6)) -> 0 | G12: =TANH(Parameters!$B$24*SUMIFS(Impact_Input!$N:$N,Impact_Input!$B:$B,"A",Impact_Input!$C:$C,$A12,Impact_Input!$D:$D,G$6)) -> 0 | H12: =TANH(Parameters!$B$24*SUMIFS(Impact_Input!$N:$N,Impact_Input!$B:$B,"A",Impact_Input!$C:$C,$A12,Impact_Input!$D:$D,H$6)) -> 0
A13: U7 | B13: =TANH(Parameters!$B$24*SUMIFS(Impact_Input!$N:$N,Impact_Input!$B:$B,"A",Impact_Input!$C:$C,$A13,Impact_Input!$D:$D,B$6)) -> 0 | C13: =TANH(Parameters!$B$24*SUMIFS(Impact_Input!$N:$N,Impact_Input!$B:$B,"A",Impact_Input!$C:$C,$A13,Impact_Input!$D:$D,C$6)) -> 0 | D13: =TANH(Parameters!$B$24*SUMIFS(Impact_Input!$N:$N,Impact_Input!$B:$B,"A",Impact_Input!$C:$C,$A13,Impact_Input!$D:$D,D$6)) -> 0 | E13: =TANH(Parameters!$B$24*SUMIFS(Impact_Input!$N:$N,Impact_Input!$B:$B,"A",Impact_Input!$C:$C,$A13,Impact_Input!$D:$D,E$6)) -> 0 | F13: =TANH(Parameters!$B$24*SUMIFS(Impact_Input!$N:$N,Impact_Input!$B:$B,"A",Impact_Input!$C:$C,$A13,Impact_Input!$D:$D,F$6)) -> 0 | G13: =TANH(Parameters!$B$24*SUMIFS(Impact_Input!$N:$N,Impact_Input!$B:$B,"A",Impact_Input!$C:$C,$A13,Impact_Input!$D:$D,G$6)) -> 0 | H13: =TANH(Parameters!$B$24*SUMIFS(Impact_Input!$N:$N,Impact_Input!$B:$B,"A",Impact_Input!$C:$C,$A13,Impact_Input!$D:$D,H$6)) -> 0.015316518
A16: OPTION B
B17: D1 | C17: D2 | D17: D3 | E17: D4 | F17: D5 | G17: D6 | H17: D7
A18: U1 | B18: =TANH(Parameters!$B$24*SUMIFS(Impact_Input!$N:$N,Impact_Input!$B:$B,"B",Impact_Input!$C:$C,$A18,Impact_Input!$D:$D,B$17)) -> 0 | C18: =TANH(Parameters!$B$24*SUMIFS(Impact_Input!$N:$N,Impact_Input!$B:$B,"B",Impact_Input!$C:$C,$A18,Impact_Input!$D:$D,C$17)) -> 0 | D18: =TANH(Parameters!$B$24*SUMIFS(Impact_Input!$N:$N,Impact_Input!$B:$B,"B",Impact_Input!$C:$C,$A18,Impact_Input!$D:$D,D$17)) -> 0 | E18: =TANH(Parameters!$B$24*SUMIFS(Impact_Input!$N:$N,Impact_Input!$B:$B,"B",Impact_Input!$C:$C,$A18,Impact_Input!$D:$D,E$17)) -> 0 | F18: =TANH(Parameters!$B$24*SUMIFS(Impact_Input!$N:$N,Impact_Input!$B:$B,"B",Impact_Input!$C:$C,$A18,Impact_Input!$D:$D,F$17)) -> -0.046333568 | G18: =TANH(Parameters!$B$24*SUMIFS(Impact_Input!$N:$N,Impact_Input!$B:$B,"B",Impact_Input!$C:$C,$A18,Impact_Input!$D:$D,G$17)) -> 0 | H18: =TANH(Parameters!$B$24*SUMIFS(Impact_Input!$N:$N,Impact_Input!$B:$B,"B",Impact_Input!$C:$C,$A18,Impact_Input!$D:$D,H$17)) -> 0
A19: U2 | B19: =TANH(Parameters!$B$24*SUMIFS(Impact_Input!$N:$N,Impact_Input!$B:$B,"B",Impact_Input!$C:$C,$A19,Impact_Input!$D:$D,B$17)) -> -0.0184759 | C19: =TANH(Parameters!$B$24*SUMIFS(Impact_Input!$N:$N,Impact_Input!$B:$B,"B",Impact_Input!$C:$C,$A19,Impact_Input!$D:$D,C$17)) -> 0 | D19: =TANH(Parameters!$B$24*SUMIFS(Impact_Input!$N:$N,Impact_Input!$B:$B,"B",Impact_Input!$C:$C,$A19,Impact_Input!$D:$D,D$17)) -> 0 | E19: =TANH(Parameters!$B$24*SUMIFS(Impact_Input!$N:$N,Impact_Input!$B:$B,"B",Impact_Input!$C:$C,$A19,Impact_Input!$D:$D,E$17)) -> 0 | F19: =TANH(Parameters!$B$24*SUMIFS(Impact_Input!$N:$N,Impact_Input!$B:$B,"B",Impact_Input!$C:$C,$A19,Impact_Input!$D:$D,F$17)) -> 0 | G19: =TANH(Parameters!$B$24*SUMIFS(Impact_Input!$N:$N,Impact_Input!$B:$B,"B",Impact_Input!$C:$C,$A19,Impact_Input!$D:$D,G$17)) -> 0 | H19: =TANH(Parameters!$B$24*SUMIFS(Impact_Input!$N:$N,Impact_Input!$B:$B,"B",Impact_Input!$C:$C,$A19,Impact_Input!$D:$D,H$17)) -> 0
A20: U3 | B20: =TANH(Parameters!$B$24*SUMIFS(Impact_Input!$N:$N,Impact_Input!$B:$B,"B",Impact_Input!$C:$C,$A20,Impact_Input!$D:$D,B$17)) -> 0.013197807 | C20: =TANH(Parameters!$B$24*SUMIFS(Impact_Input!$N:$N,Impact_Input!$B:$B,"B",Impact_Input!$C:$C,$A20,Impact_Input!$D:$D,C$17)) -> 0 | D20: =TANH(Parameters!$B$24*SUMIFS(Impact_Input!$N:$N,Impact_Input!$B:$B,"B",Impact_Input!$C:$C,$A20,Impact_Input!$D:$D,D$17)) -> 0.061515572 | E20: =TANH(Parameters!$B$24*SUMIFS(Impact_Input!$N:$N,Impact_Input!$B:$B,"B",Impact_Input!$C:$C,$A20,Impact_Input!$D:$D,E$17)) -> 0 | F20: =TANH(Parameters!$B$24*SUMIFS(Impact_Input!$N:$N,Impact_Input!$B:$B,"B",Impact_Input!$C:$C,$A20,Impact_Input!$D:$D,F$17)) -> 0 | G20: =TANH(Parameters!$B$24*SUMIFS(Impact_Input!$N:$N,Impact_Input!$B:$B,"B",Impact_Input!$C:$C,$A20,Impact_Input!$D:$D,G$17)) -> 0 | H20: =TANH(Parameters!$B$24*SUMIFS(Impact_Input!$N:$N,Impact_Input!$B:$B,"B",Impact_Input!$C:$C,$A20,Impact_Input!$D:$D,H$17)) -> 0
A21: U4 | B21: =TANH(Parameters!$B$24*SUMIFS(Impact_Input!$N:$N,Impact_Input!$B:$B,"B",Impact_Input!$C:$C,$A21,Impact_Input!$D:$D,B$17)) -> 0.010211456 | C21: =TANH(Parameters!$B$24*SUMIFS(Impact_Input!$N:$N,Impact_Input!$B:$B,"B",Impact_Input!$C:$C,$A21,Impact_Input!$D:$D,C$17)) -> 0 | D21: =TANH(Parameters!$B$24*SUMIFS(Impact_Input!$N:$N,Impact_Input!$B:$B,"B",Impact_Input!$C:$C,$A21,Impact_Input!$D:$D,D$17)) -> 0 | E21: =TANH(Parameters!$B$24*SUMIFS(Impact_Input!$N:$N,Impact_Input!$B:$B,"B",Impact_Input!$C:$C,$A21,Impact_Input!$D:$D,E$17)) -> 0 | F21: =TANH(Parameters!$B$24*SUMIFS(Impact_Input!$N:$N,Impact_Input!$B:$B,"B",Impact_Input!$C:$C,$A21,Impact_Input!$D:$D,F$17)) -> 0 | G21: =TANH(Parameters!$B$24*SUMIFS(Impact_Input!$N:$N,Impact_Input!$B:$B,"B",Impact_Input!$C:$C,$A21,Impact_Input!$D:$D,G$17)) -> 0 | H21: =TANH(Parameters!$B$24*SUMIFS(Impact_Input!$N:$N,Impact_Input!$B:$B,"B",Impact_Input!$C:$C,$A21,Impact_Input!$D:$D,H$17)) -> 0
A22: U5 | B22: =TANH(Parameters!$B$24*SUMIFS(Impact_Input!$N:$N,Impact_Input!$B:$B,"B",Impact_Input!$C:$C,$A22,Impact_Input!$D:$D,B$17)) -> 0 | C22: =TANH(Parameters!$B$24*SUMIFS(Impact_Input!$N:$N,Impact_Input!$B:$B,"B",Impact_Input!$C:$C,$A22,Impact_Input!$D:$D,C$17)) -> 0 | D22: =TANH(Parameters!$B$24*SUMIFS(Impact_Input!$N:$N,Impact_Input!$B:$B,"B",Impact_Input!$C:$C,$A22,Impact_Input!$D:$D,D$17)) -> 0 | E22: =TANH(Parameters!$B$24*SUMIFS(Impact_Input!$N:$N,Impact_Input!$B:$B,"B",Impact_Input!$C:$C,$A22,Impact_Input!$D:$D,E$17)) -> 0 | F22: =TANH(Parameters!$B$24*SUMIFS(Impact_Input!$N:$N,Impact_Input!$B:$B,"B",Impact_Input!$C:$C,$A22,Impact_Input!$D:$D,F$17)) -> 0 | G22: =TANH(Parameters!$B$24*SUMIFS(Impact_Input!$N:$N,Impact_Input!$B:$B,"B",Impact_Input!$C:$C,$A22,Impact_Input!$D:$D,G$17)) -> 0 | H22: =TANH(Parameters!$B$24*SUMIFS(Impact_Input!$N:$N,Impact_Input!$B:$B,"B",Impact_Input!$C:$C,$A22,Impact_Input!$D:$D,H$17)) -> 0
A23: U6 | B23: =TANH(Parameters!$B$24*SUMIFS(Impact_Input!$N:$N,Impact_Input!$B:$B,"B",Impact_Input!$C:$C,$A23,Impact_Input!$D:$D,B$17)) -> 0 | C23: =TANH(Parameters!$B$24*SUMIFS(Impact_Input!$N:$N,Impact_Input!$B:$B,"B",Impact_Input!$C:$C,$A23,Impact_Input!$D:$D,C$17)) -> 0 | D23: =TANH(Parameters!$B$24*SUMIFS(Impact_Input!$N:$N,Impact_Input!$B:$B,"B",Impact_Input!$C:$C,$A23,Impact_Input!$D:$D,D$17)) -> 0 | E23: =TANH(Parameters!$B$24*SUMIFS(Impact_Input!$N:$N,Impact_Input!$B:$B,"B",Impact_Input!$C:$C,$A23,Impact_Input!$D:$D,E$17)) -> 0 | F23: =TANH(Parameters!$B$24*SUMIFS(Impact_Input!$N:$N,Impact_Input!$B:$B,"B",Impact_Input!$C:$C,$A23,Impact_Input!$D:$D,F$17)) -> 0 | G23: =TANH(Parameters!$B$24*SUMIFS(Impact_Input!$N:$N,Impact_Input!$B:$B,"B",Impact_Input!$C:$C,$A23,Impact_Input!$D:$D,G$17)) -> 0 | H23: =TANH(Parameters!$B$24*SUMIFS(Impact_Input!$N:$N,Impact_Input!$B:$B,"B",Impact_Input!$C:$C,$A23,Impact_Input!$D:$D,H$17)) -> 0
A24: U7 | B24: =TANH(Parameters!$B$24*SUMIFS(Impact_Input!$N:$N,Impact_Input!$B:$B,"B",Impact_Input!$C:$C,$A24,Impact_Input!$D:$D,B$17)) -> 0 | C24: =TANH(Parameters!$B$24*SUMIFS(Impact_Input!$N:$N,Impact_Input!$B:$B,"B",Impact_Input!$C:$C,$A24,Impact_Input!$D:$D,C$17)) -> 0 | D24: =TANH(Parameters!$B$24*SUMIFS(Impact_Input!$N:$N,Impact_Input!$B:$B,"B",Impact_Input!$C:$C,$A24,Impact_Input!$D:$D,D$17)) -> 0 | E24: =TANH(Parameters!$B$24*SUMIFS(Impact_Input!$N:$N,Impact_Input!$B:$B,"B",Impact_Input!$C:$C,$A24,Impact_Input!$D:$D,E$17)) -> 0 | F24: =TANH(Parameters!$B$24*SUMIFS(Impact_Input!$N:$N,Impact_Input!$B:$B,"B",Impact_Input!$C:$C,$A24,Impact_Input!$D:$D,F$17)) -> 0 | G24: =TANH(Parameters!$B$24*SUMIFS(Impact_Input!$N:$N,Impact_Input!$B:$B,"B",Impact_Input!$C:$C,$A24,Impact_Input!$D:$D,G$17)) -> 0 | H24: =TANH(Parameters!$B$24*SUMIFS(Impact_Input!$N:$N,Impact_Input!$B:$B,"B",Impact_Input!$C:$C,$A24,Impact_Input!$D:$D,H$17)) -> -0.010211456

Sheet NCRC
A1: LEVEL 1: NON-COMPENSATORY RIGHTS CONSTRAINT (NCRC)
A3: Reference: Ripple_Logic v8.6 Section 7.0
A4: Rule: For each right r, MIN impact across coverage set must be ≥ θ_r
A5: NCRC RIGHTS FLOOR CHECK (Min_I_rights vs θ_r; PASS if Min_I_rights ≥ θ_r)
A6: OPTION A RIGHTS CHECK
A7: Right | B7: Priority | C7: θ_r | D7: Min_I_rights_A | E7: Min_I_rights_B | F7: Pass_A | G7: Pass_B | H7: Worst_Cell_A | I7: Worst_Cell_B
A8: LIFE | B8: 1 | C8: -0.9 | D8: =_xlfn.MINIFS(Rights_Coverage_View!$M$2:$M$71,Rights_Coverage_View!$L$2:$L$71,$A8) -> 0 | E8: =_xlfn.MINIFS(Rights_Coverage_View!$N$2:$N$71,Rights_Coverage_View!$L$2:$L$71,$A8) -> 0 | F8: =IF(D8>=$C8,"PASS","FAIL") -> PASS | G8: =IF(E8>=$C8,"PASS","FAIL") -> PASS | H8: =IFERROR("Rights_Coverage_View!"&ADDRESS(_xludf.aggregate(15,6,ROW(Rights_Coverage_View!$H$2:$H$100)/((Rights_Coverage_View!$B$2:$B$100=$A8)*(Rights_Coverage_View!$H$2:$H$100=D8)*(Rights_Coverage_View!$H$2:$H$100<>"")),1),8,4),"ERR") -> ERR | I8: =IFERROR("Rights_Coverage_View!"&ADDRESS(_xludf.aggregate(15,6,ROW(Rights_Coverage_View!$I$2:$I$100)/((Rights_Coverage_View!$B$2:$B$100=$A8)*(Rights_Coverage_View!$I$2:$I$100=E8)*(Rights_Coverage_View!$I$2:$I$100<>"")),1),9,4),"ERR") -> ERR
A9: BODY | B9: 2 | C9: -0.7 | D9: =_xlfn.MINIFS(Rights_Coverage_View!$M$2:$M$71,Rights_Coverage_View!$L$2:$L$71,$A9) -> 0 | E9: =_xlfn.MINIFS(Rights_Coverage_View!$N$2:$N$71,Rights_Coverage_View!$L$2:$L$71,$A9) -> 0 | F9: =IF(D9>=$C9,"PASS","FAIL") -> PASS | G9: =IF(E9>=$C9,"PASS","FAIL") -> PASS | H9: =IFERROR("Rights_Coverage_View!"&ADDRESS(_xludf.aggregate(15,6,ROW(Rights_Coverage_View!$H$2:$H$100)/((Rights_Coverage_View!$B$2:$B$100=$A9)*(Rights_Coverage_View!$H$2:$H$100=D9)*(Rights_Coverage_View!$H$2:$H$100<>"")),1),8,4),"ERR") -> ERR | I9: =IFERROR("Rights_Coverage_View!"&ADDRESS(_xludf.aggregate(15,6,ROW(Rights_Coverage_View!$I$2:$I$100)/((Rights_Coverage_View!$B$2:$B$100=$A9)*(Rights_Coverage_View!$I$2:$I$100=E9)*(Rights_Coverage_View!$I$2:$I$100<>"")),1),9,4),"ERR") -> ERR
A10: ECOL | B10: 3 | C10: -0.65 | D10: =_xlfn.MINIFS(Rights_Coverage_View!$M$2:$M$71,Rights_Coverage_View!$L$2:$L$71,$A10) -> 0 | E10: =_xlfn.MINIFS(Rights_Coverage_View!$N$2:$N$71,Rights_Coverage_View!$L$2:$L$71,$A10) -> -0.010211456 | F10: =IF(D10>=$C10,"PASS","FAIL") -> PASS | G10: =IF(E10>=$C10,"PASS","FAIL") -> PASS | H10: =IFERROR("Rights_Coverage_View!"&ADDRESS(_xludf.aggregate(15,6,ROW(Rights_Coverage_View!$H$2:$H$100)/((Rights_Coverage_View!$B$2:$B$100=$A10)*(Rights_Coverage_View!$H$2:$H$100=D10)*(Rights_Coverage_View!$H$2:$H$100<>"")),1),8,4),"ERR") -> ERR | I10: =IFERROR("Rights_Coverage_View!"&ADDRESS(_xludf.aggregate(15,6,ROW(Rights_Coverage_View!$I$2:$I$100)/((Rights_Coverage_View!$B$2:$B$100=$A10)*(Rights_Coverage_View!$I$2:$I$100=E10)*(Rights_Coverage_View!$I$2:$I$100<>"")),1),9,4),"ERR") -> ERR
A11: LBTY | B11: 4 | C11: -0.65 | D11: =_xlfn.MINIFS(Rights_Coverage_View!$M$2:$M$71,Rights_Coverage_View!$L$2:$L$71,$A11) -> -0.080725687 | E11: =_xlfn.MINIFS(Rights_Coverage_View!$N$2:$N$71,Rights_Coverage_View!$L$2:$L$71,$A11) -> -0.046333568 | F11: =IF(D11>=$C11,"PASS","FAIL") -> PASS | G11: =IF(E11>=$C11,"PASS","FAIL") -> PASS | H11: =IFERROR("Rights_Coverage_View!"&ADDRESS(_xludf.aggregate(15,6,ROW(Rights_Coverage_View!$H$2:$H$100)/((Rights_Coverage_View!$B$2:$B$100=$A11)*(Rights_Coverage_View!$H$2:$H$100=D11)*(Rights_Coverage_View!$H$2:$H$100<>"")),1),8,4),"ERR") -> ERR | I11: =IFERROR("Rights_Coverage_View!"&ADDRESS(_xludf.aggregate(15,6,ROW(Rights_Coverage_View!$I$2:$I$100)/((Rights_Coverage_View!$B$2:$B$100=$A11)*(Rights_Coverage_View!$I$2:$I$100=E11)*(Rights_Coverage_View!$I$2:$I$100<>"")),1),9,4),"ERR") -> ERR
A12: NEED | B12: 5 | C12: -0.5 | D12: =_xlfn.MINIFS(Rights_Coverage_View!$M$2:$M$71,Rights_Coverage_View!$L$2:$L$71,$A12) -> -0.085569436 | E12: =_xlfn.MINIFS(Rights_Coverage_View!$N$2:$N$71,Rights_Coverage_View!$L$2:$L$71,$A12) -> -0.0184759 | F12: =IF(D12>=$C12,"PASS","FAIL") -> PASS | G12: =IF(E12>=$C12,"PASS","FAIL") -> PASS | H12: =IFERROR("Rights_Coverage_View!"&ADDRESS(_xludf.aggregate(15,6,ROW(Rights_Coverage_View!$H$2:$H$100)/((Rights_Coverage_View!$B$2:$B$100=$A12)*(Rights_Coverage_View!$H$2:$H$100=D12)*(Rights_Coverage_View!$H$2:$H$100<>"")),1),8,4),"ERR") -> ERR | I12: =IFERROR("Rights_Coverage_View!"&ADDRESS(_xludf.aggregate(15,6,ROW(Rights_Coverage_View!$I$2:$I$100)/((Rights_Coverage_View!$B$2:$B$100=$A12)*(Rights_Coverage_View!$I$2:$I$100=E12)*(Rights_Coverage_View!$I$2:$I$100<>"")),1),9,4),"ERR") -> ERR
A13: DIGN | B13: 6 | C13: -0.55 | D13: =_xlfn.MINIFS(Rights_Coverage_View!$M$2:$M$71,Rights_Coverage_View!$L$2:$L$71,$A13) -> -0.080725687 | E13: =_xlfn.MINIFS(Rights_Coverage_View!$N$2:$N$71,Rights_Coverage_View!$L$2:$L$71,$A13) -> -0.046333568 | F13: =IF(D13>=$C13,"PASS","FAIL") -> PASS | G13: =IF(E13>=$C13,"PASS","FAIL") -> PASS | H13: =IFERROR("Rights_Coverage_View!"&ADDRESS(_xludf.aggregate(15,6,ROW(Rights_Coverage_View!$H$2:$H$100)/((Rights_Coverage_View!$B$2:$B$100=$A13)*(Rights_Coverage_View!$H$2:$H$100=D13)*(Rights_Coverage_View!$H$2:$H$100<>"")),1),8,4),"ERR") -> ERR | I13: =IFERROR("Rights_Coverage_View!"&ADDRESS(_xludf.aggregate(15,6,ROW(Rights_Coverage_View!$I$2:$I$100)/((Rights_Coverage_View!$B$2:$B$100=$A13)*(Rights_Coverage_View!$I$2:$I$100=E13)*(Rights_Coverage_View!$I$2:$I$100<>"")),1),9,4),"ERR") -> ERR
A14: PROC | B14: 7 | C14: -0.45 | D14: =_xlfn.MINIFS(Rights_Coverage_View!$M$2:$M$71,Rights_Coverage_View!$L$2:$L$71,$A14) -> 0 | E14: =_xlfn.MINIFS(Rights_Coverage_View!$N$2:$N$71,Rights_Coverage_View!$L$2:$L$71,$A14) -> 0 | F14: =IF(D14>=$C14,"PASS","FAIL") -> PASS | G14: =IF(E14>=$C14,"PASS","FAIL") -> PASS | H14: =IFERROR("Rights_Coverage_View!"&ADDRESS(_xludf.aggregate(15,6,ROW(Rights_Coverage_View!$H$2:$H$100)/((Rights_Coverage_View!$B$2:$B$100=$A14)*(Rights_Coverage_View!$H$2:$H$100=D14)*(Rights_Coverage_View!$H$2:$H$100<>"")),1),8,4),"ERR") -> ERR | I14: =IFERROR("Rights_Coverage_View!"&ADDRESS(_xludf.aggregate(15,6,ROW(Rights_Coverage_View!$I$2:$I$100)/((Rights_Coverage_View!$B$2:$B$100=$A14)*(Rights_Coverage_View!$I$2:$I$100=E14)*(Rights_Coverage_View!$I$2:$I$100<>"")),1),9,4),"ERR") -> ERR
A15: INFO | B15: 8 | C15: -0.4 | D15: =_xlfn.MINIFS(Rights_Coverage_View!$M$2:$M$71,Rights_Coverage_View!$L$2:$L$71,$A15) -> 0 | E15: =_xlfn.MINIFS(Rights_Coverage_View!$N$2:$N$71,Rights_Coverage_View!$L$2:$L$71,$A15) -> -0.046333568 | F15: =IF(D15>=$C15,"PASS","FAIL") -> PASS | G15: =IF(E15>=$C15,"PASS","FAIL") -> PASS | H15: =IFERROR("Rights_Coverage_View!"&ADDRESS(_xludf.aggregate(15,6,ROW(Rights_Coverage_View!$H$2:$H$100)/((Rights_Coverage_View!$B$2:$B$100=$A15)*(Rights_Coverage_View!$H$2:$H$100=D15)*(Rights_Coverage_View!$H$2:$H$100<>"")),1),8,4),"ERR") -> ERR | I15: =IFERROR("Rights_Coverage_View!"&ADDRESS(_xludf.aggregate(15,6,ROW(Rights_Coverage_View!$I$2:$I$100)/((Rights_Coverage_View!$B$2:$B$100=$A15)*(Rights_Coverage_View!$I$2:$I$100=E15)*(Rights_Coverage_View!$I$2:$I$100<>"")),1),9,4),"ERR") -> ERR
D16: =MIN(D8:D15) -> -0.085569436 | E16: =MIN(E8:E15) -> -0.046333568
A17: NCRC OUTCOME
A18: Option A: | B18: PASS (all rights satisfied) | C18: NCRC_A_status | D18: =IF(COUNTIF(F8:F15,"FAIL")=0,"PASS","FAIL") -> PASS | E18: (All v_r = 0)
A19: Option B: | B19: PASS (all rights satisfied) | C19: NCRC_B_status | D19: =IF(COUNTIF(G8:G15,"FAIL")=0,"PASS","FAIL") -> PASS
A20: Note: Proof Snippet columns (H:I) show the exact Rights_Coverage_View cell holding the worst-off I_rights value for each right (A and B).
A21: OPTION B RIGHTS CHECK
A22: Right | B22: Priority | C22: θ_r | D22: 0 | E22: 0 | F22: PASS
A23: LIFE | B23: 1 | C23: -0.9 | D23: 0 | E23: 0 | F23: PASS
A24: BODY | B24: 2 | C24: -0.7 | D24: -0.010211 | E24: 0 | F24: PASS
A25: ECOL | B25: 3 | C25: -0.65 | D25: -0.046334 | E25: 0 | F25: PASS
A26: LBTY | B26: 4 | C26: -0.65 | D26: -0.018476 | E26: 0 | F26: PASS
A27: NEED | B27: 5 | C27: -0.5 | D27: -0.046334 | E27: 0 | F27: PASS
A28: DIGN | B28: 6 | C28: -0.55 | D28: 0 | E28: 0 | F28: PASS
A29: PROC | B29: 7 | C29: -0.45 | D29: =MIN(IF(Rights_Coverage_View!$B$2:$B$71="PROC",Rights_Coverage_View!$I$2:$I$71,1)) -> 1 | E29: =MAX(0,C29-D29) -> 0 | F29: =IF(E29=0,"PASS","FAIL") -> PASS
A30: INFO | B30: 8 | C30: -0.4 | D30: 0 | E30: 0 | F30: PASS
A33: Overall NCRC status (B): | D33: =IF(COUNTIF(F23:F30,"FAIL")=0,"PASS","FAIL") -> PASS | E33: (All v_r = 0)
A34: Overall NCRC status (B)
A35: NCRC OUTCOME
A36: A_NCRC (Rights-Admissible): | B36: {A, B}
A37: Emergency Mode: | B37: NOT INVOKED
A38: Both options are rights-admissible
A39: Emergency Mode: NOT INVOKED

Sheet TRC
A1: LEVEL 2: TAIL RISK CONSTRAINT (TRC)
A3: Reference: Ripple_Logic v8.6 Appendix D.7
A4: Algorithm: Discrete CVaR with sorted-tail method
A6: PARAMETERS
A7: α (confidence): | B7: 0.95 | M7: SortKey | N7: Rank | P7: Sorted scenarios
A8: β (tail mass): | B8: 0.05 | M8: =L8+ROW()/1000000 -> 8e-06 | N8: =RANK(M8,$M$8:$M$14,0) -> 7 | P8: Scenario | Q8: p(s) | R8: Loss | S8: Cum_p | T8: Tail_w | U8: Tail_contrib
A9: τ_TRC (threshold): | B9: =CANON!B58 -> 0.2 | M9: =L9+ROW()/1000000 -> 9e-06 | N9: =RANK(M9,$M$8:$M$14,0) -> 6 | P9: =INDEX($J$8:$J$14,MATCH(1,$N$8:$N$14,0)) -> 0 | Q9: =IFERROR(VLOOKUP(P9,$J$8:$L$14,2,FALSE()),"") | R9: =IFERROR(VLOOKUP(P9,$J$8:$L$14,3,FALSE()),"") | S9: =IFERROR(Q9,"") | U9: =IFERROR(T9*R9,"")
A10: Context: | B10: ORG | M10: =L10+ROW()/1000000 -> 1e-05 | N10: =RANK(M10,$M$8:$M$14,0) -> 5 | P10: =INDEX($J$8:$J$14,MATCH(2,$N$8:$N$14,0)) -> 0 | Q10: =IFERROR(VLOOKUP(P10,$J$8:$L$14,2,FALSE()),"") | R10: =IFERROR(VLOOKUP(P10,$J$8:$L$14,3,FALSE()),"") | S10: =IFERROR(S9+Q10,"") | U10: =IFERROR(T10*R10,"")
M11: =L11+ROW()/1000000 -> 1.1e-05 | N11: =RANK(M11,$M$8:$M$14,0) -> 4 | P11: =INDEX($J$8:$J$14,MATCH(3,$N$8:$N$14,0)) -> 0 | Q11: =IFERROR(VLOOKUP(P11,$J$8:$L$14,2,FALSE()),"") | R11: =IFERROR(VLOOKUP(P11,$J$8:$L$14,3,FALSE()),"") | S11: =IFERROR(S10+Q11,"") | U11: =IFERROR(T11*R11,"")
A12: OPTION A: CVaR COMPUTATION | M12: =L12+ROW()/1000000 -> 1.2e-05 | N12: =RANK(M12,$M$8:$M$14,0) -> 3 | P12: =INDEX($J$8:$J$14,MATCH(4,$N$8:$N$14,0)) -> 0 | Q12: =IFERROR(VLOOKUP(P12,$J$8:$L$14,2,FALSE()),"") | R12: =IFERROR(VLOOKUP(P12,$J$8:$L$14,3,FALSE()),"") | S12: =IFERROR(S11+Q12,"") | U12: =IFERROR(T12*R12,"")
A13: Step 1: Sort scenarios by Loss DESCENDING | M13: =L13+ROW()/1000000 -> 1.3e-05 | N13: =RANK(M13,$M$8:$M$14,0) -> 2 | P13: =INDEX($J$8:$J$14,MATCH(5,$N$8:$N$14,0)) -> 0 | Q13: =IFERROR(VLOOKUP(P13,$J$8:$L$14,2,FALSE()),"") | R13: =IFERROR(VLOOKUP(P13,$J$8:$L$14,3,FALSE()),"") | S13: =IFERROR(S12+Q13,"") | U13: =IFERROR(T13*R13,"")
A14: Rank | B14: Scenario | C14: Loss | D14: p(s) | E14: Cum_p | F14: In Tail | G14: Tail_Weight | H14: Contribution | M14: =L14+ROW()/1000000 -> 1.4e-05 | N14: =RANK(M14,$M$8:$M$14,0) -> 1 | P14: =INDEX($J$8:$J$14,MATCH(6,$N$8:$N$14,0)) -> 0 | Q14: =IFERROR(VLOOKUP(P14,$J$8:$L$14,2,FALSE()),"") | R14: =IFERROR(VLOOKUP(P14,$J$8:$L$14,3,FALSE()),"") | S14: =IFERROR(S13+Q14,"") | U14: =IFERROR(T14*R14,"")
A15: 1 | B15: S06 | C15: 0.0235 | D15: 0.03 | E15: 0.03 | F15: YES | G15: 0.03 | H15: 0.000705 | P15: =INDEX($J$8:$J$14,MATCH(7,$N$8:$N$14,0)) -> 0 | Q15: =IFERROR(VLOOKUP(P15,$J$8:$L$14,2,FALSE()),"") | R15: =IFERROR(VLOOKUP(P15,$J$8:$L$14,3,FALSE()),"") | S15: =IFERROR(S14+Q15,"") | U15: =IFERROR(T15*R15,"")
A16: 2 | B16: S04 | C16: 0.0195 | D16: 0.07 | E16: 0.1 | F16: PARTIAL | G16: 0.02 | H16: 0.00039
A17: 3 | B17: S03 | C17: 0.0175 | D17: 0.08 | E17: 0.18 | F17: NO | G17: 0 | H17: 0
A18: 4 | B18: S05 | C18: 0.0135 | D18: 0.05 | E18: 0.23 | F18: NO | G18: 0 | H18: 0 | M18: SortKey | N18: Rank | P18: Sorted scenarios
A19: 5 | B19: S07 | C19: 0.01 | D19: 0.02 | E19: 0.25 | F19: NO | G19: 0 | H19: 0 | M19: =L19+ROW()/1000000 -> 1.9e-05 | N19: =RANK(M19,$M$19:$M$25,0) -> 7 | P19: Scenario | Q19: p(s) | R19: Loss | S19: Cum_p | T19: Tail_w | U19: Tail_contrib
A20: 6 | B20: S02 | C20: 0.007 | D20: 0.15 | E20: 0.4 | F20: NO | G20: 0 | H20: 0 | M20: =L20+ROW()/1000000 -> 2e-05 | N20: =RANK(M20,$M$19:$M$25,0) -> 6 | P20: =INDEX($J$19:$J$25,MATCH(1,$N$19:$N$25,0)) -> 0 | Q20: =IFERROR(VLOOKUP(P20,$J$19:$L$25,2,FALSE()),"") | R20: =IFERROR(VLOOKUP(P20,$J$19:$L$25,3,FALSE()),"") | S20: =IFERROR(Q20,"") | U20: =IFERROR(T20*R20,"")
A21: 7 | B21: S01 | C21: 0 | D21: 0.6 | E21: 1 | F21: NO | G21: 0 | H21: 0 | M21: =L21+ROW()/1000000 -> 2.1e-05 | N21: =RANK(M21,$M$19:$M$25,0) -> 5 | P21: =INDEX($J$19:$J$25,MATCH(2,$N$19:$N$25,0)) -> 0 | Q21: =IFERROR(VLOOKUP(P21,$J$19:$L$25,2,FALSE()),"") | R21: =IFERROR(VLOOKUP(P21,$J$19:$L$25,3,FALSE()),"") | S21: =IFERROR(S20+Q21,"") | U21: =IFERROR(T21*R21,"")
M22: =L22+ROW()/1000000 -> 2.2e-05 | N22: =RANK(M22,$M$19:$M$25,0) -> 4 | P22: =INDEX($J$19:$J$25,MATCH(3,$N$19:$N$25,0)) -> 0 | Q22: =IFERROR(VLOOKUP(P22,$J$19:$L$25,2,FALSE()),"") | R22: =IFERROR(VLOOKUP(P22,$J$19:$L$25,3,FALSE()),"") | S22: =IFERROR(S21+Q22,"") | U22: =IFERROR(T22*R22,"")
A23: Step 2: CVaR_A = Σ(Contribution) / β | M23: =L23+ROW()/1000000 -> 2.3e-05 | N23: =RANK(M23,$M$19:$M$25,0) -> 3 | P23: =INDEX($J$19:$J$25,MATCH(4,$N$19:$N$25,0)) -> 0 | Q23: =IFERROR(VLOOKUP(P23,$J$19:$L$25,2,FALSE()),"") | R23: =IFERROR(VLOOKUP(P23,$J$19:$L$25,3,FALSE()),"") | S23: =IFERROR(S22+Q23,"") | U23: =IFERROR(T23*R23,"")
A24: Sum of contributions: | B24: 0.001095 | M24: =L24+ROW()/1000000 -> 2.4e-05 | N24: =RANK(M24,$M$19:$M$25,0) -> 2 | P24: =INDEX($J$19:$J$25,MATCH(5,$N$19:$N$25,0)) -> 0 | Q24: =IFERROR(VLOOKUP(P24,$J$19:$L$25,2,FALSE()),"") | R24: =IFERROR(VLOOKUP(P24,$J$19:$L$25,3,FALSE()),"") | S24: =IFERROR(S23+Q24,"") | U24: =IFERROR(T24*R24,"")
A25: CVaR_A: | B25: 0.0219 | M25: =L25+ROW()/1000000 -> 2.5e-05 | N25: =RANK(M25,$M$19:$M$25,0) -> 1 | P25: =INDEX($J$19:$J$25,MATCH(6,$N$19:$N$25,0)) -> 0 | Q25: =IFERROR(VLOOKUP(P25,$J$19:$L$25,2,FALSE()),"") | R25: =IFERROR(VLOOKUP(P25,$J$19:$L$25,3,FALSE()),"") | S25: =IFERROR(S24+Q25,"") | U25: =IFERROR(T25*R25,"")
A26: Status: | B26: PASS | C26: (CVaR_A = 0.0219 ≤ τ_TRC = 0.20) | P26: =INDEX($J$19:$J$25,MATCH(7,$N$19:$N$25,0)) -> 0 | Q26: =IFERROR(VLOOKUP(P26,$J$19:$L$25,2,FALSE()),"") | R26: =IFERROR(VLOOKUP(P26,$J$19:$L$25,3,FALSE()),"") | S26: =IFERROR(S25+Q26,"") | U26: =IFERROR(T26*R26,"")
A29: OPTION B: CVaR COMPUTATION
A30: Rank | B30: Scenario | C30: Loss | D30: p(s) | E30: Cum_p | F30: In Tail | G30: Tail_Weight | H30: Contribution
A31: 1 | B31: S03 | C31: 0.0315 | D31: 0.08 | E31: 0.08 | F31: PARTIAL | G31: 0.05 | H31: 0.001575
A32: 2 | B32: S04 | C32: 0.0235 | D32: 0.07 | E32: 0.15 | F32: NO | G32: 0 | H32: 0
A33: 3 | B33: S06 | C33: 0.02175 | D33: 0.03 | E33: 0.18 | F33: NO | G33: 0 | H33: 0
A34: 4 | B34: S05 | C34: 0.0135 | D34: 0.05 | E34: 0.23 | F34: NO | G34: 0 | H34: 0
A35: 5 | B35: S02 | C35: 0.0105 | D35: 0.15 | E35: 0.38 | F35: NO | G35: 0 | H35: 0
A36: 6 | B36: S07 | C36: 0.007 | D36: 0.02 | E36: 0.4 | F36: NO | G36: 0 | H36: 0
A37: 7 | B37: S01 | C37: 0.003574 | D37: 0.6 | E37: 1 | F37: NO | G37: 0 | H37: 0
A39: Step 2: CVaR_B = Σ(Contribution) / β
A40: Sum of contributions: | B40: 0.001575
A41: CVaR_B: | B41: 0.0315
A42: Status: | B42: PASS | C42: (CVaR_B = 0.0315 ≤ τ_TRC = 0.20)
A43: =IF(Dashboard!$B$36="YES"," 2nd: Option "&IF($H$15<=$H$28,"B","A")&" (CVaR = "&TEXT(MAX($H$15,$H$28),"0.000")&")","")
A45: TRC OUTCOME
A46: A_adm = {A, B}
A47: TRC Mode: NORMAL (both options pass)
A48: Cascade proceeds to Containment (Level 3)

Sheet Containment
A1: LEVEL 3: CONTAINMENT CONSTRAINT (Tier 2 proxy: union-score diagnostic)
J2: Containment computed
A3: Reference: Section 9.0 (Full ΔUCI containment is Tier 3+ binding; Tier 2 uses proxy display here) [v8.6] | J3: θ_pos | K3: =CANON!B23 -> 0.05
A4: ="θ_pos = "&TEXT(Parameters!$B$28,"0.00")&" | τ_c = "&TEXT(Parameters!$B$27,"0.00") -> θ_pos = 0.05 | τ_c = -0.10 | J4: τ_c | K4: =CANON!B24 -> -0.1
A5: =IF(Dashboard!$B$36="YES","NOTE: Informational only (TRC fallback active).","NOTE: Normal mode (containment evaluated for admissible options).") -> NOTE: Normal mode (containment evaluated for admissible options). | J5: Union | K5: S_u(A) | L5: S_u(B)
J6: U1 | K6: =(I_prop!B7+I_prop!C7+I_prop!D7+I_prop!E7+I_prop!F7+I_prop!G7+I_prop!H7)/7 -> 0.056038249 | L6: =(I_prop!B18+I_prop!C18+I_prop!D18+I_prop!E18+I_prop!F18+I_prop!G18+I_prop!H18)/7 -> -0.0066190811
A7: OPTION A: UNION SCORES | J7: U2 | K7: =(I_prop!B8+I_prop!C8+I_prop!D8+I_prop!E8+I_prop!F8+I_prop!G8+I_prop!H8)/7 -> 0.0065945966 | L7: =(I_prop!B19+I_prop!C19+I_prop!D19+I_prop!E19+I_prop!F19+I_prop!G19+I_prop!H19)/7 -> -0.0026394143
A8: Union | B8: 0.056 | C8: YES | J8: U3 | K8: =(I_prop!B9+I_prop!C9+I_prop!D9+I_prop!E9+I_prop!F9+I_prop!G9+I_prop!H9)/7 -> -0.014360137 | L8: =(I_prop!B20+I_prop!C20+I_prop!D20+I_prop!E20+I_prop!F20+I_prop!G20+I_prop!H20)/7 -> 0.01067334
A9: U1 | B9: 0.0066 | C9: NO | J9: U4 | K9: =(I_prop!B10+I_prop!C10+I_prop!D10+I_prop!E10+I_prop!F10+I_prop!G10+I_prop!H10)/7 -> -0.012224205 | L9: =(I_prop!B21+I_prop!C21+I_prop!D21+I_prop!E21+I_prop!F21+I_prop!G21+I_prop!H21)/7 -> 0.0014587794
A10: U2 | B10: -0.0144 | C10: NO | J10: U5 | K10: =(I_prop!B11+I_prop!C11+I_prop!D11+I_prop!E11+I_prop!F11+I_prop!G11+I_prop!H11)/7 -> 0 | L10: =(I_prop!B22+I_prop!C22+I_prop!D22+I_prop!E22+I_prop!F22+I_prop!G22+I_prop!H22)/7 -> 0
A11: U3 | B11: -0.0122 | C11: NO | J11: U6 | K11: =(I_prop!B12+I_prop!C12+I_prop!D12+I_prop!E12+I_prop!F12+I_prop!G12+I_prop!H12)/7 -> 0 | L11: =(I_prop!B23+I_prop!C23+I_prop!D23+I_prop!E23+I_prop!F23+I_prop!G23+I_prop!H23)/7 -> 0
A12: U4 | B12: 0 | C12: NO | J12: U7 | K12: =(I_prop!B13+I_prop!C13+I_prop!D13+I_prop!E13+I_prop!F13+I_prop!G13+I_prop!H13)/7 -> 0.002188074 | L12: =(I_prop!B24+I_prop!C24+I_prop!D24+I_prop!E24+I_prop!F24+I_prop!G24+I_prop!H24)/7 -> -0.0014587794
A13: U5 | B13: 0 | C13: NO
A14: U6 | B14: 0.0022 | C14: NO | J14: Containment_Status_A | K14: =IF(COUNTIF($K$6:$K$12,">="&$K$3)=0,"PASS (vacuous)",IF(0>=$K$4,"PASS","FAIL")) -> PASS
A15: U7 | C15: NO | J15: Containment_Status_B | K15: =IF(COUNTIF($L$6:$L$12,">="&$K$3)=0,"PASS (vacuous)",IF(0>=$K$4,"PASS","FAIL")) -> PASS (vacuous)
A16: U_pos(A) = {U1} (U1 ≥ 0.05)
A18: Containment_A: PASS (vacuous)
A20: OPTION B: UNION SCORES
A21: Union | B21: -0.0066 | C21: NO
A22: U1 | B22: -0.0026 | C22: NO
A23: U2 | B23: 0.0107 | C23: NO
A24: U3 | B24: 0.0015 | C24: NO
A25: U4 | B25: 0 | C25: NO
A26: U5 | B26: 0 | C26: NO
A27: U6 | B27: -0.0015 | C27: NO
A28: U7 | C28: NO
A29: U_pos(B) = ∅ (no union ≥ 0.05)
A30: Containment_B: PASS (vacuous)
A31: Containment_B: PASS (vacuous)
A32: CONTAINMENT OUTCOME
A33: A_sel (Selectable): {A, B}
A34: Cascade proceeds to RLS (Level 4)
A35: =IF(Dashboard!$B$36="YES","NOTE: Informational only (TRC fallback active).","NOTE: Normal mode (containment evaluated for admissible options).") -> NOTE: Normal mode (containment evaluated for admissible options).

Sheet RLS
A1: LEVEL 4: RIPPLE LOGIC SCORE
A3: Reference: Ripple_Logic v8.6 Section 10.0
A4: RLS = Σ_u Σ_d w_u × v_d × m(u,d) × κ(u,d) × I_prop_welfare(u,d,a)
B5: 0.005462
B6: 0.000202 | C6: =B61 -> 0.015312943
A7: OPTION A RLS COMPUTATION | B7: Computed RLS(B): | C7: =B62 -> -0.0011223874
A9: Union-Dimension Contributions:
A10: U1-D5 | B10: 0.138 | C10: 0.00282
A11: U1-D6 | B11: 0.098 | C11: 0.002
A12: U2-D1 | B12: =INDEX(I_prop!$B$7:$H$13, MATCH("U2", I_prop!$A$7:$A$13,0), MATCH("D1", I_prop!$B$6:$H$6,0)) -> 0.046162176
A13: U3-D1 | B13: =INDEX(I_prop!$B$7:$H$13, MATCH("U3", I_prop!$A$7:$A$13,0), MATCH("D1", I_prop!$B$6:$H$6,0)) -> -0.019795274
A14: U3-D3 | B14: =INDEX(I_prop!$B$7:$H$13, MATCH("U3", I_prop!$A$7:$A$13,0), MATCH("D3", I_prop!$B$6:$H$6,0)) -> -0.080725687
A15: U4-D1 | B15: =INDEX(I_prop!$B$7:$H$13, MATCH("U4", I_prop!$A$7:$A$13,0), MATCH("D1", I_prop!$B$6:$H$6,0)) -> -0.085569436
A16: U7-D7 | B16: =INDEX(I_prop!$B$7:$H$13, MATCH("U7", I_prop!$A$7:$A$13,0), MATCH("D7", I_prop!$B$6:$H$6,0)) -> 0.015316518
A17: RLS(A) = 0.005462
A21: OPTION B RLS COMPUTATION
A22: U1-D5 | B22: -0.073 | C22: -0.00149
A23: U2-D1 | B23: =INDEX(I_prop!$B$18:$H$24, MATCH("U2", I_prop!$A$18:$A$24,0), MATCH("D1", I_prop!$B$17:$H$17,0)) -> -0.0184759
A24: U3-D1 | B24: =INDEX(I_prop!$B$18:$H$24, MATCH("U3", I_prop!$A$18:$A$24,0), MATCH("D1", I_prop!$B$17:$H$17,0)) -> 0.013197807
A25: U3-D3 | B25: =INDEX(I_prop!$B$18:$H$24, MATCH("U3", I_prop!$A$18:$A$24,0), MATCH("D3", I_prop!$B$17:$H$17,0)) -> 0.061515572
A26: U4-D1 | B26: =INDEX(I_prop!$B$18:$H$24, MATCH("U4", I_prop!$A$18:$A$24,0), MATCH("D1", I_prop!$B$17:$H$17,0)) -> 0.010211456
A27: U7-D7 | B27: =INDEX(I_prop!$B$18:$H$24, MATCH("U7", I_prop!$A$18:$A$24,0), MATCH("D7", I_prop!$B$17:$H$17,0)) -> -0.010211456
A28: RLS(B) = 0.000202
A32: RLS COMPARISON
A33: RLS(A) = 0.005462
A34: RLS(B) = 0.000202
A35: Gap = 0.00526
A36: σ_est = 0.02
A37: ="Gap/√(2σ²+ε) = "&TEXT(ABS(CANON!B63-CANON!B64)/SQRT(2*CANON!B26^2+0.000001),"0.000")&" < δ = "&TEXT(CANON!B22,"0.###") -> Gap/√(2σ²+ε) = 0.186 < δ = 2
A38: RLS OUTCOME: NON-DECISIVE
A39: Higher RLS: Option A (proceed to tie-break)
A41: RLS OUTCOME
A42: RLS would favor A (higher score) but gap not decisive
A44: Per Section 10.0: RLS MUST NEVER override NCRC or TRC
A50: CALC BLOCK (v1.5): RLS computed from I_prop and weights
B51: D1 | C51: D2 | D51: D3 | E51: D4 | F51: D5 | G51: D6 | H51: D7 | I51: w_u
A52: Union | B52: =Parameters!$B$48 -> 0.14285714 | C52: =Parameters!$B$49 -> 0.14285714 | D52: =Parameters!$B$50 -> 0.14285714 | E52: =Parameters!$B$51 -> 0.14285714 | F52: =Parameters!$B$52 -> 0.14285714 | G52: =Parameters!$B$53 -> 0.14285714 | H52: =Parameters!$B$54 -> 0.14285714
A53: U1 | B53: =$I53*B52 -> 0.043952381 | C53: =$I53*C52 -> 0.043952381 | D53: =$I53*D52 -> 0.043952381 | E53: =$I53*E52 -> 0.043952381 | F53: =$I53*F52 -> 0.043952381 | G53: =$I53*G52 -> 0.043952381 | H53: =$I53*H52 -> 0.043952381 | I53: =Parameters!$B$38 -> 0.30766667
A54: U2 | B54: =$I54*B52 -> 0.022333333 | C54: =$I54*C52 -> 0.022333333 | D54: =$I54*D52 -> 0.022333333 | E54: =$I54*E52 -> 0.022333333 | F54: =$I54*F52 -> 0.022333333 | G54: =$I54*G52 -> 0.022333333 | H54: =$I54*H52 -> 0.022333333 | I54: =Parameters!$B$39 -> 0.15633333
A55: U3 | B55: =$I55*B52 -> 0.01747619 | C55: =$I55*C52 -> 0.01747619 | D55: =$I55*D52 -> 0.01747619 | E55: =$I55*E52 -> 0.01747619 | F55: =$I55*F52 -> 0.01747619 | G55: =$I55*G52 -> 0.01747619 | H55: =$I55*H52 -> 0.01747619 | I55: =Parameters!$B$40 -> 0.12233333
A56: U4 | B56: =$I56*B52 -> 0.016666667 | C56: =$I56*C52 -> 0.016666667 | D56: =$I56*D52 -> 0.016666667 | E56: =$I56*E52 -> 0.016666667 | F56: =$I56*F52 -> 0.016666667 | G56: =$I56*G52 -> 0.016666667 | H56: =$I56*H52 -> 0.016666667 | I56: =Parameters!$B$41 -> 0.11666667
A57: U5 | B57: =$I57*B52 -> 0.013047619 | C57: =$I57*C52 -> 0.013047619 | D57: =$I57*D52 -> 0.013047619 | E57: =$I57*E52 -> 0.013047619 | F57: =$I57*F52 -> 0.013047619 | G57: =$I57*G52 -> 0.013047619 | H57: =$I57*H52 -> 0.013047619 | I57: =Parameters!$B$42 -> 0.091333333
A58: U6 | B58: =$I58*B52 -> 0.014771429 | C58: =$I58*C52 -> 0.014771429 | D58: =$I58*D52 -> 0.014771429 | E58: =$I58*E52 -> 0.014771429 | F58: =$I58*F52 -> 0.014771429 | G58: =$I58*G52 -> 0.014771429 | H58: =$I58*H52 -> 0.014771429 | I58: =Parameters!$B$43 -> 0.1034
A59: U7 | B59: =$I59*B52 -> 0.014609524 | C59: =$I59*C52 -> 0.014609524 | D59: =$I59*D52 -> 0.014609524 | E59: =$I59*E52 -> 0.014609524 | F59: =$I59*F52 -> 0.014609524 | G59: =$I59*G52 -> 0.014609524 | H59: =$I59*H52 -> 0.014609524 | I59: =Parameters!$B$44 -> 0.10226667
A61: RLS(A) | B61: =SUMPRODUCT(I_prop!$B$7:$H$13, $B$53:$H$59) -> 0.015312943
A62: RLS(B) | B62: =SUMPRODUCT(I_prop!$B$18:$H$24, $B$53:$H$59) -> -0.0011223874
A63: Preferred by RLS (higher) | B63: =IF(B61>B62,"A",IF(B62>B61,"B","TIE")) -> A

Sheet UCI_HOI
A1: LEVEL 5: TIE-BREAK METRICS
A3: Reference: Ripple_Logic v8.6 Section 11.0
A4: HOI = Hollowing-Out Index (canonical per v8.6)
A5: Per Section 11: Used when RLS is non-decisive
A8: UCI computes structural condition, independent of welfare impacts.
A9: Per union u: UCI_u = (Cohesion + Flow + Resilience + Equity) / 4
A10: Overall: UCI = average(UCI_u) across unions (Tier 2).
A11: R = Review cycle, E = Evidence quality
A12: (Tier 3: sources/provenance required; UCI must be structurally independent of RLS inputs.)
A13: Union | B13: C (Cohesion) | C13: F (Flow) | D13: R (Resilience) | E13: E (Equity) | F13: UCI_u
A14: U1 | B14: 0.7 | C14: 0.7 | D14: 0.7 | E14: 1 | F14: =AVERAGE(B14:E14) -> 0.775
A15: U2 | B15: 0.7 | C15: 0.7 | D15: 0.7 | E15: 0.7 | F15: =AVERAGE(B15:E15) -> 0.7
A16: U3 | B16: 0.7 | C16: 0.7 | D16: 0.7 | E16: 0.7 | F16: =AVERAGE(B16:E16) -> 0.7
A17: U4 | B17: 0.7 | C17: 0.7 | D17: 0.7 | E17: 0.7 | F17: =AVERAGE(B17:E17) -> 0.7
A18: U5 | B18: 0.7 | C18: 0.7 | D18: 0.7 | E18: 0.7 | F18: =AVERAGE(B18:E18) -> 0.7
A19: U6 | B19: 0.7 | C19: 0.7 | D19: 0.7 | E19: 0.7 | F19: =AVERAGE(B19:E19) -> 0.7
A20: U7 | B20: 0.7 | C20: 0.7 | D20: 0.7 | E20: 0.7 | F20: =AVERAGE(B20:E20) -> 0.7
A22: UCI (mean over unions) | B22: =AVERAGE(F14:F20) -> 0.71071429
A23: Note: Uniform values = evaluator assessment
A24: For Tier 3: require independent structural indicators
A26: HOI STATUS
A27: HOI = 0 (no human override requested)
A28: Status: OK
A29: TIE-BREAK OUTCOME
A30: UCI: Non-decisive (uniform evaluator assessment)
A31: HOI: 0 (no hollowing-out risk flagged)
A32: Resolution: JUDGMENT_CALL - Select higher RLS (A) with monitoring

Sheet Dashboard
A1: RIPPLE_LOGIC v8.6 - DECISION DASHBOARD
A2: ="Sheet: "&CANON!B7&" | Framework: "&CANON!B5 -> Sheet: v2.2 | Framework: Ripple_Logic v8.6 | B2: ="Sheet: "&CANON!B7&" | Framework: "&CANON!B5 -> Sheet: v2.2 | Framework: Ripple_Logic v8.6
A4: DISCLOSURE | B4: Current dashboard and selection logic implement a two-option comparison (Option A vs Option B). Do not represent the workbook as native multi-option optimization without extending the comparison logic.
A6: DECISION CONTEXT
A7: Decision: | B7: =PCC!B5 -> Remote Work Policy Implementation
A8: Date: | B8: =PCC!B6 -> 2026-02-01
A9: Tier: | B9: =CANON!B10&" ("&IF(CANON!B10=1,"Personal",IF(CANON!B10=2,"Core","High-Stakes"))&")" -> 2 (Core)
A10: Context: | B10: =CANON!B11 -> ORG
A11: AI Deployment: | B11: =CANON!B12 -> NO
A12: TRC Active: | B12: =IF(CANON!B13=1,"YES","NO") -> YES
A14: LEXICOGRAPHIC CASCADE
A15: Level | B15: Gate | C15: Option A | D15: Option B | E15: Resolution
A16: 1 | B16: NCRC | C16: =CANON!B51 -> PASS | D16: =CANON!B52 -> PASS | E16: =IF(AND(C14="PASS",D14="PASS"),"Both Pass",IF(C14="PASS","A only",IF(D14="PASS","B only","Neither"))) -> Neither
A17: 2 | B17: TRC | C17: =CANON!B56&" (CVaR="&TEXT(CANON!B54,"0.0000")&")" -> PASS (CVaR=0.0219) | D17: =CANON!B57&" (CVaR="&TEXT(CANON!B55,"0.0000")&")" -> PASS (CVaR=0.0315) | E17: =IF(AND(CANON!B56="PASS",CANON!B57="PASS"),"Both Pass",IF(CANON!B56="PASS","A only",IF(CANON!B57="PASS","B only","Neither"))) -> Both Pass
A18: 3 | B18: Containment | C18: =CANON!B60 -> PASS | D18: =CANON!B61 -> PASS (vacuous) | E18: =IF(AND(C16="PASS",D16="PASS"),"Both Pass","Review") -> Both Pass
A19: 4 | B19: RLS | C19: =TEXT(CANON!B63,"0.000000") -> 0.005462 | D19: =TEXT(CANON!B64,"0.000000") -> 0.000202 | E19: =IF(CANON!B63>CANON!B64,"A higher",IF(CANON!B64>CANON!B63,"B higher","Tie")) -> A higher
A21: Selection-note: | B21: Two-option surface only (A/B)
A22: Selection Mode: | B22: =CANON!B70 -> NORMAL
A23: Selected Option: | B23: =IF(CANON!B71="","NONE (INVALID)",IF(CANON!B71="TIE","TIE (UCI required)","OPTION "&CANON!B71)) -> OPTION A
A24: Selection Basis: | B24: =CANON!B72 -> RLS comparison
A25: Weight Profile: | B25: =Config!B15 -> PLSS_LOCAL
A26: PLSS Scope Note: | B26: =IF(Config!B15="PLSS_LOCAL","See PLSS_Local_Scope for q_u and w_u^PLSS","Uniform weights active") -> See PLSS_Local_Scope for q_u and w_u^PLSS
A27: CLAIMABILITY STATUS (from CANON)
A28: Claimable Run: | B28: =CANON!B81 -> YES
A29: Invalid Flags: | B29: =CANON!B80 -> 0
A30: C_cat Blank Count: | B30: =CANON!B76 -> 0
A31: Scenario Impact Missing: | B31: =IF(CANON!B77=TRUE(),"YES (BLOCKS CLAIM)","NO") -> NO
A33: AUDIT FLAGS SUMMARY
A34: Invalid Count: | B34: =Audit_Flags!B21 -> 0
A35: Escalate Count: | B35: =Audit_Flags!B22 -> 0
A36: Review Count: | B36: =Audit_Flags!B23 -> 1
A37: Total Active: | B37: =Audit_Flags!B24 -> 1
A39: Triggered Flags: | B39: ⚠ REVIEW flags present
A42: =Audit_Flags!B26 -> NO
A45: Audit flags (active) | B45: =Audit_Flags!B24 -> 1
A49: REQUIRED FOLLOW-UP
A50: 1. ☐ Document judgment call rationale
A51: 2. ☐ Schedule enhanced monitoring (quarterly)
A52: =TEXT(DATE(2026,2,2)+90,"YYYY-MM-DD") -> 2026-05-03
A53: 4. ☐ Consider Tier 3 upgrade if stakes increase

Sheet Audit_Flags
A1: AUDIT FLAGS - FORMULA-DRIVEN SSOT (v1.8.3)
A2: ALL Triggered cells (B5:B17) are FORMULAS - zero typed values
A3: Manual override detector (B18) catches any tampering
A4: Flag_ID | B4: Triggered | C4: Severity | D4: Description | E4: Formula Logic | F4: Source | G4: Helper_Flag | H4: Helper_Sev
A5: CATASTROPHE_CELL_OMITTED_INVALID | B5: =IF(AND(CANON!B13=1,CANON!B76>0),"YES","NO") -> NO | C5: INVALID | D5: Any catastrophe cell in C_cat used in TRC loss computation/disclosure is omitted/excluded/not disclosed such that TRC CVaR cannot be independently recomputed (e.g., C_cat blank when TRC active). | E5: =IF(AND(CANON!$B$13=1,CANON!$B$76>0),"YES","NO") -> NO | F5: CANON!B13,B76 | G5: =IF(B5="YES",A5,"") | H5: =IF(B5="YES",C5,"") | I5: =IF($H5="INVALID",$G5,"") | J5: =IF($H5="ESCALATE",$G5,"") | K5: =IF($H5="REVIEW",$G5,"") | L5: =IF($G5<>"",$G5&" ("&$H5&")","")
A6: MANDATORY_TAIL_CATEGORY_MISSING | B6: =IF(WTSL_Categories!$B$17 < WTSL_Categories!$B$16,"YES","NO") -> NO | C6: ESCALATE | D6: Missing mandatory tail category (required WTSL category not covered at p_floor). | E6: =IF(WTSL_Categories!$B$17 < WTSL_Categories!$B$16,"YES","NO") -> NO | F6: WTSL_Categories!B16,B17 | G6: =IF(B6="YES",A6,"") | H6: =IF(B6="YES",C6,"") | I6: =IF($H6="INVALID",$G6,"") | J6: =IF($H6="ESCALATE",$G6,"") | K6: =IF($H6="REVIEW",$G6,"") | L6: =IF($G6<>"",$G6&" ("&$H6&")","")
A7: CONFIG_DRIFT | B7: =IF(Config!B2<>CANON!B7,"YES","NO") -> NO | C7: INVALID | D7: Config version <> CANON | E7: Config!B2<>CANON!B7 | F7: Config!B2 | G7: =IF(B7="YES",A7,"") | H7: =IF(B7="YES",C7,"") | I7: =IF($H7="INVALID",$G7,"") | J7: =IF($H7="ESCALATE",$G7,"") | K7: =IF($H7="REVIEW",$G7,"") | L7: =IF($G7<>"",$G7&" ("&$H7&")","")
A8: RIGHTS_COUNT_MISMATCH | B8: =IF(CANON!B38<>8,"YES","NO") -> NO | C8: INVALID | D8: Rights count <> 8 | E8: CANON!B38<>8 | F8: CANON!B38 | G8: =IF(B8="YES",A8,"") | H8: =IF(B8="YES",C8,"") | I8: =IF($H8="INVALID",$G8,"") | J8: =IF($H8="ESCALATE",$G8,"") | K8: =IF($H8="REVIEW",$G8,"") | L8: =IF($G8<>"",$G8&" ("&$H8&")","")
A9: SELECTION_INVALID | B9: =IF(OR(CANON!B71="",CANON!B71="NONE"),"YES","NO") -> NO | C9: INVALID | D9: No valid selection | E9: SELECTED_OPTION blank | F9: CANON!B71 | G9: =IF(B9="YES",A9,"") | H9: =IF(B9="YES",C9,"") | I9: =IF($H9="INVALID",$G9,"") | J9: =IF($H9="ESCALATE",$G9,"") | K9: =IF($H9="REVIEW",$G9,"") | L9: =IF($G9<>"",$G9&" ("&$H9&")","")
A10: TRC_FALLBACK_INVOKED | B10: =IF(AND(CANON!B67>0,CANON!B68=0),"YES","NO") -> NO | C10: ESCALATE | D10: TRC failed for admissible | E10: A_NCRC>0 AND A_ADM=0 | F10: CANON!B67,B68 | G10: =IF(B10="YES",A10,"") | H10: =IF(B10="YES",C10,"") | I10: =IF($H10="INVALID",$G10,"") | J10: =IF($H10="ESCALATE",$G10,"") | K10: =IF($H10="REVIEW",$G10,"") | L10: =IF($G10<>"",$G10&" ("&$H10&")","")
A11: EMERGENCY_MODE_INVOKED | B11: =IF(CANON!B67=0,"YES","NO") -> NO | C11: ESCALATE | D11: No rights-admissible options | E11: A_NCRC_COUNT=0 | F11: CANON!B67 | G11: =IF(B11="YES",A11,"") | H11: =IF(B11="YES",C11,"") | I11: =IF($H11="INVALID",$G11,"") | J11: =IF($H11="ESCALATE",$G11,"") | K11: =IF($H11="REVIEW",$G11,"") | L11: =IF($G11<>"",$G11&" ("&$H11&")","")
A12: ESCALATION_REQUIRED | B12: =IF(CANON!B73="YES","YES","NO") -> NO | C12: ESCALATE | D12: Escalation required | E12: CANON!B73=YES | F12: CANON!B73 | G12: =IF(B12="YES",A12,"") | H12: =IF(B12="YES",C12,"") | I12: =IF($H12="INVALID",$G12,"") | J12: =IF($H12="ESCALATE",$G12,"") | K12: =IF($H12="REVIEW",$G12,"") | L12: =IF($G12<>"",$G12&" ("&$H12&")","")
A13: SIGMA_MISSING_REQUIRED | B13: =IF(AND(CANON!$B$8>=2,OR(CANON!$B$137="",CANON!$B$26="",CANON!$B$26<=0)),"YES","NO") -> NO | C13: ESCALATE | D13: Uncertainty σ required for Tier 2+ but missing/invalid (method or sigma_est not declared). | E13: =IF(AND(CANON!$B$8>=2,OR(CANON!$B$137="",CANON!$B$26="",CANON!$B$26<=0)),"YES","NO") -> NO | F13: CANON!B8,B26,B137 | G13: =IF(B13="YES",A13,"") | H13: =IF(B13="YES",C13,"") | I13: =IF($H13="INVALID",$G13,"") | J13: =IF($H13="ESCALATE",$G13,"") | K13: =IF($H13="REVIEW",$G13,"") | L13: =IF($G13<>"",$G13&" ("&$H13&")","")
A14: SUBGROUP_LIMITATION | B14: =IF(AND(Subgroup_Overrides!B17=0,Subgroup_Analysis!B46=0),"YES","NO") -> NO | C14: REVIEW | D14: No subgroup override entries AND no documented subgroup analysis | E14: Overrides=0 AND analysis_done=0 | F14: Subgroup_Overrides!B17 + Subgroup_Analysis!B46 | G14: =IF(B14="YES",A14,"") | H14: =IF(B14="YES",C14,"") | I14: =IF($H14="INVALID",$G14,"") | J14: =IF($H14="ESCALATE",$G14,"") | K14: =IF($H14="REVIEW",$G14,"") | L14: =IF($G14<>"",$G14&" ("&$H14&")","")
A15: NONDECISIVE_GAP_REVIEW | B15: =IF(ABS(CANON!B63-CANON!B64)/SQRT(2*CANON!B26^2+0.000001)<CANON!B22,"YES","NO") -> YES | C15: REVIEW | D15: RLS discrimination band indicates a non-decisive gap (|RLS_A − RLS_B| within δ), requires reviewer attention / UCI. | E15: =IF(AND(CANON!$B$8>=2,RLS!$B$38="YES"),"YES","NO") -> NO | F15: CANON!B8,RLS!B38,CANON!B94 | G15: =IF(B15="YES",A15,"") -> NONDECISIVE_GAP_REVIEW | H15: =IF(B15="YES",C15,"") -> REVIEW | I15: =IF($H15="INVALID",$G15,"") | J15: =IF($H15="ESCALATE",$G15,"") | K15: =IF($H15="REVIEW",$G15,"") -> NONDECISIVE_GAP_REVIEW | L15: =IF($G15<>"",$G15&" ("&$H15&")","") -> NONDECISIVE_GAP_REVIEW (REVIEW)
A16: UCI_SOURCE_UNVERIFIED | B16: =IF(CANON!B10>=3,"YES","NO") -> NO | C16: REVIEW | D16: UCI unverified (Tier 3+) | E16: TIER>=3 | F16: CANON!B10 | G16: =IF(B16="YES",A16,"") | H16: =IF(B16="YES",C16,"") | I16: =IF($H16="INVALID",$G16,"") | J16: =IF($H16="ESCALATE",$G16,"") | K16: =IF($H16="REVIEW",$G16,"") | L16: =IF($G16<>"",$G16&" ("&$H16&")","")
A17: SENSITIVITY_NOT_RUN | B17: =IF(Sensitivity_Analysis!B3="NOT PERFORMED","YES","NO") -> NO | C17: REVIEW | D17: Sensitivity not executed | E17: Status=NOT PERFORMED | F17: Sensitivity_Analysis!B3 | G17: =IF(B17="YES",A17,"") | H17: =IF(B17="YES",C17,"") | I17: =IF($H17="INVALID",$G17,"") | J17: =IF($H17="ESCALATE",$G17,"") | K17: =IF($H17="REVIEW",$G17,"") | L17: =IF($G17<>"",$G17&" ("&$H17&")","")
A18: MANUAL_FLAG_OVERRIDE | B18: =IF(SUMPRODUCT(--((B5:B17<>"YES")*(B5:B17<>"NO")))+SUMPRODUCT(--((B25:B28<>"YES")*(B25:B28<>"NO")))>0,"YES","NO") -> NO | C18: INVALID | D18: Manual override detected | E18: Triggers if any flag trigger cell is not an explicit YES/NO (format break / potential manual overwrite). | F18: Self-check | G18: =IF(B18="YES",A18,"") | H18: =IF(B18="YES",C18,"") | I18: =IF($H18="INVALID",$G18,"") | J18: =IF($H18="ESCALATE",$G18,"") | K18: =IF($H18="REVIEW",$G18,"") | L18: =IF($G18<>"",$G18&" ("&$H18&")","")
I19: ACTIVE_FLAG_DETAILS | J19: =IF(_xlfn.TEXTJOIN(", ",TRUE(),$L$5:$L$18,$L$25:$L$28)="","(none)",_xlfn.TEXTJOIN(", ",TRUE(),$L$5:$L$18,$L$25:$L$28)) -> NONDECISIVE_GAP_REVIEW (REVIEW)
A20: COMPUTED SUMMARY (COUNTIFS formulas) | I20: INVALID_FLAGS_LIST | J20: =IF(_xlfn.TEXTJOIN(", ",TRUE(),$I$5:$I$18,$I$25:$I$28)="","(none)",_xlfn.TEXTJOIN(", ",TRUE(),$I$5:$I$18,$I$25:$I$28)) -> (none)
A21: INVALID_COUNT | B21: =COUNTIFS(B5:B18,"YES",C5:C18,"INVALID")+COUNTIFS(B25:B28,"YES",C25:C28,"INVALID") -> 0 | C21: Formula | I21: ESCALATE_FLAGS_LIST | J21: =IF(_xlfn.TEXTJOIN(", ",TRUE(),$J$5:$J$18,$J$25:$J$28)="","(none)",_xlfn.TEXTJOIN(", ",TRUE(),$J$5:$J$18,$J$25:$J$28)) -> (none)
A22: ESCALATE_COUNT | B22: =COUNTIFS(B5:B18,"YES",C5:C18,"ESCALATE")+COUNTIFS(B25:B28,"YES",C25:C28,"ESCALATE") -> 0 | C22: Formula | I22: REVIEW_FLAGS_LIST | J22: =IF(_xlfn.TEXTJOIN(", ",TRUE(),$K$5:$K$18,$K$25:$K$28)="","(none)",_xlfn.TEXTJOIN(", ",TRUE(),$K$5:$K$18,$K$25:$K$28)) -> NONDECISIVE_GAP_REVIEW
A23: REVIEW_COUNT | B23: =COUNTIFS(B5:B18,"YES",C5:C18,"REVIEW")+COUNTIFS(B25:B28,"YES",C25:C28,"REVIEW") -> 1 | C23: Formula
A24: TOTAL_ACTIVE | B24: =SUM(B21:B23) -> 1 | C24: Formula
A25: SCOPE_COVERAGE_REDUCED | B25: =IF(AND(CANON!B133="REDUCED",OR(CANON!B134="NONE",CANON!B134="")),"YES","NO") -> NO | C25: REVIEW | D25: Reduced-scope used without ScopeCoverage declaration | E25: SCOPE_COVERAGE_MODE=REDUCED AND (OmittedScopes=NONE or blank) | F25: CANON v8.6 fields | G25: =IF(B25="YES",A25,"") | H25: =IF(B25="YES",C25,"") | I25: =IF($H25="INVALID",$G25,"") | J25: =IF($H25="ESCALATE",$G25,"") | K25: =IF($H25="REVIEW",$G25,"") | L25: =IF($G25<>"",$G25&" ("&$H25&")","")
A26: SCI_BELOW_MINIMUM | B26: =IF(AND(CANON!$B$10>=2,CANON!B130<IF(CANON!$B$10=2,1,IF(CANON!$B$10=3,2,0))),"YES","NO") -> NO | C26: ESCALATE | D26: SCI below tier minimum (Tier 2: SCI≥1; Tier 3: SCI≥2) | E26: TIER>=2 AND SCI_LEVEL < tier_minimum | F26: CANON v8.6 SCI fields | G26: =IF(B26="YES",A26,"") | H26: =IF(B26="YES",C26,"") | I26: =IF($H26="INVALID",$G26,"") | J26: =IF($H26="ESCALATE",$G26,"") | K26: =IF($H26="REVIEW",$G26,"") | L26: =IF($G26<>"",$G26&" ("&$H26&")","")
A27: SCI_AT_MINIMUM_NO_UPGRADE | B27: =IF(AND(CANON!$B$10>=2,CANON!B130=IF(CANON!$B$10=2,1,IF(CANON!$B$10=3,2,0)),CANON!B131=""),"YES","NO") -> NO | C27: REVIEW | D27: SCI at tier minimum but no NextRunUpgrade action declared | E27: SCI=tier_min AND SCI_NEXT_RUN_UPGRADE blank | F27: CANON v8.6 SCI fields | G27: =IF(B27="YES",A27,"") | H27: =IF(B27="YES",C27,"") | I27: =IF($H27="INVALID",$G27,"") | J27: =IF($H27="ESCALATE",$G27,"") | K27: =IF($H27="REVIEW",$G27,"") | L27: =IF($G27<>"",$G27&" ("&$H27&")","")
A28: UNCERTAINTY_NOT_DECLARED | B28: =IF(AND(CANON!$B$10>=2,OR(CANON!B137="",CANON!B137=0)),"YES","NO") -> NO | C28: INVALID | D28: Tier 2+ requires uncertainty method (A/B/C) per v8.6 | E28: TIER>=2 AND UNCERTAINTY_METHOD blank | F28: CANON v8.6 UNCERTAINTY_METHOD | G28: =IF(B28="YES",A28,"") | H28: =IF(B28="YES",C28,"") | I28: =IF($H28="INVALID",$G28,"") | J28: =IF($H28="ESCALATE",$G28,"") | K28: =IF($H28="REVIEW",$G28,"") | L28: =IF($G28<>"",$G28&" ("&$H28&")","")
A29: CANON LINK VERIFICATION
A30: CANON!B80 must equal B21 | B30: =CANON!B80 -> 0
A31: Match: | B31: =IF(B30=B21,"✓ SSOT","❌ DRIFT") -> ✓ SSOT
A34: FLAG TAXONOMY NOTE (v8.6)
A35: This workbook emits two kinds of flags: (1) Canon-aligned audit flags intended to correspond to Ripple_Logic v8.6 Appendix H.3 reviewer actions, and (2) Tool-local integrity flags that protect the calculator/PCC emitter itself. Tool-local flags are marked TOOL_LOCAL below and SHOULD NOT be interpreted as new Ripple_Logic normative audit taxonomy.
A37: Flag_ID | B37: Classification | C37: Canonical reference / mapping | D37: Reviewer note
A38: CONFIG_DRIFT | B38: TOOL_LOCAL | C38: (none) | D38: Workbook config/version mismatch; treat as INVALID for this emitter.
A39: RIGHTS_COUNT_MISMATCH | B39: TOOL_LOCAL | C39: (none) | D39: Workbook sanity check; not a Ripple_Logic audit flag.
A40: SELECTION_INVALID | B40: TOOL_LOCAL | C40: (none) | D40: No selected option; tool integrity failure.
A41: MANUAL_FLAG_OVERRIDE | B41: TOOL_LOCAL | C41: (none) | D41: Manual edits detected in trigger cells; invalidate run output.
A42: NONDECISIVE_GAP_REVIEW | B42: TOOL_LOCAL | C42: Maps to: REVIEW (underdetermined) | D42: Indicates discrimination band / non-decisive gap; triggers reviewer attention.
A43: UCI_SOURCE_UNVERIFIED | B43: TOOL_LOCAL | C43: Maps to: REVIEW (evidence) | D43: Source provenance for UCI/HOI inputs not documented in this workbook.
A44: SENSITIVITY_NOT_RUN | B44: TOOL_LOCAL | C44: Maps to: REVIEW (sensitivity) | D44: Sensitivity analysis not executed or not documented for this run.
A45: SCOPE_COVERAGE_REDUCED | B45: TOOL_LOCAL | C45: Maps to: REVIEW (scope) | D45: Scope coverage reduced; ensure disclosure in PCC.

Sheet PCC
A1: PROVENANCE AND COMPLIANCE CERTIFICATE (PCC)
A3: SECTION 1: DECISION METADATA
A4: Decision_ID | B4: ORG-2026-001
A5: Decision_Name | B5: Remote Work Policy Implementation
A6: Date | B6: 2026-02-01
A7: Evaluator | B7: James Pether Sörling, Lead Architect, MathGov Institute
A8: Reviewer | B8: N/A (Tier 2 - independent review optional)
A9: Tier_Level | B9: 2 (Core)
A10: Context_Type | B10: ORG
A11: Sheet_Version | B11: =CANON!B7 -> v2.2
A12: Framework_Version | B12: =CANON!B5 -> Ripple_Logic v8.6
A13: SGP_Version | B13: =CANON!B6 -> SGP v4.3
B14: YES
A15: CLAIMABLE_RUN | B15: =IF(CANON!B81="YES","YES (Tier 2 Conformant, "&CANON!B7&")","NO") -> YES (Tier 2 Conformant, v2.2)
A16: SECTION 2: CONFIGURATION
A17: Weight_Profile | B17: UNIFORM (1/7 each)
A18: Propagation_Mode | B18: NONE
A19: Kernel_Status | B19: Not used
A20: β_saturation | B20: 2
A21: δ_discrimination | B21: 2
A22: τ_c_containment | B22: -0.1
A23: θ_pos | B23: 0.05
A24: T_ref | B24: 25
A25: α_CVaR | B25: =CANON!B18 -> 0.95
A26: τ_TRC | B26: =CANON!B58 -> 0.2
A27: Uncertainty_Method | B27: =CANON!B137 -> C | C27: Method C: constant σ for all active welfare cells (sigma_est).
A28: Sigma_AllActiveCells | B28: =CANON!B26 -> 0.02 | C28: σ used for discrimination band ε/δ checks and nondecisive-gap detection (Tier 2 worked run).
A29: SECTION 3: RIGHTS CONFIGURATION
A30: Rights_Coverage_Version | B30: v8.6 Canonical
A31: Rights_Checked | B31: 8 (LIFE,BODY,ECOL,LBTY,NEED,DIGN,PROC,INFO)
A32: Coverage_Sets_Count | B32: =COUNTA(Rights_Coverage!$B$7:$B$76) -> 70
A33: Subgroup_Policy | B33: Overrides table (Subgroup_Overrides) optional; SUBGROUP_LIMITATION flagged if missing on negative rights cells
A34: BaselineType_Welfare | B34: STATUS_QUO | C34: Welfare deltas are measured relative to the declared status-quo baseline (not the rights-floor reference).
A35: BaselineReference_Welfare | B35: RL v8.6 Sections 6–9 (welfare deltas) + Appendix P conventions | C35: Explicit declaration for auditability: welfare baseline is STATUS_QUO unless otherwise stated.
A36: BaselineType_Gates | B36: FLOOR_REFERENCE | C36: Rights/catastrophe gating baseline is the rights floor (not status quo).
A37: BaselineReference_Gates | B37: RL v8.6 Section 5.1A | C37: Gate comparisons reference θ_r (rights floors) and declared catastrophe constraints.
A38: SECTION 4: TRC CONFIGURATION
A39: C_cat_Set
A40: C_cat_Weights | B40: PASS
A41: C_cat_Extended | B41: PASS
A42: Scenario_Count | B42: 7
A43: All_WTSL_Covered | B43: YES (5/5 mandatory)
A44: All_p_floors_Met | B44: =IF(WTSL_Categories!$B$17>=WTSL_Categories!$B$16,"YES","NO") -> YES
B46: PASS
A47: SECTION 5: CASCADE RESULTS | B47: PASS
A48: NCRC_Status_A | B48: PASS
A49: NCRC_Status_B | B49: PASS
A50: Emergency_Mode | B50: NOT INVOKED
A51: CVaR_A | B51: 0.0219
A52: CVaR_B | B52: 0.0315
A53: A_adm | B53: {A, B}
A54: TRC_Fallback | B54: NO
A55: Containment_A | B55: =CANON!B60 -> PASS | C55: Tier 2: containment proxy display (union-score diagnostic). Tier 3+: implement full ΔUCI containment per Section 9.0.
A56: Containment_B | B56: =CANON!B61 -> PASS (vacuous) | C56: Tier 2: containment proxy display (union-score diagnostic). Tier 3+: implement full ΔUCI containment per Section 9.0.
A57: RLS_A | B57: 0.005462
A58: RLS_B | B58: 0.000202
A59: RLS_Decisive | B59: NO
B61: 0.005462
A62: SECTION 6: DECISION | B62: 0.000202
A63: Selection_Mode | B63: =CANON!B70 -> NORMAL
A64: Selection_Basis | B64: =CANON!B72 -> RLS comparison
A65: Recommended_Option | B65: =IF(CANON!B71="","None",CANON!B71) -> A
A66: CVaR_Deficit | B66: =IF(Dashboard!$B$36="YES",TEXT(MIN(TRC!$H$15,TRC!$H$28)-Config!$B$12,"0.000")&" above τ_TRC","0.000") -> 0.000
A67: Confidence | B67: MEDIUM
A68: Escalation_Required | B68: =CANON!B73 -> NO
A69: Escalation_Path | B69: A
A70: Admissible_Options | B70: {A, B}
A71: Rights_Admissible | B71: {A, B}
B72: YES
A73: SECTION 7: AUDIT FLAGS
A74: Active Flags (INVALID): | B74: =Audit_Flags!B21 -> 0
A75: Active Flags (ESCALATE): | B75: =Audit_Flags!B22 -> 0
A76: Active Flags (REVIEW): | B76: =Audit_Flags!B23 -> 1 | C76: Mitigation required
A77: Active Flag Details: | B77: =Audit_Flags!$J$19 -> NONDECISIVE_GAP_REVIEW (REVIEW)
B78: Note: REVIEW flags do not block claimability but require documentation.
A80: SECTION 8: FIVE-SENTENCE PUBLIC RATIONALE (5SPR)
A81: 1. CONTEXT: | B81: Organization evaluating remote work policy (Option A: implement remote; Option B: retain in-office). ORG context, Tier 2.
A82: 2. OPTIONS: | B82: Option A: flexibility, reduced emissions, less cohesion. Option B: team bonds, facility costs, commute burden.
A83: 3. CONSTRAINTS: | B83: Both pass NCRC (8 rights) and TRC (CVaR_A=0.0219, CVaR_B=0.0315 ≤ 0.20). WTSL-AIX voluntary.
A84: 4. SELECTION: | B84: Option A selected via RLS (0.005462 vs 0.000202). Gap non-decisive; judgment call documented.
A85: 5. MONITORING: | B85: ="NCAR quarterly. REVIEW flags: "&IF(Audit_Flags!B26="","(none)",Audit_Flags!B26)&". Reflect: "&$B$102&"." -> NCAR quarterly. REVIEW flags: NO. Reflect: .
A86: Monitoring (snapshot): | B86: Run NCAR (Notice–Choose–Act–Reflect) monitoring on a 30–90 day cadence, review any REVIEW flags, collect outcome indicators, and record adjustments or mitigations in the PCC log.
A89: SECTION 9: RISK MITIGATION PLAN
A90: =IF(Dashboard!$B$36="YES","Objective: Reduce selected option CVaR ("&TEXT(MIN(TRC!$H$15,TRC!$H$28),"0.000")&") to ≤ τ_TRC ("&TEXT(Config!$B$12,"0.00")&") via mitigation within a defined timeline.","Objective: Maintain CVaR ≤ τ_TRC ("&TEXT(Config!$B$12,"0.00")&") and monitor tail-risk assumptions.") -> Objective: Maintain CVaR ≤ τ_TRC (0.20) and monitor tail-risk assumptions.
A91: M1 | B91: Hybrid work pandemic contingency | C91: Qualitative (Tier-2 exemplar: no numeric CVaR delta claimed)
A92: M2 | B92: Infrastructure backup systems | C92: Qualitative (Tier-2 exemplar: no numeric CVaR delta claimed)
A93: M3 | B93: Community resilience fund | C93: Qualitative (Tier-2 exemplar: no numeric CVaR delta claimed)
A94: M4 | B94: Climate adaptation plan | C94: Qualitative (Tier-2 exemplar: no numeric CVaR delta claimed)
A95: M5 | B95: AI system audit/fallbacks | C95: Qualitative (Tier-2 exemplar: no numeric CVaR delta claimed)
A96: TOTAL | B96: Tail-risk posture | C96: =IF(Dashboard!$B$36="YES","Mitigation required (CVaR above τ_TRC).","Headroom = "&TEXT(CANON!$B$106-IF(CANON!$B$71="A",CANON!$B$104,IF(CANON!$B$71="B",CANON!$B$105,"")),"0.000")&" (τ_TRC - CVaR_selected). Monitor assumptions + rerun TRC on change.") -> Headroom = 0.178 (τ_TRC - CVaR_selected). Monitor assumptions + rerun TRC on change. | D96: =CANON!B106-IF(CANON!B71="A",CANON!B104,CANON!B105) -> 0.1781
A97: Audit_Flags_Active (canon-aligned unless TOOL_LOCAL; see Audit_Flags mapping note) | B97: =Audit_Flags!$F$2 -> 0
A99: SECTION 10: NCAR SCHEDULE
A100: Notice: Complete (this PCC)
A101: Choose: Complete (Option A via normal cascade) | B101: Option A via normal cascade
A102: Act: Begins upon sign-off
A103: 2026-05-03
A104: Reflect: Scheduled | B104: =TEXT(DATE(2026,2,2)+90,"YYYY-MM-DD") -> 2026-05-03
A106: SECTION 11: STEWARDSHIP COMPLIANCE (v8.6 Section 14.7, Appendix N)
A107: Stewardship_Profile | B107: N/A (Tier 2 - Stewardship profiles apply at MODE 2+ per RLAS v8.6 §8.7)
A108: Conditional_Stewardship_Active | B108: FALSE | C108: (Stw_req defaults FALSE for MODE 0-1; TRUE for MODE 2+ per RLAS v8.6 §8.7)
...

Sheet Sensitivity_Analysis
A1: SENSITIVITY ANALYSIS
A3: Module Status: | B3: PERFORMED
A4: Tier Requirement: | B4: Small sensitivity tests executed (weights + scenario probabilities).
A5: Audit Flag: | B5: ="SENSITIVITY_NOT_RUN = "&IF(B3="NOT PERFORMED","YES","NO")&" (REVIEW severity)" -> SENSITIVITY_NOT_RUN = NO (REVIEW severity)
A7: PERTURBATION TESTS
A8: Test | B8: Change | C8: Metric | D8: Result | E8: Selection stable? | F8: Notes
A9: SENS-01 | B9: Weights: D1 +10% (renorm) | C9: Preferred option | D9: =D34 -> A | E9: =IF(D9=$D$14,"YES","NO") -> YES | F9: RLS recomputed from I_prop with perturbed dimension weights
A10: SENS-02 | B10: Weights: D7 +10% (renorm) | C10: Preferred option | D10: =D35 -> A | E10: =IF(D10=$D$14,"YES","NO") -> YES | F10: RLS recomputed from I_prop with perturbed dimension weights
A11: SENS-03 | B11: Weights: D3&D5 +10% (renorm) | C11: Preferred option | D11: =D36 -> A | E11: =IF(D11=$D$14,"YES","NO") -> YES | F11: RLS recomputed from I_prop with perturbed dimension weights
A12: SENS-04 | B12: Scenario p stress: worst-loss scenarios +20% (renorm) | C12: TRC status (A,B) | D12: =N122&", "&N123 -> PASS, PASS | E12: =IF(AND(N122="PASS",N123="PASS"),"YES","NO") -> YES | F12: CVaR recomputed with stressed probabilities; compare to τ_TRC
A13: Baseline | B13: RLS_A | C13: RLS_B | D13: Preferred | E13: Gap
A14: Sensitivity analysis optional. Selection stability assumed based on margin: | B14: =RLS!B61 -> 0.015312943 | C14: =RLS!B62 -> -0.0011223874 | D14: =IF(B14>=C14,"A","B") -> A | E14: =B14-C14 -> 0.01643533
A15: CVaR_A (0.0219) and CVaR_B (0.0315) are both << τ_TRC (0.20)
A16: Overall sensitivity verdict | B16: =IF(AND($D$34=$D$14,$D$35=$D$14,$D$36=$D$14,$N$122="PASS",$N$123="PASS"),"STABLE","CHANGES DETECTED") -> STABLE
K20: D1 | L20: D2 | M20: D3 | N20: D4 | O20: D5 | P20: D6 | Q20: D7
J21: Base v_d | K21: =Parameters!$B$48 -> 0.14285714 | L21: =Parameters!$B$49 -> 0.14285714 | M21: =Parameters!$B$50 -> 0.14285714 | N21: =Parameters!$B$51 -> 0.14285714 | O21: =Parameters!$B$52 -> 0.14285714 | P21: =Parameters!$B$53 -> 0.14285714 | Q21: =Parameters!$B$54 -> 0.14285714
J22: Factors (SENS-01) | K22: 1.1 | L22: 1 | M22: 1 | N22: 1 | O22: 1 | P22: 1 | Q22: 1
J23: v_d* (SENS-01) | K23: =K$21*K$22/SUMPRODUCT($K$21:$Q$21,$K$22:$Q$22) -> 0.15492958 | L23: =L$21*L$22/SUMPRODUCT($K$21:$Q$21,$K$22:$Q$22) -> 0.14084507 | M23: =M$21*M$22/SUMPRODUCT($K$21:$Q$21,$K$22:$Q$22) -> 0.14084507 | N23: =N$21*N$22/SUMPRODUCT($K$21:$Q$21,$K$22:$Q$22) -> 0.14084507 | O23: =O$21*O$22/SUMPRODUCT($K$21:$Q$21,$K$22:$Q$22) -> 0.14084507 | P23: =P$21*P$22/SUMPRODUCT($K$21:$Q$21,$K$22:$Q$22) -> 0.14084507 | Q23: =Q$21*Q$22/SUMPRODUCT($K$21:$Q$21,$K$22:$Q$22) -> 0.14084507
J24: Factors (SENS-02) | K24: 1 | L24: 1 | M24: 1 | N24: 1 | O24: 1 | P24: 1 | Q24: 1.1
A25: Selection stability: computed in this exemplar via the SENS-01..SENS-04 perturbations below (see Summary). | J25: v_d* (SENS-02) | K25: =K$21*K$24/SUMPRODUCT($K$21:$Q$21,$K$24:$Q$24) -> 0.14084507 | L25: =L$21*L$24/SUMPRODUCT($K$21:$Q$21,$K$24:$Q$24) -> 0.14084507 | M25: =M$21*M$24/SUMPRODUCT($K$21:$Q$21,$K$24:$Q$24) -> 0.14084507 | N25: =N$21*N$24/SUMPRODUCT($K$21:$Q$21,$K$24:$Q$24) -> 0.14084507 | O25: =O$21*O$24/SUMPRODUCT($K$21:$Q$21,$K$24:$Q$24) -> 0.14084507 | P25: =P$21*P$24/SUMPRODUCT($K$21:$Q$21,$K$24:$Q$24) -> 0.14084507 | Q25: =Q$21*Q$24/SUMPRODUCT($K$21:$Q$21,$K$24:$Q$24) -> 0.15492958
J26: Factors (SENS-03) | K26: 1 | L26: 1 | M26: 1.1 | N26: 1 | O26: 1.1 | P26: 1 | Q26: 1
A27: 4. IMPACT MAGNITUDE PERTURBATION (±20%) | J27: v_d* (SENS-03) | K27: =K$21*K$26/SUMPRODUCT($K$21:$Q$21,$K$26:$Q$26) -> 0.13888889 | L27: =L$21*L$26/SUMPRODUCT($K$21:$Q$21,$K$26:$Q$26) -> 0.13888889 | M27: =M$21*M$26/SUMPRODUCT($K$21:$Q$21,$K$26:$Q$26) -> 0.15277778 | N27: =N$21*N$26/SUMPRODUCT($K$21:$Q$21,$K$26:$Q$26) -> 0.13888889 | O27: =O$21*O$26/SUMPRODUCT($K$21:$Q$21,$K$26:$Q$26) -> 0.15277778 | P27: =P$21*P$26/SUMPRODUCT($K$21:$Q$21,$K$26:$Q$26) -> 0.13888889 | Q27: =Q$21*Q$26/SUMPRODUCT($K$21:$Q$21,$K$26:$Q$26) -> 0.13888889
A28: Key instances: I03 (flexibility), I01 (isolation)
A29: Additional tests: Not performed for this run | J29: Union w_u
I30: U1 | J30: =Parameters!$B$38 -> 0.30766667 | K30: =$J30*K$23 -> 0.047666667 | L30: =$J30*L$23 -> 0.043333333 | M30: =$J30*M$23 -> 0.043333333 | N30: =$J30*N$23 -> 0.043333333 | O30: =$J30*O$23 -> 0.043333333 | P30: =$J30*P$23 -> 0.043333333 | Q30: =$J30*Q$23 -> 0.043333333
I31: U2 | J31: =Parameters!$B$39 -> 0.15633333 | K31: =$J31*K$23 -> 0.024220657 | L31: =$J31*L$23 -> 0.022018779 | M31: =$J31*M$23 -> 0.022018779 | N31: =$J31*N$23 -> 0.022018779 | O31: =$J31*O$23 -> 0.022018779 | P31: =$J31*P$23 -> 0.022018779 | Q31: =$J31*Q$23 -> 0.022018779
A32: 5. ROBUSTNESS CLASSIFICATION | I32: U3 | J32: =Parameters!$B$40 -> 0.12233333 | K32: =$J32*K$23 -> 0.018953052 | L32: =$J32*L$23 -> 0.017230047 | M32: =$J32*M$23 -> 0.017230047 | N32: =$J32*N$23 -> 0.017230047 | O32: =$J32*O$23 -> 0.017230047 | P32: =$J32*P$23 -> 0.017230047 | Q32: =$J32*Q$23 -> 0.017230047
A33: Weight sensitivity results | I33: U4 | J33: =Parameters!$B$41 -> 0.11666667 | K33: =$J33*K$23 -> 0.018075117 | L33: =$J33*L$23 -> 0.016431925 | M33: =$J33*M$23 -> 0.016431925 | N33: =$J33*N$23 -> 0.016431925 | O33: =$J33*O$23 -> 0.016431925 | P33: =$J33*P$23 -> 0.016431925 | Q33: =$J33*Q$23 -> 0.016431925
A34: SENS-01 Preferred | B34: =SUMPRODUCT(I_prop!$B$7:$H$13,$K$30:$Q$36) -> 0.015024197 | C34: =SUMPRODUCT(I_prop!$B$18:$H$24,$K$30:$Q$36) -> -0.0011077415 | D34: =IF(B34>=C34,"A","B") -> A | E34: =B34-C34 -> 0.016131938 | I34: U5 | J34: =Parameters!$B$42 -> 0.091333333 | K34: =$J34*K$23 -> 0.014150235 | L34: =$J34*L$23 -> 0.01286385 | M34: =$J34*M$23 -> 0.01286385 | N34: =$J34*N$23 -> 0.01286385 | O34: =$J34*O$23 -> 0.01286385 | P34: =$J34*P$23 -> 0.01286385 | Q34: =$J34*Q$23 -> 0.01286385
A35: SENS-02 Preferred | B35: =SUMPRODUCT(I_prop!$B$7:$H$13,$K$40:$Q$46) -> 0.015119329 | C35: =SUMPRODUCT(I_prop!$B$18:$H$24,$K$40:$Q$46) -> -0.0011212874 | D35: =IF(B35>=C35,"A","B") -> A | E35: =B35-C35 -> 0.016240616 | I35: U6 | J35: =Parameters!$B$43 -> 0.1034 | K35: =$J35*K$23 -> 0.016019718 | L35: =$J35*L$23 -> 0.01456338 | M35: =$J35*M$23 -> 0.01456338 | N35: =$J35*N$23 -> 0.01456338 | O35: =$J35*O$23 -> 0.01456338 | P35: =$J35*P$23 -> 0.01456338 | Q35: =$J35*Q$23 -> 0.01456338
A36: SENS-03 Preferred | B36: =SUMPRODUCT(I_prop!$B$7:$H$13,$K$50:$Q$56) -> 0.015814472 | C36: =SUMPRODUCT(I_prop!$B$18:$H$24,$K$50:$Q$56) -> -0.0011846806 | D36: =IF(B36>=C36,"A","B") -> A | E36: =B36-C36 -> 0.016999152 | I36: U7 | J36: =Parameters!$B$44 -> 0.10226667 | K36: =$J36*K$23 -> 0.015844131 | L36: =$J36*L$23 -> 0.014403756 | M36: =$J36*M$23 -> 0.014403756 | N36: =$J36*N$23 -> 0.014403756 | O36: =$J36*O$23 -> 0.014403756 | P36: =$J36*P$23 -> 0.014403756 | Q36: =$J36*Q$23 -> 0.014403756
A37: Status note: PERFORMED for this Tier‑2 exemplar (weight sensitivity + CVaR stress checks). Tier‑3 deployments may expand the test set and increase rigor.
I40: U1 | J40: =Parameters!$B$38 -> 0.30766667 | K40: =$J40*K$25 -> 0.043333333 | L40: =$J40*L$25 -> 0.043333333 | M40: =$J40*M$25 -> 0.043333333 | N40: =$J40*N$25 -> 0.043333333 | O40: =$J40*O$25 -> 0.043333333 | P40: =$J40*P$25 -> 0.043333333 | Q40: =$J40*Q$25 -> 0.047666667
I41: U2 | J41: =Parameters!$B$39 -> 0.15633333 | K41: =$J41*K$25 -> 0.022018779 | L41: =$J41*L$25 -> 0.022018779 | M41: =$J41*M$25 -> 0.022018779 | N41: =$J41*N$25 -> 0.022018779 | O41: =$J41*O$25 -> 0.022018779 | P41: =$J41*P$25 -> 0.022018779 | Q41: =$J41*Q$25 -> 0.024220657
I42: U3 | J42: =Parameters!$B$40 -> 0.12233333 | K42: =$J42*K$25 -> 0.017230047 | L42: =$J42*L$25 -> 0.017230047 | M42: =$J42*M$25 -> 0.017230047 | N42: =$J42*N$25 -> 0.017230047 | O42: =$J42*O$25 -> 0.017230047 | P42: =$J42*P$25 -> 0.017230047 | Q42: =$J42*Q$25 -> 0.018953052
I43: U4 | J43: =Parameters!$B$41 -> 0.11666667 | K43: =$J43*K$25 -> 0.016431925 | L43: =$J43*L$25 -> 0.016431925 | M43: =$J43*M$25 -> 0.016431925 | N43: =$J43*N$25 -> 0.016431925 | O43: =$J43*O$25 -> 0.016431925 | P43: =$J43*P$25 -> 0.016431925 | Q43: =$J43*Q$25 -> 0.018075117
I44: U5 | J44: =Parameters!$B$42 -> 0.091333333 | K44: =$J44*K$25 -> 0.01286385 | L44: =$J44*L$25 -> 0.01286385 | M44: =$J44*M$25 -> 0.01286385 | N44: =$J44*N$25 -> 0.01286385 | O44: =$J44*O$25 -> 0.01286385 | P44: =$J44*P$25 -> 0.01286385 | Q44: =$J44*Q$25 -> 0.014150235
I45: U6 | J45: =Parameters!$B$43 -> 0.1034 | K45: =$J45*K$25 -> 0.01456338 | L45: =$J45*L$25 -> 0.01456338 | M45: =$J45*M$25 -> 0.01456338 | N45: =$J45*N$25 -> 0.01456338 | O45: =$J45*O$25 -> 0.01456338 | P45: =$J45*P$25 -> 0.01456338 | Q45: =$J45*Q$25 -> 0.016019718
I46: U7 | J46: =Parameters!$B$44 -> 0.10226667 | K46: =$J46*K$25 -> 0.014403756 | L46: =$J46*L$25 -> 0.014403756 | M46: =$J46*M$25 -> 0.014403756 | N46: =$J46*N$25 -> 0.014403756 | O46: =$J46*O$25 -> 0.014403756 | P46: =$J46*P$25 -> 0.014403756 | Q46: =$J46*Q$25 -> 0.015844131
I50: U1 | J50: =Parameters!$B$38 -> 0.30766667 | K50: =$J50*K$27 -> 0.042731481 | L50: =$J50*L$27 -> 0.042731481 | M50: =$J50*M$27 -> 0.04700463 | N50: =$J50*N$27 -> 0.042731481 | O50: =$J50*O$27 -> 0.04700463 | P50: =$J50*P$27 -> 0.042731481 | Q50: =$J50*Q$27 -> 0.042731481
I51: U2 | J51: =Parameters!$B$39 -> 0.15633333 | K51: =$J51*K$27 -> 0.021712963 | L51: =$J51*L$27 -> 0.021712963 | M51: =$J51*M$27 -> 0.023884259 | N51: =$J51*N$27 -> 0.021712963 | O51: =$J51*O$27 -> 0.023884259 | P51: =$J51*P$27 -> 0.021712963 | Q51: =$J51*Q$27 -> 0.021712963
I52: U3 | J52: =Parameters!$B$40 -> 0.12233333 | K52: =$J52*K$27 -> 0.016990741 | L52: =$J52*L$27 -> 0.016990741 | M52: =$J52*M$27 -> 0.018689815 | N52: =$J52*N$27 -> 0.016990741 | O52: =$J52*O$27 -> 0.018689815 | P52: =$J52*P$27 -> 0.016990741 | Q52: =$J52*Q$27 -> 0.016990741
I53: U4 | J53: =Parameters!$B$41 -> 0.11666667 | K53: =$J53*K$27 -> 0.016203704 | L53: =$J53*L$27 -> 0.016203704 | M53: =$J53*M$27 -> 0.017824074 | N53: =$J53*N$27 -> 0.016203704 | O53: =$J53*O$27 -> 0.017824074 | P53: =$J53*P$27 -> 0.016203704 | Q53: =$J53*Q$27 -> 0.016203704
I54: U5 | J54: =Parameters!$B$42 -> 0.091333333 | K54: =$J54*K$27 -> 0.012685185 | L54: =$J54*L$27 -> 0.012685185 | M54: =$J54*M$27 -> 0.013953704 | N54: =$J54*N$27 -> 0.012685185 | O54: =$J54*O$27 -> 0.013953704 | P54: =$J54*P$27 -> 0.012685185 | Q54: =$J54*Q$27 -> 0.012685185
I55: U6 | J55: =Parameters!$B$43 -> 0.1034 | K55: =$J55*K$27 -> 0.014361111 | L55: =$J55*L$27 -> 0.014361111 | M55: =$J55*M$27 -> 0.015797222 | N55: =$J55*N$27 -> 0.014361111 | O55: =$J55*O$27 -> 0.015797222 | P55: =$J55*P$27 -> 0.014361111 | Q55: =$J55*Q$27 -> 0.014361111
I56: U7 | J56: =Parameters!$B$44 -> 0.10226667 | K56: =$J56*K$27 -> 0.014203704 | L56: =$J56*L$27 -> 0.014203704 | M56: =$J56*M$27 -> 0.015624074 | N56: =$J56*N$27 -> 0.014203704 | O56: =$J56*O$27 -> 0.015624074 | P56: =$J56*P$27 -> 0.014203704 | Q56: =$J56*Q$27 -> 0.014203704
J100: Scenario | K100: p_base | L100: Factor_up | M100: p_stress_up | N100: Factor_down | O100: p_stress_down
J101: =TRC!B15 -> S06 | K101: =TRC!D15 -> 0.03 | L101: =IF(OR(J101="S06",J101="S04",J101="S03"),1.2,1) -> 1.2 | M101: =K101*L101/SUMPRODUCT($K$101:$K$107,$L$101:$L$107) -> 0.034749035 | N101: =IF(OR(J101="S06",J101="S04",J101="S03"),0.8,1) -> 0.8 | O101: =K101*N101/SUMPRODUCT($K$101:$K$107,$N$101:$N$107) -> 0.024896266
J102: =TRC!B16 -> S04 | K102: =TRC!D16 -> 0.07 | L102: =IF(OR(J102="S06",J102="S04",J102="S03"),1.2,1) -> 1.2 | M102: =K102*L102/SUMPRODUCT($K$101:$K$107,$L$101:$L$107) -> 0.081081081 | N102: =IF(OR(J102="S06",J102="S04",J102="S03"),0.8,1) -> 0.8 | O102: =K102*N102/SUMPRODUCT($K$101:$K$107,$N$101:$N$107) -> 0.058091286
J103: =TRC!B17 -> S03 | K103: =TRC!D17 -> 0.08 | L103: =IF(OR(J103="S06",J103="S04",J103="S03"),1.2,1) -> 1.2 | M103: =K103*L103/SUMPRODUCT($K$101:$K$107,$L$101:$L$107) -> 0.092664093 | N103: =IF(OR(J103="S06",J103="S04",J103="S03"),0.8,1) -> 0.8 | O103: =K103*N103/SUMPRODUCT($K$101:$K$107,$N$101:$N$107) -> 0.066390041
J104: =TRC!B18 -> S05 | K104: =TRC!D18 -> 0.05 | L104: =IF(OR(J104="S06",J104="S04",J104="S03"),1.2,1) -> 1 | M104: =K104*L104/SUMPRODUCT($K$101:$K$107,$L$101:$L$107) -> 0.048262548 | N104: =IF(OR(J104="S06",J104="S04",J104="S03"),0.8,1) -> 1 | O104: =K104*N104/SUMPRODUCT($K$101:$K$107,$N$101:$N$107) -> 0.05186722
J105: =TRC!B19 -> S07 | K105: =TRC!D19 -> 0.02 | L105: =IF(OR(J105="S06",J105="S04",J105="S03"),1.2,1) -> 1 | M105: =K105*L105/SUMPRODUCT($K$101:$K$107,$L$101:$L$107) -> 0.019305019 | N105: =IF(OR(J105="S06",J105="S04",J105="S03"),0.8,1) -> 1 | O105: =K105*N105/SUMPRODUCT($K$101:$K$107,$N$101:$N$107) -> 0.020746888
J106: =TRC!B20 -> S02 | K106: =TRC!D20 -> 0.15 | L106: =IF(OR(J106="S06",J106="S04",J106="S03"),1.2,1) -> 1 | M106: =K106*L106/SUMPRODUCT($K$101:$K$107,$L$101:$L$107) -> 0.14478764 | N106: =IF(OR(J106="S06",J106="S04",J106="S03"),0.8,1) -> 1 | O106: =K106*N106/SUMPRODUCT($K$101:$K$107,$N$101:$N$107) -> 0.15560166
J107: =TRC!B21 -> S01 | K107: =TRC!D21 -> 0.6 | L107: =IF(OR(J107="S06",J107="S04",J107="S03"),1.2,1) -> 1 | M107: =K107*L107/SUMPRODUCT($K$101:$K$107,$L$101:$L$107) -> 0.57915058 | N107: =IF(OR(J107="S06",J107="S04",J107="S03"),0.8,1) -> 1 | O107: =K107*N107/SUMPRODUCT($K$101:$K$107,$N$101:$N$107) -> 0.62240664
J109: CVaR recompute (p stress UP)
J110: Rank | K110: Scenario | L110: Loss | M110: p_stress | N110: Cum_p | O110: Tail_w | P110: Contrib | R110: β | S110: =TRC!B8 -> 0.05
J111: 1 | K111: =TRC!B15 -> S06 | L111: =TRC!C15 -> 0.0235 | M111: =VLOOKUP(K111,$J$101:$M$107,4,FALSE()) -> 0.034749035 | N111: =M111 -> 0.034749035 | O111: =MIN(M111,$S$110) -> 0.034749035 | P111: =O111*L111 -> 0.00081660232 | R111: τ_TRC | S111: =TRC!B9 -> 0.2
J112: 2 | K112: =TRC!B16 -> S04 | L112: =TRC!C16 -> 0.0195 | M112: =VLOOKUP(K112,$J$101:$M$107,4,FALSE()) -> 0.081081081 | N112: =N111+M112 -> 0.11583012 | O112: =MAX(0,MIN(M112,$S$110-N111)) -> 0.015250965 | P112: =O112*L112 -> 0.00029739382
J113: 3 | K113: =TRC!B17 -> S03 | L113: =TRC!C17 -> 0.0175 | M113: =VLOOKUP(K113,$J$101:$M$107,4,FALSE()) -> 0.092664093 | N113: =N112+M113 -> 0.20849421 | O113: =MAX(0,MIN(M113,$S$110-N112)) -> 0 | P113: =O113*L113 -> 0
J114: 4 | K114: =TRC!B18 -> S05 | L114: =TRC!C18 -> 0.0135 | M114: =VLOOKUP(K114,$J$101:$M$107,4,FALSE()) -> 0.048262548 | N114: =N113+M114 -> 0.25675676 | O114: =MAX(0,MIN(M114,$S$110-N113)) -> 0 | P114: =O114*L114 -> 0
J115: 5 | K115: =TRC!B19 -> S07 | L115: =TRC!C19 -> 0.01 | M115: =VLOOKUP(K115,$J$101:$M$107,4,FALSE()) -> 0.019305019 | N115: =N114+M115 -> 0.27606178 | O115: =MAX(0,MIN(M115,$S$110-N114)) -> 0 | P115: =O115*L115 -> 0
J116: 6 | K116: =TRC!B20 -> S02 | L116: =TRC!C20 -> 0.007 | M116: =VLOOKUP(K116,$J$101:$M$107,4,FALSE()) -> 0.14478764 | N116: =N115+M116 -> 0.42084942 | O116: =MAX(0,MIN(M116,$S$110-N115)) -> 0 | P116: =O116*L116 -> 0
J117: 7 | K117: =TRC!B21 -> S01 | L117: =TRC!C21 -> 0 | M117: =VLOOKUP(K117,$J$101:$M$107,4,FALSE()) -> 0.57915058 | N117: =N116+M117 -> 1 | O117: =MAX(0,MIN(M117,$S$110-N116)) -> 0 | P117: =O117*L117 -> 0
R119: CVaR_A_up | S119: =SUM(P111:P117)/$S$110 -> 0.022279923
R120: Status_A_up | S120: =IF(S119<=$S$111,"PASS","FAIL") -> PASS
M121: TRC stress UP status | N121: A | O121: B
M122: TRC stress DOWN status | N122: =S120 -> PASS | O122: =S142 -> PASS
N123: =S162 -> PASS | O123: =S175 -> PASS
J131: CVaR recompute for Option B (p stress UP)
J132: Rank | K132: Scenario | L132: Loss | M132: p_stress | N132: Cum_p | O132: Tail_w | P132: Contrib
J133: 1 | K133: =TRC!B31 -> S03 | L133: =TRC!C31 -> 0.0315 | M133: =VLOOKUP(K133,$J$101:$M$107,4,FALSE()) -> 0.092664093 | N133: =M133 -> 0.092664093 | O133: =MIN(M133,$S$110) -> 0.05 | P133: =O133*L133 -> 0.001575
J134: 2 | K134: =TRC!B32 -> S04 | L134: =TRC!C32 -> 0.0235 | M134: =VLOOKUP(K134,$J$101:$M$107,4,FALSE()) -> 0.081081081 | N134: =N133+M134 -> 0.17374517 | O134: =MAX(0,MIN(M134,$S$110-N133)) -> 0 | P134: =O134*L134 -> 0
J135: 3 | K135: =TRC!B33 -> S06 | L135: =TRC!C33 -> 0.02175 | M135: =VLOOKUP(K135,$J$101:$M$107,4,FALSE()) -> 0.034749035 | N135: =N134+M135 -> 0.20849421 | O135: =MAX(0,MIN(M135,$S$110-N134)) -> 0 | P135: =O135*L135 -> 0
J136: 4 | K136: =TRC!B34 -> S05 | L136: =TRC!C34 -> 0.0135 | M136: =VLOOKUP(K136,$J$101:$M$107,4,FALSE()) -> 0.048262548 | N136: =N135+M136 -> 0.25675676 | O136: =MAX(0,MIN(M136,$S$110-N135)) -> 0 | P136: =O136*L136 -> 0
J137: 5 | K137: =TRC!B35 -> S02 | L137: =TRC!C35 -> 0.0105 | M137: =VLOOKUP(K137,$J$101:$M$107,4,FALSE()) -> 0.14478764 | N137: =N136+M137 -> 0.4015444 | O137: =MAX(0,MIN(M137,$S$110-N136)) -> 0 | P137: =O137*L137 -> 0
J138: 6 | K138: =TRC!B36 -> S07 | L138: =TRC!C36 -> 0.007 | M138: =VLOOKUP(K138,$J$101:$M$107,4,FALSE()) -> 0.019305019 | N138: =N137+M138 -> 0.42084942 | O138: =MAX(0,MIN(M138,$S$110-N137)) -> 0 | P138: =O138*L138 -> 0
J139: 7 | K139: =TRC!B37 -> S01 | L139: =TRC!C37 -> 0.003574 | M139: =VLOOKUP(K139,$J$101:$M$107,4,FALSE()) -> 0.57915058 | N139: =N138+M139 -> 1 | O139: =MAX(0,MIN(M139,$S$110-N138)) -> 0 | P139: =O139*L139 -> 0
R141: CVaR_B_up | S141: =SUM(P133:P139)/$S$110 -> 0.0315
R142: Status_B_up | S142: =IF(S141<=$S$111,"PASS","FAIL") -> PASS
J151: CVaR recompute (p stress DOWN)
J152: Rank | K152: Scenario | L152: Loss | M152: p_stress | N152: Cum_p | O152: Tail_w | P152: Contrib
J153: 1 | K153: =TRC!B15 -> S06 | L153: =TRC!C15 -> 0.0235 | M153: =VLOOKUP(K153,$J$101:$O$107,6,FALSE()) -> 0.024896266 | N153: =M153 -> 0.024896266 | O153: =MIN(M153,$S$110) -> 0.024896266 | P153: =O153*L153 -> 0.00058506224
J154: 2 | K154: =TRC!B16 -> S04 | L154: =TRC!C16 -> 0.0195 | M154: =VLOOKUP(K154,$J$101:$O$107,6,FALSE()) -> 0.058091286 | N154: =N153+M154 -> 0.082987552 | O154: =MAX(0,MIN(M154,$S$110-N153)) -> 0.025103734 | P154: =O154*L154 -> 0.00048952282
J155: 3 | K155: =TRC!B17 -> S03 | L155: =TRC!C17 -> 0.0175 | M155: =VLOOKUP(K155,$J$101:$O$107,6,FALSE()) -> 0.066390041 | N155: =N154+M155 -> 0.14937759 | O155: =MAX(0,MIN(M155,$S$110-N154)) -> 0 | P155: =O155*L155 -> 0
J156: 4 | K156: =TRC!B18 -> S05 | L156: =TRC!C18 -> 0.0135 | M156: =VLOOKUP(K156,$J$101:$O$107,6,FALSE()) -> 0.05186722 | N156: =N155+M156 -> 0.20124481 | O156: =MAX(0,MIN(M156,$S$110-N155)) -> 0 | P156: =O156*L156 -> 0
J157: 5 | K157: =TRC!B19 -> S07 | L157: =TRC!C19 -> 0.01 | M157: =VLOOKUP(K157,$J$101:$O$107,6,FALSE()) -> 0.020746888 | N157: =N156+M157 -> 0.2219917 | O157: =MAX(0,MIN(M157,$S$110-N156)) -> 0 | P157: =O157*L157 -> 0
J158: 6 | K158: =TRC!B20 -> S02 | L158: =TRC!C20 -> 0.007 | M158: =VLOOKUP(K158,$J$101:$O$107,6,FALSE()) -> 0.15560166 | N158: =N157+M158 -> 0.37759336 | O158: =MAX(0,MIN(M158,$S$110-N157)) -> 0 | P158: =O158*L158 -> 0
J159: 7 | K159: =TRC!B21 -> S01 | L159: =TRC!C21 -> 0 | M159: =VLOOKUP(K159,$J$101:$O$107,6,FALSE()) -> 0.62240664 | N159: =N158+M159 -> 1 | O159: =MAX(0,MIN(M159,$S$110-N158)) -> 0 | P159: =O159*L159 -> 0
R161: CVaR_A_down | S161: =SUM(P153:P159)/$S$110 -> 0.021491701
R162: Status_A_down | S162: =IF(S161<=$S$111,"PASS","FAIL") -> PASS
J164: Option B (p stress DOWN)
J165: Rank | K165: Scenario | L165: Loss | M165: p_stress | N165: Cum_p | O165: Tail_w | P165: Contrib
J166: 1 | K166: =TRC!B31 -> S03 | L166: =TRC!C31 -> 0.0315 | M166: =VLOOKUP(K166,$J$101:$O$107,6,FALSE()) -> 0.066390041 | N166: =M166 -> 0.066390041 | O166: =MIN(M166,$S$110) -> 0.05 | P166: =O166*L166 -> 0.001575
J167: 2 | K167: =TRC!B32 -> S04 | L167: =TRC!C32 -> 0.0235 | M167: =VLOOKUP(K167,$J$101:$O$107,6,FALSE()) -> 0.058091286 | N167: =N166+M167 -> 0.12448133 | O167: =MAX(0,MIN(M167,$S$110-N166)) -> 0 | P167: =O167*L167 -> 0
J168: 3 | K168: =TRC!B33 -> S06 | L168: =TRC!C33 -> 0.02175 | M168: =VLOOKUP(K168,$J$101:$O$107,6,FALSE()) -> 0.024896266 | N168: =N167+M168 -> 0.14937759 | O168: =MAX(0,MIN(M168,$S$110-N167)) -> 0 | P168: =O168*L168 -> 0
J169: 4 | K169: =TRC!B34 -> S05 | L169: =TRC!C34 -> 0.0135 | M169: =VLOOKUP(K169,$J$101:$O$107,6,FALSE()) -> 0.05186722 | N169: =N168+M169 -> 0.20124481 | O169: =MAX(0,MIN(M169,$S$110-N168)) -> 0 | P169: =O169*L169 -> 0
J170: 5 | K170: =TRC!B35 -> S02 | L170: =TRC!C35 -> 0.0105 | M170: =VLOOKUP(K170,$J$101:$O$107,6,FALSE()) -> 0.15560166 | N170: =N169+M170 -> 0.35684647 | O170: =MAX(0,MIN(M170,$S$110-N169)) -> 0 | P170: =O170*L170 -> 0
J171: 6 | K171: =TRC!B36 -> S07 | L171: =TRC!C36 -> 0.007 | M171: =VLOOKUP(K171,$J$101:$O$107,6,FALSE()) -> 0.020746888 | N171: =N170+M171 -> 0.37759336 | O171: =MAX(0,MIN(M171,$S$110-N170)) -> 0 | P171: =O171*L171 -> 0
J172: 7 | K172: =TRC!B37 -> S01 | L172: =TRC!C37 -> 0.003574 | M172: =VLOOKUP(K172,$J$101:$O$107,6,FALSE()) -> 0.62240664 | N172: =N171+M172 -> 1 | O172: =MAX(0,MIN(M172,$S$110-N171)) -> 0 | P172: =O172*L172 -> 0
R174: CVaR_B_down | S174: =SUM(P166:P172)/$S$110 -> 0.0315
...

Sheet Subgroup_Analysis
A1: SUBGROUP ANALYSIS - WORST-OFF DOCUMENTATION
A3: Reference: Ripple_Logic v8.6 Section 7.3 - Tier 2 requires subgroup enumeration
A5: OPTION A: NEGATIVE IMPACT CELLS
A7: Cell: U3-D3 (Community-Social) | Agg I_prop: -0.069
A8: Rights: LBTY (-0.65), DIGN (-0.55)
A9: Subgroup | B9: I_prop | C9: Rationale
A10: General population | B10: -0.069 | C10: Baseline
A11: Elderly (65+) | B11: -0.1 | C11: Higher isolation risk
A12: Single-person HH | B12: -0.12 | C12: No household buffer
A13: New employees (<1yr) | B13: -0.15 | C13: Harder to integrate
A14: WORST-OFF | B14: -0.15 | C14: New employees
A15: Threshold checks: LBTY -0.15 > -0.65 ✓ | DIGN -0.15 > -0.55 ✓
A17: Cell: U4-D1 (Org-Material) | Agg I_prop: -0.176
A18: Rights: NEED (-0.50)
A19: Worst-off: Facilities dept at -0.30
A20: Threshold: -0.30 > -0.50 ✓
A22: Cell: U3-D1 (Community-Material) | Agg I_prop: -0.075
A23: Rights: NEED (-0.50)
A24: Worst-off: Local restaurants at -0.20
A25: Threshold: -0.20 > -0.50 ✓
A28: OPTION B: NEGATIVE IMPACT CELLS
A30: Cell: U1-D5 (Self-Agency) | Agg I_prop: -0.073
A31: Rights: LBTY, DIGN, INFO
... A45: NCRC outcome ROBUST with subgroup analysis
A46: analysis_done (computed) | B46: =IF(COUNTIF($A$1:$A$200,"WORST-OFF")>0,1,0) -> 1

Sheet Subgroup_Overrides
A1: SUBGROUP OVERRIDES TABLE
A3: Policy: Conservative Bound (γ_subgroup = 1.5)
A4: I_rights = max(-1, γ × I_prop) when no override
A5: Applies only for NCRC, not RLS
A7: γ_subgroup: | B7: 1.5
A9: OVERRIDE DATA TABLE
A10: Override_ID | B10: Option | C10: Rights_Cell | D10: Union | E10: Dimension | F10: Worst_Off_Impact | G10: Source
A14: COMPUTED STATUS
A15: Data range: | B15: F11:F100
A16: Entry formula: | B16: =COUNT(F11:F100) -> 0
A17: Valid entries: | B17: =COUNT(F11:F100) -> 0
A18: OVERRIDES_TABLE_EMPTY: | B18: =IF(B17=0,"YES","NO") -> YES
A19: SUBGROUP_LIMITATION (Audit_Flags): | B19: =Audit_Flags!B14 -> NO
A20: MITIGATION (Tier 2)
A21: • Conservative bound applied
A22: • REVIEW flag accepted
A23: • Data collection scheduled

Sheet SGP_Input
A1: SGP INPUT INTERFACE
A3: Reference: Ripple_Logic v8.6 Appendix G - Sentience Gradient Protocol Interface
A4: SGP Version: 4.3
A6: HUMAN PLATEAU RULE (Non-Overridable)
A7: For any human person H: SG_norm(H) := 1.0
A8: This is independent of measurement, disability, observability
A9: MUST NOT be weakened by any weighting scheme
A11: STAKEHOLDER s_k VALUES
A12: ID | B12: Stakeholder | C12: Substrate | D12: SG_norm | E12: Basis
A13: SK01 | B13: Employees (all) | C13: Human | D13: 1 | E13: Plateau Rule
A14: SK02 | B14: Household members | C14: Human | D14: 1 | E14: Plateau Rule
A15: SK03 | B15: Community members | C15: Human | D15: 1 | E15: Plateau Rule
A16: SK04 | B16: Organization staff | C16: Human | D16: 1 | E16: Plateau Rule
A17: SK05 | B17: Policy stakeholders | C17: Human | D17: 1 | E17: Plateau Rule
A18: SK06 | B18: Humanity (aggregate) | C18: Human | D18: 1 | E18: Plateau Rule
A21: BIOSPHERE NOTE
A22: U7 impacts = environmental integrity, not direct animal welfare
A23: If direct animal welfare at stake, apply SGP evidence tiers

Sheet SGP_Integration
A1: SGP INTEGRATION DOCUMENTATION
A3: Reference: Ripple_Logic v8.6 Appendix G
A4: Reference: SGP v4.3
A6: HUMAN PLATEAU RULE CONFIRMATION
A7: ┌────────────────────────────────────────────────────────┐
A8: │ All stakeholders in this decision are human persons. │
A9: │ Therefore: s_k = SG_norm(H) = 1.0 for all instances. │
A10: │ The Human Plateau Rule has been applied without │
A11: │ exception. No sentience multiplier has reduced any │
A12: │ human stakeholder's impact weight. │
A13: └────────────────────────────────────────────────────────┘
A15: SGP MISINTERPRETATION GUARD COMPLIANCE
A16: Prohibited Inference | B16: Status
A17: Linguistic fluency → sentience | B17: NOT APPLIED ✓
A18: Self-report → sufficient evidence | B18: NOT APPLIED ✓
A19: Intelligence → moral status | B19: NOT APPLIED ✓
A20: Sentience → governance authority | B20: NOT APPLIED ✓
A21: Precaution → attribution | B21: NOT APPLIED ✓
A22: Low SGP → reduced human protections | B22: PROHIBITED & CONFIRMED ✓
A25: IMPACT INSTANCE VERIFICATION
A26: All 14 impact instances (I01-I14) use s_k = 1.0 ✓
A28: ATTESTATION
A29: ☑ Human Plateau Rule applied to all human stakeholders
A30: ☑ No SGP output weakened NCRC protections
A31: ☑ No sentience multiplier reduced human welfare weight
A32: ☑ SGP Misinterpretation Guard principles followed
A34: Evaluator: ___________________________ Date: ___________

Sheet User_Guide
A1: RIPPLE ALIGNERS SHEET - USER GUIDE (v2.2)
A3: IMPORTANT DISCLOSURE
A4: Current workbook selection logic compares Option A vs Option B only. For three or more substantive options, extend the workbook logic or run sequential pairwise/fresh evaluations with documented rationale.
A5: QUICK START
A6: 1. Config: Set tier level, context type, and Weight Profile
A7: 2. PLSS_Local_Scope: If using local-scope mode, enter q_u values and review floor-preserving weights
A8: 3. Impact_Input: Enter all causal pathways (μ, r, ℓ, c, t, e, s)
A9: 4. Review I_prop: Verify computed impact matrix
A10: 5. Check NCRC: All rights must pass (v_r = 0)
A11: 6. Check TRC: CVaR must be ≤ τ_TRC for context
A12: 7. If TRC fails: Follow fallback procedure (Section 8.8)
A13: 8. Dashboard: Review final recommendation
... A15: SHEET INDEX
A16: 1 | B16: Config | C16: Global settings
A17: 2 | B17: 70 total (U,D) pairs across all 8 rights | C17: Canonical values (locked)
A18: 3 | B18: Rights_Coverage | C18: 70 (U,D) pairs across all 8 rights
A19: 4 | B19: C_cat | C19: Catastrophe cells for TRC
A20: 5 | B20: WTSL_Categories | C20: 6 mandatory tail categories
A21: 6 | B21: Impact_Input | C21: Enter impacts here
A22: 7 | B22: Scenario_Impacts | C22: Scenario-conditioned losses (NEW)
A23: 8 | B23: I_prop | C23: Computed impact matrix
A24: 9 | B24: NCRC | C24: Level 1 rights check
A25: 10 | B25: TRC | C25: Level 2 tail risk + fallback
A26: 11 | B26: Containment | C26: Level 3 structural check
A27: 12 | B27: RLS | C27: Level 4 welfare score
... A36: 21 | B36: Version_Control | C36: Version tracking (NEW)
A39: KEY FORMULAS
A40: τ(t) = MIN(1, LN(1+MAX(t, t_min)) / LN(1+T_ref)) [Ripple_Logic v8.6 Appendix B.1]
A41: Contribution = μ × r × ℓ × c × e × s × τ(t)
A42: v_r(a) = max(0, θ_r - min I_rights over R_r)
A43: L(a,s) = Σ_{c∈C_cat} ω_c × max(0, -I_prop_c)
A44: CVaR_α = E[L | L ≥ VaR_α]
A45: RLS = Σ w_u × v_d × sat(I_prop)
A47: v8.6 ADDITIONS
A48: 8. PCC Section 12: Set ScopeCoverage mode (FULL/REDUCED) and document active/omitted scopes
A49: 9. PCC Section 13: Log stakeholder instances with InstanceMap (REQUIRED at Tier 2 when triggers hold)
A50: 10. PCC Section 14: Declare SCI level and NextRunUpgrade if at tier minimum
A51: 11. PCC Section 15: Review active cell definition for uncertainty coverage
... A54: NOTE: "Union Scopes" (short: Scopes) is the v8.6 canonical term; "Union(s)" remains a valid legacy alias

Sheet Version_Control
A1: VERSION CONTROL AND CONFORMANCE
A2: =CANON!B7 -> v2.2
A3: ="Sheet Version: "&CANON!B7 -> Sheet Version: v2.2
A4: ="Framework: "&CANON!B5 -> Framework: Ripple_Logic v8.6
A5: ="SGP: "&CANON!B6 -> SGP: SGP v4.3
A6: ="SGP: "&CANON!B6 -> SGP: SGP v4.3
A7: Modified: 2026-03-15
A8: v1.7.0 | B8: 2026-02-03 | C8: SSOT_ENFORCED: Schema validation computed, SC-06 fixed, PUBLISH_READY gate includes PLACEHOLDER_COUNT
A9: VERSION HISTORY
A10: Version | B10: Date | C10: Changes
A11: v2.2 | B11: 2026-03-15 | C11: Publication-ready disclosure release: added explicit two-option limitation notice across Release_Notes, Dashboard, and User_Guide; version advanced to v2.2 for audit-response packaging. Core formulas and v8.6 / SGP v4.3 pins remain unchanged.
A12: v2.0 | B12: 2026-03-14 | C12: Ripple_Logic v8.6 + SGP v4.3 synchronization. Added PLSS_Local_Scope helper sheet, profile-driven union weights with floor-preserving residual allocation, and updated Release Notes, Config, Dashboard, User Guide, and Version Control. | D12: OpenAI-assisted
A13: v2.1 | B13: 2026-03-15 | C13: BUG FIXES + VERSION SYNC (v2.1): (1) Fixed _xludf.TEXTJOIN→TEXTJOIN, _xludf.minifs→MINIFS, _xludf.aggregate→AGGREGATE (hash-NAME formula errors errors resolved in Audit_Flags J19:J22 and for Excel compatibility across Rights_Coverage_View and NCRC). (2) Sanity_Checklist SC-01..04 Expected values changed from stale hardcoded strings to dynamic CANON/Config cross-references; SC-33 repurposed as SGP version check (SC-34); SC-IDs SC-30..33 in rows 42-45 corrected; PASS/FAIL counts extended to all 34 checks. (3) All stale v8.5.4 PATCHED descriptive refs updated to v8.6 across 11 sheets. (4) SGP version refs updated 4.2.3→4.3. (5) Release_Notes B8 corrected from Audit_Flags!B26 to Audit_Flags!J19 (active flag list). (6) Version_Control A2 fixed from stored text to formula; B2 stale value cleared. | D13: Claude-assisted
A14: v1.8.3 | B14: 2026-02-16 | C14: v8.5.4 PATCHED RE-PIN: Framework→Ripple_Logic v8.5.4 PATCHED. Added SCI (Section 5.0.1), ScopeCoverage (Section 2.2A), InstanceMap (Appendix H), active cell definition (Section 10.3). New audit flags: SCOPE_COVERAGE_REDUCED (REVIEW), SCI_BELOW_MINIMUM (ESCALATE), SCI_AT_MINIMUM_NO_UPGRADE (REVIEW), UNCERTAINTY_NOT_DECLARED (INVALID). Tier 2 uncertainty REQUIRED. PCC Sections 12-15 added. All 27 sheet section refs updated to v8.5.4 PATCHED. Terminology: "Union Scopes" adopted per v8.5.4 PATCHED. | D14: Claude-assisted
A15: v1.8.1-1.8.2 | B15: 2026-02-14/15 | C15: Internal development versions (v8.1→v8.5.4 PATCHED transition); not published.
A16: 1.6.2 | B16: 2026-02-02 | C16: CVaR algorithm fix (D.7 compliance), type hygiene, SSOT propagation, SC-24/25 added | D16: Claude-assisted
A17: 1.6.3 | B17: 2026-02-02 | C17: Schema enforcement, sanity check standardization, PCC cleanup, WTSL-AIX note, subgroup policy, sensitivity labeling, NONDECISIVE_GAP flag | D17: Claude-assisted
A18: 1.6.4 | B18: 2026-02-02 | C18: FINAL: Boolean→numeric, hardened schema, audit consistency, placeholders removed, publish-ready gate | D18: Claude-assisted
A19: 1.6.5 | B19: 2026-02-02 | C19: SSOT enforcement: computed flags, no hardcoded triggers, placeholder removal, TRC audit format, NCRC cleanup, conservative subgroup bound | D19: Claude-assisted
A20: 1.6.6 | B20: 2026-02-02 | C20: FINAL: Formula-based triggers, computed PASS/FAIL sanity, SSOT enforcement, placeholder eradication, τ_TRC linked, TEXTJOIN flags | D20: Claude-assisted
A21: 1.6.7 | B21: 2026-02-02 | C21: DEFINITIVE: All triggers/counts/gates are formulas, SSOT enforced, no typed values, manual override sentinel, Release Integrity Panel | D21: Claude-assisted
A22: 1.6.1 | B22: 2026-02-01 | C22: CLAIM-READY: C_cat filled; CVaR computed; type fixes; full SSOT
A23: 1.5.5 | B23: 2026-01-31 | C23: Computed Dashboard; TRC sorted scenarios
A24: 1.5.6 | B24: 2026-01-31 | C24: Audit_Flags computed formulas
A25: 1.5.7 | B25: 2026-02-01 | C25: Fixed Containment/RANK formulas; full computed Audit_Flags; error-free
A26: 1.5.8 | B26: 2026-02-01 | C26: Claim-ready: +PROC right; fixed Containment refs; σ_est toggle; Sanity Checklist; blank=INVALID
A27: Mandatory Tails | B27: ="✓ PASS ("&CANON!B41&"/"&CANON!B41&")" -> ✓ PASS (5/5)
A28: p_floor (≥0.02) | B28: ✓ PASS
A29: Containment | B29: ✓ PASS (vacuous)
A30: RLS | B30: ✓ PASS (computed)
A31: PCC | B31: ✓ PASS (with 5SPR)
A32: Audit Flags | B32: ✓ PASS (NONDECISIVE_GAP_REVIEW active)
A33: OVERALL | B33: ✓ TIER 2 CONFORMANT
A34: v1.7.3 | B34: 2026-02-03 | C34: PUBLISH_FINAL: Fixed MINIFS compatibility (140), wrapped TRC IFERROR, unified version labels, bracket policy clarified
A35: v1.7.3 | B35: 2026-02-03 | C35: RC_POLISH: reconciled version ids; clarified containment as Tier-2 proxy; improved SUBGROUP_LIMITATION trigger (analysis-aware); updated σ_est policy note | D35: Claude+GPT-assisted
A36: v1.7.5 | B36: 2026-02-04 | C36: PUBLISH_HARDEN: Fixed NCRC Min_I_rights calc (AGGREGATE), PCC Section 7 + 5SPR auto-pulls Audit_Flags, removed header version drift, clarified overrides vs audit flag, mandatory tails display links to CANON. | D36: GPT-assisted
A37: v1.7.9 | B37: 2026-02-04 | C37: FINAL_HARDEN: aligned RLS decisiveness display with Gap/√(2σ²+ε); PCC mitigation reframed as qualitative + headroom; added TRC outputs populated sanity check; fixed placeholder check reference. | D37: GPT-assisted
A38: v1.8.0 | B38: 2026-02-13 | C38: CANON RE-PIN: Framework→Ripple_Logic v8.5.4 PATCHED, SGP→v4.2.3. τ(t) corrected to MIN(1,LN(1+MAX(t,t_min))/LN(1+T_ref)) with t_min=0.083 per v8.5.4 PATCHED Appendix B.1. All 27 sheet section refs updated. Stewardship block added to PCC. UCI E₁=1 verified. Config date updated. | D38: Claude-assisted
A40: TIER 3 READINESS CHECKLIST
A41: ☐ Expand scenarios to ≥20 (currently 7)
A42: ☐ Complete sensitivity analysis
A43: ☐ Independent reviewer sign-off
A44: ☐ Full subgroup enumeration
A45: ☐ Add kernel with KQS (if QUICK mode)
A46: ☐ UCI from structural indicators
A47: ☐ Uncertainty quantification (σ values)
A49: KNOWN LIMITATIONS (v1.5)
A50: Normal cascade complete; RLS non-decisive requires judgment call
A51: 2. Scenario count (7) above Tier 2 min but below Tier 3
A52: 3. UCI values = evaluator assessment, not structural indicators
... A54: 5. Kernel not used (NONE mode) - appropriate for Tier 2
A55: PATCH_NOTE | B55: Added explicit PCC BaselineType_Welfare = STATUS_QUO and reference lines (restoring v1.8.4 clarity).
A56: PATCH_TIMESTAMP_UTC | B56: 2026-02-20T13:28:45Z
